[{"index": 1, "page": [{"bbox_text": [[259.0, 30.0, 889.0, 60.0]], "bbox_layout": [250.859375, 26.14501953125, 899.765625, 71.6943359375], "text": ["CONVENTIONS ET ACCORDS INTERNATIONAUX"], "label": "SectionHeader", "position": 0}, {"bbox_text": [[64.0, 105.0, 559.0, 119.0], [95.0, 122.0, 559.0, 135.0], [93.0, 138.0, 559.0, 151.0], [94.0, 156.0, 558.0, 169.0], [93.0, 171.0, 397.0, 186.0]], "bbox_layout": [53.984375, 94.50439453125, 573.28125, 197.98828125], "text": ["Ordonnance n\u00ba 65-194 du 29 juillet 1965 portant ratification", "de la convention relative \u00e0 l'exequatur et \u00e0 l'extradition", "entre l'Alg\u00e9rie et la France et de l'echange de lettres", "relatives \u00e0 la modification du protocole judiciaire alg\u00e9ro-", "fran\u00e7ais du 28 ao\u00fbt 1962 (rectificatif)."], "label": "Text", "position": 1}, {"bbox_text": [[70.0, 217.0, 559.0, 231.0]], "bbox_layout": [61.3671875, 207.2119140625, 568.0859375, 241.2255859375], "text": [" Journal officies n\u00ba 68 du 17 ao\u00fbt 1965, page 758, 2\u00e8me colonne."], "label": "Text", "position": 2}, {"bbox_text": [[77.0, 247.0, 559.0, 262.0], [63.0, 263.0, 559.0, 277.0], [63.0, 282.0, 564.0, 296.0]], "bbox_layout": [54.94140625, 238.486328125, 571.640625, 304.970703125], "text": ["Lettre de l'ambassadeur, haut representant de la France", "en Alg\u00e9rie a Monsieur Mohammed El Hadi Hadi Sma\u00efne.", "ministre de la justice, garde des sceaux, en date du 27 ao\u00fbt 1964."], "label": "Text", "position": 3}, {"bbox_text": [[596.0, 104.0, 1076.0, 124.0], [581.0, 122.0, 830.0, 138.0]], "bbox_layout": [572.421875, 97.06787109375, 1092.265625, 148.51318359375], "text": ["Article 17 du protocole judiciaire franco-alg\u00e9rien du 28 ao\u00fbt", "1962, deuxi\u00e8me alin\u00e9a, in fine."], "label": "Text", "position": 4}, {"bbox_text": [[581.0, 151.0, 681.0, 165.0]], "bbox_layout": [574.609375, 143.89404296875, 700.703125, 177.39501953125], "text": ["Au lieu de :"], "label": "Text", "position": 5}, {"bbox_text": [[597.0, 180.0, 1077.0, 200.0], [580.0, 196.0, 977.0, 218.0], [580.0, 222.0, 628.0, 235.0]], "bbox_layout": [569.6875, 172.3486328125, 1091.71875, 235.7568359375], "text": ["... par d\u00e9claration orale ou par lettre recommand\u00e9e avec", "accus\u00e9 de r\u00e9ception enregistr\u00e9es au greffe de la", "Lire :"], "label": "Text", "position": 6}, {"bbox_text": [[580.0, 222.0, 628.0, 235.0]], "bbox_layout": [577.890625, 219.1748046875, 644.921875, 250.7958984375], "text": ["Lire :"], "label": "Text", "position": 7}, {"bbox_text": [[597.0, 248.0, 1077.0, 267.0], [580.0, 266.0, 1077.0, 284.0], [578.0, 283.0, 629.0, 296.0]], "bbox_layout": [569.6875, 240.0244140625, 1091.71875, 304.1162109375], "text": ["... par d\u00e9claration orale ou par lettre recommand\u00e9e avec", "accus\u00e9 de r\u00e9ception enregistr\u00e9e au greffe de la juridiation", "saisie."], "label": "Text", "position": 8}, {"bbox_text": [[259.0, 384.0, 880.0, 415.0]], "bbox_layout": [251.953125, 379.6484375, 897.578125, 426.9921875], "text": ["DECRETS, ARRETES, DECISIONS ET CIRCULAIRES"], "label": "SectionHeader", "position": 9}, {"bbox_text": [[62.0, 535.0, 558.0, 553.0], [93.0, 551.0, 252.0, 568.0]], "bbox_layout": [52.48046875, 526.62109375, 572.734375, 578.75], "text": ["D\u00e9crets des 9, 19 et 23 aout 1965 portant mouvement dans le", "corps pr\u00e9fectoral"], "label": "SectionHeader", "position": 11}, {"bbox_text": [[77.0, 597.0, 557.0, 617.0], [62.0, 614.0, 558.0, 634.0], [62.0, 629.0, 557.0, 651.0], [62.0, 649.0, 121.0, 662.0]], "bbox_layout": [51.5234375, 591.220703125, 571.09375, 673.427734375], "text": ["Par d\u00e9cret du 9 ao\u00fbt 1965, il est mis fin, \u00e0 compter du", "1\u00bar ao\u00fbt 1965, \u00e0 la d\u00e9l\u00e9gation de M. Bachir Bourghoud dans", "les fonctions de sous-pr\u00e9fet, chef de cabinet du pr\u00e9fet d'El-", "Asnam."], "label": "Text", "position": 12}, {"bbox_text": [[75.0, 695.0, 556.0, 715.0], [62.0, 713.0, 557.0, 732.0], [61.0, 731.0, 121.0, 744.0]], "bbox_layout": [51.66015625, 684.873046875, 570.0, 754.43359375], "text": ["Par d\u00e9cret du 9 ao\u00fbt 1967 M. Bachir Bourghoud est d\u00e9l\u00e9gu\u00e9,", "\u00e0 compter du 1\u00bar ao\u00fbt 1965, dans les fonctions de sous-pr\u00e9fet", "d'Alger."], "label": "Text", "position": 13}, {"bbox_text": [[75.0, 784.0, 556.0, 799.0], [59.0, 798.0, 556.0, 817.0], [59.0, 816.0, 132.0, 830.0]], "bbox_layout": [50.29296875, 774.08203125, 568.359375, 841.93359375], "text": ["Par d\u00e9cret du 9 ao\u00fbt 1965, M. Tahar Boucif est d\u00e9l\u00e9gu\u00e9,", "\u00e0 compter du 1\u00bar ao\u00fbt 1965, dans les fonctions de sous-pr\u00e9fet", "de Blida."], "label": "Text", "position": 14}, {"bbox_text": [[75.0, 873.0, 556.0, 890.0], [61.0, 887.0, 554.0, 908.0], [60.0, 907.0, 396.0, 921.0]], "bbox_layout": [50.703125, 865.0, 567.8125, 931.484375], "text": ["Par d\u00e9cret du 19 ao\u00fbt 1965, il est mis fin, \u00e0 compter du", "22 juille: 1965, \u00e0 la d\u00e9l\u00e9gation de M. Mohamed Ait Amrane,", "dans les fonctions de pr\u00e9fet d'El-Asnam."], "label": "Text", "position": 15}, {"bbox_text": [[73.0, 961.0, 555.0, 979.0]], "bbox_layout": [69.0234375, 952.5, 566.4453125, 987.5390625], "text": ["Le Chef du Gouvernement, Pr\u00e9sident du Conseil des ministres,"], "label": "Text", "position": 16}, {"bbox_text": [[75.0, 990.0, 556.0, 1008.0], [60.0, 1008.0, 476.0, 1024.0]], "bbox_layout": [51.11328125, 981.2109375, 565.625, 1031.2890625], "text": ["Vu le d\u00e9cret n\u00ba 62-50. du 19 juillet 1962 fixant les conditions", "de nomination de certains hauts fonctionnaires ;"], "label": "Text", "position": 17}, {"bbox_text": [[74.0, 1036.0, 438.0, 1053.0]], "bbox_layout": [67.3828125, 1027.6953125, 454.0625, 1061.3671875], "text": ["Sur proposition du ministre de l'int\u00e9rieur ;"], "label": "Text", "position": 18}, {"bbox_text": [[149.0, 1066.0, 224.0, 1080.0]], "bbox_layout": [141.484375, 1056.40625, 239.140625, 1090.078125], "text": ["D\u00e9cr\u00e8te :"], "label": "Text", "position": 19}, {"bbox_text": [[74.0, 1093.0, 554.0, 1113.0], [58.0, 1111.0, 553.0, 1128.0]], "bbox_layout": [51.25, 1085.80078125, 568.359375, 1135.87890625], "text": ["Article 1\u00bar. - M. Mohamed Nedjadi est d\u00e9l\u00e9gu\u00e9, \u00e0 compter", "du 27 juillet 1965, dans les fonctions de pr\u00e9fet d'El-Asnam."], "label": "Text", "position": 20}, {"bbox_text": [[73.0, 1139.0, 554.0, 1160.0], [58.0, 1158.0, 555.0, 1175.0], [56.0, 1173.0, 460.0, 1192.0]], "bbox_layout": [49.47265625, 1130.91796875, 565.625, 1198.76953125], "text": ["Art. 2. - Le ministre de l'int\u00e9rieur est charge de l'ex\u00e9cution", "du pr\u00e9sent d\u00e9cret qui sera publi\u00e9 au Journal officiel de la", "R\u00e9publique alg\u00e9rienne d\u00e9mocratique et populaire."], "label": "Text", "position": 21}, {"bbox_text": [[72.0, 1202.0, 327.0, 1219.0]], "bbox_layout": [65.46875, 1193.80859375, 338.9453125, 1227.48046875], "text": ["Fait \u00e0 Alger, le 19 ao\u00fbt 1965."], "label": "Text", "position": 22}, {"bbox_text": [[211.0, 1232.0, 396.0, 1247.0]], "bbox_layout": [200.546875, 1222.51953125, 410.3125, 1256.19140625], "text": ["Houari BOUMEDIENE."], "label": "Text", "position": 23}, {"bbox_text": [[70.0, 1288.0, 553.0, 1307.0]], "bbox_layout": [63.69140625, 1280.625, 565.625, 1315.6640625], "text": ["Le Chef du Gouvernement, Pr\u00e9sident du Conseil des ministres,"], "label": "Text", "position": 24}, {"bbox_text": [[72.0, 1324.0, 552.0, 1342.0], [56.0, 1340.0, 472.0, 1359.0]], "bbox_layout": [51.93359375, 1312.75390625, 564.53125, 1366.93359375], "text": ["Vu le d\u00e9cret n\u00ba 62-502 du 19 juillet 1962 fixant les conditions", "de nomination de certains hauts fonctionnaires ;"], "label": "Text", "position": 25}, {"bbox_text": [[70.0, 1377.0, 436.0, 1394.0]], "bbox_layout": [62.87109375, 1368.80859375, 450.78125, 1402.48046875], "text": ["Sur proposition du ministre de l'int\u00e9rieur ;"], "label": "Text", "position": 26}, {"bbox_text": [[671.0, 479.0, 747.0, 493.0]], "bbox_layout": [654.453125, 470.56640625, 760.859375, 504.23828125], "text": ["D\u00e9cr\u00e8te :"], "label": "SectionHeader", "position": 27}, {"bbox_text": [[596.0, 508.0, 1076.0, 527.0], [581.0, 524.0, 1076.0, 543.0], [581.0, 542.0, 1046.0, 559.0]], "bbox_layout": [570.78125, 499.9609375, 1090.625, 567.8125], "text": ["Article 1\u00bar. - M. Abdelghani Akbi, pr\u00e9c\u00e9demment d\u00e9l\u00e9gu\u00e9", "dans les 'fonctions de pr\u00e9fet de Batna, est d\u00e9l\u00e9gu\u00e9, \u00e0 compter", "du 22 juillet 1965, dans les fonctions de pr\u00e9fet d'Oran."], "label": "Text", "position": 28}, {"bbox_text": [[596.0, 570.0, 1076.0, 589.0], [580.0, 589.0, 1077.0, 605.0], [579.0, 605.0, 986.0, 622.0]], "bbox_layout": [570.234375, 564.560546875, 1090.078125, 632.412109375], "text": ["Art. 2. - Le ministre de l'int\u00e9rieur est charg\u00e9 de l'ex\u00e9cution", "du pr\u00e9sent d\u00e9cret qui sera publi\u00e9 au Journal officiel de la", "R\u00e9publique alg\u00e9rienne d\u00e9mocratique et populaire."], "label": "Text", "position": 29}, {"bbox_text": [[595.0, 635.0, 850.0, 649.0]], "bbox_layout": [589.375, 627.109375, 855.46875, 660.78125], "text": ["Fait \u00e0 Alger, le 19 ao\u00fbt 1965."], "label": "Text", "position": 30}, {"bbox_text": [[734.0, 665.0, 919.0, 679.0]], "bbox_layout": [726.640625, 655.478515625, 934.765625, 688.466796875], "text": ["Houari BOUMEDIENE,"], "label": "SectionHeader", "position": 31}, {"bbox_text": [[593.0, 713.0, 1075.0, 733.0]], "bbox_layout": [580.078125, 705.72265625, 1085.703125, 739.39453125], "text": ["Le Chef du Gouvernement, Pr\u00e9sident du Conseil des ministres,"], "label": "Text", "position": 32}, {"bbox_text": [[592.0, 750.0, 1077.0, 768.0], [577.0, 766.0, 968.0, 784.0]], "bbox_layout": [569.140625, 741.953125, 1088.984375, 792.03125], "text": ["Vu le d\u00e9cret n\u00ba 62-502 du 19 juillet 1962 fixant les conditions", "de nomination de certains hauts fonctionnaires."], "label": "Text", "position": 33}, {"bbox_text": [[592.0, 803.0, 948.0, 817.0]], "bbox_layout": [585.546875, 793.90625, 963.203125, 827.578125], "text": ["Sur proposition du ministre de l'int\u00e9rieur."], "label": "Text", "position": 34}, {"bbox_text": [[670.0, 845.0, 745.0, 859.0]], "bbox_layout": [662.65625, 834.921875, 762.5, 868.59375], "text": ["D\u00e9cr\u00e8te :"], "label": "Text", "position": 35}, {"bbox_text": [[592.0, 885.0, 1080.0, 905.0], [577.0, 902.0, 1075.0, 921.0]], "bbox_layout": [573.515625, 877.98828125, 1088.984375, 929.43359375], "text": ["Article 1\u00ba . - M. Abdelaziz Ouhibi est d\u00e9l\u00e9gu\u00e9, \u00e0 compter", "du 19 juin 1965, dans les fonctions de pr\u00e9fet de Sa\u00efda."], "label": "Text", "position": 36}, {"bbox_text": [[592.0, 940.0, 1074.0, 954.0], [576.0, 954.0, 1073.0, 974.0], [576.0, 971.0, 974.0, 988.0]], "bbox_layout": [569.140625, 929.2578125, 1086.796875, 997.109375], "text": ["Art. 2. - Le ministre de l'int\u00e9rieur est charg\u00e9 de l'ex\u00e9cution", "du pr\u00e9sent d\u00e9cret qui sera publi\u00e9 au Journal officiel de la", "R\u00e9publique alg\u00e9rienne d\u00e9mocratique et populaire."], "label": "Text", "position": 37}, {"bbox_text": [[592.0, 1002.0, 847.0, 1016.0]], "bbox_layout": [586.09375, 991.46484375, 858.75, 1025.13671875], "text": ["Fait \u00e0 Alger, le 19 ao\u00fbt 1965."], "label": "Text", "position": 38}, {"bbox_text": [[730.0, 1030.0, 918.0, 1045.0]], "bbox_layout": [723.359375, 1021.54296875, 931.484375, 1055.21484375], "text": ["Houari BOUMEDIENE."], "label": "Text", "position": 39}, {"bbox_text": [[589.0, 1086.0, 1072.0, 1104.0]], "bbox_layout": [575.15625, 1076.9140625, 1084.0625, 1111.953125], "text": ["Le Chef du Gouvernement, Pr\u00e9sident du Conseil des ministres,"], "label": "Text", "position": 40}, {"bbox_text": [[591.0, 1115.0, 1072.0, 1134.0], [576.0, 1132.0, 994.0, 1150.0]], "bbox_layout": [573.515625, 1107.67578125, 1085.703125, 1159.12109375], "text": ["Vu le d\u00e9cret n\u00ba 62-502 du 19 juillet 1962 fixant les conditions", "de nomination de certains hauts fonctionnaires ;"], "label": "Text", "position": 41}, {"bbox_text": [[590.0, 1162.0, 957.0, 1177.0]], "bbox_layout": [581.171875, 1153.4765625, 963.203125, 1187.1484375], "text": ["Sur proposition du ministre de l'int\u00e9rieur ;"], "label": "Text", "position": 42}, {"bbox_text": [[666.0, 1197.0, 742.0, 1211.0]], "bbox_layout": [661.5625, 1187.65625, 757.03125, 1221.328125], "text": ["D\u00e9cr\u00e8te :"], "label": "SectionHeader", "position": 43}, {"bbox_text": [[591.0, 1224.0, 1071.0, 1243.0], [574.0, 1241.0, 1072.0, 1260.0], [574.0, 1258.0, 623.0, 1274.0]], "bbox_layout": [566.40625, 1217.05078125, 1085.15625, 1286.26953125], "text": ["Article 1\u00bar. - M. Mohamed Moulasserdoun est d\u00e9l\u00e9gu\u00e9, \u00e0", "compter du 26 juillet 1965 dans les fonctions de pr\u00e9fet de", "Sa\u00efda."], "label": "Text", "position": 44}, {"bbox_text": [[590.0, 1290.0, 1072.0, 1304.0], [574.0, 1303.0, 1071.0, 1322.0], [574.0, 1323.0, 979.0, 1337.0]], "bbox_layout": [566.40625, 1280.625, 1086.25, 1347.109375], "text": ["Art. 2. - Le ministre de l'int\u00e9rieur est charg\u00e9 de l'ex\u00e9cution", "du pr\u00e9sent d\u00e9cret qui sera publi\u00e9 au Journal officiel de la", "R\u00e9publique alg\u00e9rienne d\u00e9mocratique et populaire."], "label": "Text", "position": 45}, {"bbox_text": [[728.0, 1380.0, 916.0, 1395.0]], "bbox_layout": [706.953125, 1368.80859375, 931.484375, 1403.84765625], "text": ["Houari BOUMEDIENE."], "label": "Text", "position": 47}]}, {"index": 2, "page": [{"bbox_text": [[56.0, 17.0, 537.0, 31.0], [43.0, 33.0, 537.0, 49.0], [42.0, 49.0, 415.0, 67.0]], "bbox_layout": [32.109375, 6.49169921875, 558.515625, 80.538330078125], "text": ["Par d\u00e9cret du 19 ao\u00fbt 1965, il est mis fin, \u00e0 compter", "du 26 juillet 1965, \u00e0 la d\u00e9l\u00e9gation de M. Kader Kalache", "dans les fonctions de pr\u00e9fet de Constantine."], "label": "Text", "position": 0}, {"bbox_text": [[55.0, 96.0, 535.0, 112.0]], "bbox_layout": [40.44921875, 87.2412109375, 549.21875, 122.79296875], "text": ["Le Chef du Gouvernement, Pr\u00e9sident du Conseil des ministres,"], "label": "Text", "position": 1}, {"bbox_text": [[56.0, 125.0, 537.0, 142.0], [41.0, 140.0, 458.0, 158.0]], "bbox_layout": [31.42578125, 116.9775390625, 548.671875, 169.9609375], "text": ["Vu le d\u00e9cret n\u00ba 62-502 du 19 juillet 1962 fixant les conditions", "de nomination de certains hauts fonctionnaires ;"], "label": "Text", "position": 2}, {"bbox_text": [[56.0, 168.0, 420.0, 189.0]], "bbox_layout": [52.34375, 163.20556640625, 429.1796875, 197.8173828125], "text": ["Sur proposition du ministre de l'int\u00e9rieur ;"], "label": "Text", "position": 3}, {"bbox_text": [[130.0, 199.0, 207.0, 213.0]], "bbox_layout": [102.109375, 190.1220703125, 228.203125, 223.7939453125], "text": ["D\u00e9cr\u00e8te :"], "label": "Text", "position": 4}, {"bbox_text": [[116.0, 229.0, 535.0, 246.0], [56.0, 231.0, 111.0, 243.0], [42.0, 244.0, 535.0, 265.0], [40.0, 262.0, 537.0, 281.0], [40.0, 280.0, 138.0, 294.0]], "bbox_layout": [30.46875, 219.8583984375, 550.859375, 304.7998046875], "text": ["19r. - M. Mohamed Kadi, pr\u00e9c\u00e9demment d\u00e9l\u00e9gu\u00e9", "Article", "dans les fonctions de pr\u00e9fet de Mostaganem, est d\u00e9l\u00e9gu\u00e9, \u00e0", "compter du 26 juillet 1965, dans les fonctions de pr\u00e9fet de", "Constantine."], "label": "Text", "position": 5}, {"bbox_text": [[57.0, 310.0, 537.0, 324.0], [41.0, 325.0, 536.0, 344.0], [40.0, 342.0, 443.0, 360.0]], "bbox_layout": [30.87890625, 301.71875, 548.671875, 368.88671875], "text": ["Art. 2. - Le ministre de l'int\u00e9rieur est charg\u00e9 de l'ex\u00e9cution", "du pr\u00e9sent d\u00e9cret qui sera rubli\u00e9 au Journal officiel de la", "R\u00e9publique alg\u00e9rienne d\u00e9mocratique et populaire."], "label": "Text", "position": 6}, {"bbox_text": [[56.0, 372.0, 310.0, 387.0]], "bbox_layout": [50.01953125, 362.216796875, 323.90625, 395.888671875], "text": ["Fait \u00e0 Alger, le 19 ao\u00fbt 1965."], "label": "Text", "position": 7}, {"bbox_text": [[196.0, 402.0, 384.0, 416.0]], "bbox_layout": [191.5234375, 392.63671875, 391.4453125, 426.30859375], "text": ["Houari BOUMEDIENE."], "label": "SectionHeader", "position": 8}, {"bbox_text": [[56.0, 447.0, 536.0, 465.0], [41.0, 462.0, 534.0, 481.0], [41.0, 480.0, 365.0, 497.0]], "bbox_layout": [31.015625, 437.412109375, 550.859375, 506.630859375], "text": ["Par d\u00e9cret du 19 ao\u00fbt 1965, il est mis fin, \u00e0 compter du", "5 d\u00e9cembre 1964, \u00e0 la d\u00e9l\u00e9gation de M. Abdelkader Maachou", "dans les fonctions de pr\u00e9fet des Oasis."], "label": "Text", "position": 9}, {"bbox_text": [[56.0, 526.0, 537.0, 545.0], [40.0, 541.0, 535.0, 563.0], [40.0, 560.0, 363.0, 577.0]], "bbox_layout": [30.1953125, 518.076171875, 547.3046875, 588.662109375], "text": ["Par d\u00e9cret du 19 ao\u00fbt 1965, il est mis fin, \u00e0 compter du", "6 avril 1965, \u00e0 la del\u00e9gation de M. Abderrahmane Bendjaber", "dans les fonctions de pr\u00e9fet des Oasis."], "label": "Text", "position": 10}, {"bbox_text": [[55.0, 605.0, 535.0, 625.0]], "bbox_layout": [48.7890625, 596.689453125, 545.1171875, 631.728515625], "text": ["Le Chef du Gouvernement, Pr\u00e9sident du Conseil des ministres,"], "label": "Text", "position": 11}, {"bbox_text": [[56.0, 635.0, 537.0, 652.0], [41.0, 651.0, 456.0, 671.0]], "bbox_layout": [32.3828125, 626.42578125, 548.9453125, 677.87109375], "text": ["Vu le d\u00e9cret n\u00ba 62-502 du 19 juillet 1962 fixant les conditions", "de nomination de certains hauts fonctionnaires ;"], "label": "Text", "position": 12}, {"bbox_text": [[56.0, 681.0, 420.0, 698.0]], "bbox_layout": [49.8828125, 671.884765625, 434.375, 706.240234375], "text": ["Sur proposition du ministre de l'int\u00e9rieur ;"], "label": "Text", "position": 13}, {"bbox_text": [[131.0, 710.0, 206.0, 724.0]], "bbox_layout": [121.25, 700.25390625, 216.4453125, 733.92578125], "text": ["D\u00e9crete :"], "label": "Text", "position": 14}, {"bbox_text": [[56.0, 738.0, 535.0, 755.0], [41.0, 755.0, 462.0, 773.0]], "bbox_layout": [30.33203125, 729.6484375, 550.859375, 781.09375], "text": ["Article 1\u00bar. - M. Abdallah Fadel est d\u00e9legu\u00e9, \u00e0 compter du", "8 juin 1965, dans les fonctions de pr\u00e9fet des Oasis."], "label": "Text", "position": 15}, {"bbox_text": [[57.0, 786.0, 535.0, 800.0], [40.0, 800.0, 534.0, 820.0], [41.0, 817.0, 442.0, 836.0]], "bbox_layout": [29.78515625, 776.1328125, 547.03125, 843.984375], "text": ["Art 2. - Le ministre de l'interieur est charge de l'ex\u00e9cution", "du pr\u00e9sent d\u00e9cret qui sera publi\u00e9 au Journal officiel de la", "R\u00e9publique alg\u00e9rienne d\u00e9mocratique et populaire."], "label": "Text", "position": 16}, {"bbox_text": [[56.0, 848.0, 308.0, 863.0]], "bbox_layout": [50.29296875, 836.97265625, 323.90625, 870.64453125], "text": ["Fait \u00e0 Alger, le 19 ao\u00fbt 1965."], "label": "Text", "position": 17}, {"bbox_text": [[194.0, 877.0, 378.0, 892.0]], "bbox_layout": [188.2421875, 867.734375, 391.4453125, 902.7734375], "text": ["Houari BOUMEDIENE."], "label": "Text", "position": 18}, {"bbox_text": [[55.0, 929.0, 534.0, 946.0], [40.0, 943.0, 534.0, 964.0], [37.0, 963.0, 98.0, 976.0]], "bbox_layout": [28.0078125, 917.63671875, 548.9453125, 986.85546875], "text": ["Par d\u00e9cret du 19 ao\u00fbt 1965, M Mohamed Harti est d\u00e9l\u00e9gue,", "\u00e0 compter du 10 avril 1965, dans les fonctions de sous-pr\u00e9fet", "d'Alger."], "label": "Text", "position": 19}, {"bbox_text": [[55.0, 1008.0, 535.0, 1025.0], [39.0, 1022.0, 535.0, 1042.0], [38.0, 1041.0, 333.0, 1057.0]], "bbox_layout": [29.1015625, 997.6171875, 547.3046875, 1069.5703125], "text": ["Par d\u00e9cret du 19 ao\u00fbt 1965, il est mis fin, \u00e0 compter du", "1er ao\u00fbt 1965, \u00e0 la d\u00e9l\u00e9gation de M. Mohamed Harti, dans", "les fonctions de sous-pr\u00e9fet d'Alger."], "label": "Text", "position": 20}, {"bbox_text": [[54.0, 1087.0, 534.0, 1104.0], [40.0, 1103.0, 69.0, 1116.0], [68.0, 1103.0, 534.0, 1120.0], [40.0, 1122.0, 399.0, 1136.0]], "bbox_layout": [29.921875, 1077.59765625, 547.03125, 1148.18359375], "text": ["Par d\u00e9cret du 19 ao\u00fbt 1965, il est mis fin, \u00e0 compter du", "lor", "ao\u00fbt 1965, \u00e0 la d\u00e9l\u00e9gation de Tedjini Bachir Bouiadjra", "dans les fonctions de sous-pr\u00e9fet de Blida."], "label": "Text", "position": 21}, {"bbox_text": [[55.0, 1167.0, 534.0, 1183.0], [40.0, 1182.0, 534.0, 1199.0], [39.0, 1201.0, 399.0, 1215.0]], "bbox_layout": [29.1015625, 1156.2109375, 545.6640625, 1229.53125], "text": ["Par d\u00e9cret du 19 juillet 1965, il est mis fin, \u00e0 compter du", "27 juillet 1965, \u00e0 la d\u00e9l\u00e9gation de M. Mohamed Nedjadi", "dans les fonctions de sous-pr\u00e9fet de l'\u00e9n\u00e8s."], "label": "Text", "position": 22}, {"bbox_text": [[53.0, 1244.0, 533.0, 1263.0], [40.0, 1261.0, 532.0, 1277.0], [39.0, 1277.0, 533.0, 1296.0], [39.0, 1296.0, 406.0, 1308.0]], "bbox_layout": [28.828125, 1235.5078125, 547.578125, 1322.5], "text": ["Par decret du 19 ao\u00fbt 1965, M. Benyoucef Boumehdi,", "pr\u00e9c\u00e9dement d\u00e9l\u00e9gu\u00e9 dans les fonctions de sous-pr\u00e9fet d'El-", "Abiodh-Sidi-Cheikh, est d\u00e9l\u00e9gue, \u00e0 compter du 20 f\u00e9vrier 1965,", "dans les fonctions de sous-pr\u00e9fet d'El-Asnam."], "label": "Text", "position": 23}, {"bbox_text": [[52.0, 1350.0, 534.0, 1367.0], [37.0, 1369.0, 534.0, 1383.0], [39.0, 1386.0, 411.0, 1398.0]], "bbox_layout": [27.05078125, 1339.4140625, 547.03125, 1410.0], "text": ["Par d\u00e9cret du 19 ao\u00fbt 1965 il est mis fin, \u00e0 compter du", "26 juillet 1965, \u00e0 la d\u00e8l\u00e9gation de M. Mohamed Moulasserdoun", "dans les fonctions de sous-prefet de Tlemcen."], "label": "Text", "position": 24}, {"bbox_text": [[573.0, 18.0, 1052.0, 33.0], [559.0, 34.0, 1056.0, 51.0], [559.0, 52.0, 1056.0, 68.0], [559.0, 68.0, 789.0, 82.0]], "bbox_layout": [554.921875, 7.901611328125, 1068.203125, 90.706787109375], "text": ["Par d\u00e9cret du 19 ao\u00fbt 1965, M. Abdallah Chami, pr\u00e9c\u00e9dem-", "ment d\u00e9l\u00e9gu\u00e9 dans les fonctions de sous-pr\u00e9fet de Beni-Saf,", "est d\u00e9l\u00e9gu\u00e9, \u00e0 compter du 3 ao\u00fbt 1965, dans les fonctions", "de sous-pr\u00e9fet de Tlemcen,"], "label": "Text", "position": 25}, {"bbox_text": [[614.0, 119.0, 860.0, 136.0], [574.0, 121.0, 612.0, 130.0], [868.0, 122.0, 955.0, 136.0], [957.0, 123.0, 1053.0, 136.0], [559.0, 136.0, 1054.0, 153.0], [559.0, 154.0, 740.0, 168.0]], "bbox_layout": [548.90625, 110.654296875, 1066.5625, 178.84765625], "text": ["d\u00e9cret du 19 ao\u00fbt 1965, M.", "Par", "Mustapha", "Lalaoui est", "d\u00e9l\u00e9gu\u00e9, \u00e0 compter du 5 ao\u00fbt 1965, dans les fonctions de", "sous-pr\u00e9fet de T\u00e9lagh."], "label": "Text", "position": 26}, {"bbox_text": [[574.0, 205.0, 1053.0, 221.0], [629.0, 221.0, 1054.0, 238.0], [560.0, 222.0, 617.0, 233.0], [559.0, 240.0, 1054.0, 254.0], [559.0, 253.0, 769.0, 271.0]], "bbox_layout": [546.71875, 194.39453125, 1070.9375, 281.38671875], "text": ["Par d\u00e9cret du 19 ao\u00fbt 1965, M. Sadok Agli, pr\u00e9c\u00e9demment", "dans les fonctions de sous-pr\u00e9fet de Djanet, est", "d\u00e9l\u00e9gu\u00e9", "d\u00e9l\u00e9gu\u00e9. \u00e0 compter du 1\u00ba janvier 1965, dans les fonctions", "de sous-pr\u00e9fet d'El-Goi\u00e9a."], "label": "Text", "position": 27}, {"bbox_text": [[573.0, 326.0, 1054.0, 341.0]], "bbox_layout": [559.296875, 315.9033203125, 1064.921875, 350.9423828125], "text": ["Le Chef du Gouvernement, Pr\u00e9sident du Conseil des ministres,"], "label": "Text", "position": 28}, {"bbox_text": [[574.0, 357.0, 1053.0, 371.0], [559.0, 370.0, 950.0, 388.0]], "bbox_layout": [551.09375, 345.126953125, 1067.65625, 397.255859375], "text": ["Vu le d\u00e9cret n\u00ba 62-502 du 19 juillet 1962 fixant les conditions", "de nomination de certains hauts fonctionnaires,"], "label": "Text", "position": 29}, {"bbox_text": [[573.0, 400.0, 925.0, 418.0]], "bbox_layout": [563.671875, 391.26953125, 939.140625, 425.625], "text": ["Sur proposition du ministre de l'int\u00e9rieur,"], "label": "Text", "position": 30}, {"bbox_text": [[652.0, 430.0, 726.0, 444.0]], "bbox_layout": [618.90625, 420.6640625, 750.46875, 453.65234375], "text": ["D\u00e9cr\u00e8te :"], "label": "Text", "position": 31}, {"bbox_text": [[574.0, 459.0, 665.0, 472.0], [696.0, 459.0, 1053.0, 477.0], [559.0, 474.0, 1054.0, 494.0], [559.0, 493.0, 822.0, 508.0]], "bbox_layout": [550.546875, 449.375, 1068.203125, 517.91015625], "text": ["Article 1\u00bar.", "M. Mohamed Sadek Benyahia est d\u00e9l\u00e9gu\u00e9,", "\u00e0 compter du 20 juin 1965, dans les fonctions de pr\u00e9fet hors", "cadre au minist\u00e8re de l'int\u00e9rieur."], "label": "Text", "position": 32}, {"bbox_text": [[574.0, 522.0, 1055.0, 540.0], [559.0, 535.0, 1054.0, 559.0], [559.0, 556.0, 953.0, 572.0]], "bbox_layout": [549.7265625, 512.265625, 1068.75, 582.16796875], "text": ["Art. 2. - Le ministre de l'int\u00e9rieur est charge de l'ex\u00e9cution", "du pr\u00e9sent d\u00e9cret, qui sera publi\u00e9 au Journal officiel de la", "R\u00e9publique alg\u00e9rienne d\u00e9mocratique et populaire."], "label": "Text", "position": 33}, {"bbox_text": [[574.0, 583.0, 817.0, 601.0]], "bbox_layout": [565.859375, 575.15625, 826.484375, 609.51171875], "text": ["Fait \u00e0 Alger, le 23 ao\u00fbt 1965,"], "label": "Text", "position": 34}, {"bbox_text": [[714.0, 613.0, 901.0, 632.0]], "bbox_layout": [704.21875, 605.234375, 905.78125, 638.90625], "text": ["Houari BOUMEDIENE."], "label": "Text", "position": 35}, {"bbox_text": [[574.0, 678.0, 1053.0, 699.0], [559.0, 695.0, 1055.0, 714.0], [559.0, 710.0, 826.0, 728.0]], "bbox_layout": [550.0, 669.833984375, 1065.46875, 738.7109375], "text": ["Par d\u00e9cret du 23 ao\u00fbt 1965, li est mis fin, \u00e0 compter du", "19 juin 1965, \u00e0 la d\u00e9l\u00e9gation de M. Mohamed Dekhli dans", "les fonctions de pr\u00e9fet de Sa\u00efda."], "label": "Text", "position": 36}, {"bbox_text": [[574.0, 769.0, 1053.0, 788.0], [574.0, 791.0, 1054.0, 811.0], [559.0, 807.0, 974.0, 829.0]], "bbox_layout": [553.828125, 762.4609375, 1067.109375, 839.8828125], "text": ["Le Chef du Gouvernement, President du Conseil des ministres,", "Vu le d\u00e9cret n\u00ba 62-502 du 19 juillet 1962 fixant les conditions", "de nomination de certains hauts fonctionnaires ;"], "label": "Text", "position": 37}, {"bbox_text": [[573.0, 831.0, 938.0, 849.0]], "bbox_layout": [572.96875, 825.3515625, 952.8125, 860.390625], "text": ["Sur proposition du ministre de l'interieur ;"], "label": "Text", "position": 38}, {"bbox_text": [[648.0, 862.0, 724.0, 876.0]], "bbox_layout": [633.125, 852.6953125, 735.15625, 886.3671875], "text": ["D\u00e9cr\u00e8te :"], "label": "Text", "position": 39}, {"bbox_text": [[574.0, 892.0, 1053.0, 908.0], [559.0, 906.0, 1053.0, 927.0], [559.0, 924.0, 1053.0, 942.0]], "bbox_layout": [551.09375, 881.40625, 1065.46875, 947.890625], "text": ["Article 1\u00bar. - M. Abdelaziz Ouhibi, pr\u00e9c\u00e9demment d\u00e9l\u00e9gu\u00e9", "dans les fonctions de pr\u00e9fet de Sa\u00efda, est d\u00e9l\u00e9gu\u00e9, \u00e0 compter", "du 22 juillet 1965, dans les fonctions de pr\u00e9fet de l'iaret."], "label": "Text", "position": 40}, {"bbox_text": [[574.0, 952.0, 1053.0, 971.0], [558.0, 971.0, 1053.0, 988.0], [558.0, 985.0, 961.0, 1004.0]], "bbox_layout": [548.90625, 944.98046875, 1066.5625, 1011.46484375], "text": ["Art. 2. - Le ministre de l'interieur est charge de l'ex\u00e9cution", "du pr\u00e9sent d\u00e9cret qui sera publi\u00e9 au Journal officiel de la", "R\u00e9publique alg\u00e9rienne d\u00e9mocratique et populaire."], "label": "Text", "position": 41}, {"bbox_text": [[574.0, 1014.0, 817.0, 1032.0]], "bbox_layout": [561.484375, 1005.13671875, 826.484375, 1040.17578125], "text": ["Fait \u00e0 Alger, le 23 ao\u00fbt 1965,"], "label": "Text", "position": 42}, {"bbox_text": [[713.0, 1045.0, 895.0, 1060.0]], "bbox_layout": [702.03125, 1035.21484375, 900.3125, 1068.88671875], "text": ["Houari BOUMEDIENE."], "label": "Text", "position": 43}, {"bbox_text": [[572.0, 1099.0, 1053.0, 1113.0], [559.0, 1114.0, 1053.0, 1131.0], [556.0, 1131.0, 924.0, 1147.0]], "bbox_layout": [547.8125, 1086.484375, 1067.65625, 1158.4375], "text": ["Par d\u00e9cret du 23 ao\u00fbt 1965, il est mis fin, \u00e0 compter du", "1er ao\u00fbt 1965, \u00e0 la d\u00e9l\u00e9gation de M. Abdelhamid Bouzeliffa", "dans les fonctions de sous-pr\u00e9fet hors cadre."], "label": "Text", "position": 44}, {"bbox_text": [[573.0, 1184.0, 1053.0, 1199.0], [556.0, 1199.0, 1053.0, 1216.0], [556.0, 1216.0, 840.0, 1230.0]], "bbox_layout": [545.625, 1173.30078125, 1068.75, 1242.51953125], "text": ["Par d\u00e9cret du 23 ao\u00fbt 1965, il est mis fin, \u00e0 compter du", "9 juin 1965, \u00e0 la d\u00e9l\u00e9gation de M. Malek Cherifi dans les", "fonctions de sous-pr\u00e9fet de Beja\u00efa."], "label": "Text", "position": 45}, {"bbox_text": [[573.0, 1266.0, 1052.0, 1283.0], [556.0, 1284.0, 1052.0, 1300.0], [556.0, 1300.0, 640.0, 1314.0]], "bbox_layout": [551.09375, 1256.69921875, 1065.46875, 1327.28515625], "text": ["Par d\u00e9cret du 23 ao\u00fbt 1965, M. Youcef Kebache est d\u00e9l\u00e9gu\u00e9,", "\u00e0 compter du 24 juin 1965, dans les fonctions de sous-pr\u00e9fet", "de Beja\u00efa."], "label": "Text", "position": 46}, {"bbox_text": [[573.0, 1352.0, 1052.0, 1370.0], [556.0, 1368.0, 1053.0, 1387.0], [556.0, 1388.0, 783.0, 1398.0]], "bbox_layout": [547.8125, 1342.1484375, 1064.375, 1410.0], "text": ["Par decret du 23 ao\u00fbt 1965, M. Abdelhamid Bouzeliffa est", "d\u00e9l\u00e9gu\u00e9, \u00e0 compt\u00e8r du 1er ao\u00fbt 1965, dans les fonctions de", "sous-pr\u00e9fet de Dar-El-Beida."], "label": "Text", "position": 47}]}, {"index": 3, "page": [{"bbox_text": [[88.0, 23.0, 569.0, 32.0], [74.0, 40.0, 568.0, 48.0], [73.0, 58.0, 451.0, 66.0]], "bbox_layout": [65.87890625, 12.5372314453125, 590.78125, 81.35009765625], "text": ["Par d\u00e9cret du 23 ao\u00fbt 1965, il est mis fin, \u00e0 compter du", "1er ao\u00fbt 1965, \u00e0 la d\u00e9l\u00e9gation de M. Abdelkrim Bendaoud dans", "les fonctions de sous-pr\u00e9fet d'A\u00efn-T\u00e9mouchent."], "label": "Text", "position": 0}, {"bbox_text": [[76.0, 115.0, 571.0, 122.0], [106.0, 131.0, 217.0, 145.0]], "bbox_layout": [66.5625, 102.109375, 585.859375, 154.7509765625], "text": ["Arr\u00eat\u00e9s des 6 et 11 ao\u00fbt 1965 portant mouvement de personnel", "de pr\u00e9fecture."], "label": "Text", "position": 1}, {"bbox_text": [[88.0, 176.0, 570.0, 186.0], [75.0, 194.0, 570.0, 201.0], [77.0, 211.0, 237.0, 223.0]], "bbox_layout": [67.51953125, 162.265625, 586.953125, 233.53515625], "text": ["Par arr\u00eat\u00e9 du 6 ao\u00fbt 1965, M. Mohammed A\u00eft-Kaci est", "radi\u00e9 du cadre des secr\u00e9taires administratifs de pr\u00e9fecture", "(pr\u00e9fecture d'Alger)."], "label": "Text", "position": 2}, {"bbox_text": [[90.0, 239.0, 524.0, 248.0]], "bbox_layout": [80.09765625, 225.498046875, 537.1875, 260.87890625], "text": ["Ledit arr\u00eat\u00e9 prend effet \u00e0 compter du 4 juin 1964."], "label": "Text", "position": 3}, {"bbox_text": [[91.0, 286.0, 572.0, 293.0], [77.0, 303.0, 572.0, 311.0], [77.0, 321.0, 572.0, 327.0], [77.0, 336.0, 399.0, 347.0]], "bbox_layout": [68.4765625, 271.1279296875, 586.40625, 358.1201171875], "text": ["Par arr\u00eat\u00e9 du 11 ao\u00fbt 1965, M. Sidi Mohamed Guellil est", "nomm\u00e9 en qualit\u00e9 d'attach\u00e9 de pr\u00e9fecture stagiaire, sous", "r\u00e9serve de la justification des conditions prescrites par l'article 2", "du d\u00e9cret n\u00ba 62-503 du 19 juillet 1962."], "label": "Text", "position": 4}, {"bbox_text": [[92.0, 366.0, 523.0, 374.0]], "bbox_layout": [82.1484375, 351.962890625, 533.6328125, 386.318359375], "text": ["L'int\u00e9ress\u00e9 est mis \u00e0 la disposition du pr\u00e9fet d'Oran."], "label": "Text", "position": 5}, {"bbox_text": [[93.0, 410.0, 572.0, 420.0], [78.0, 429.0, 572.0, 435.0]], "bbox_layout": [69.70703125, 393.662109375, 589.140625, 449.892578125], "text": ["Par arr\u00eat\u00e9 du 11 ao\u00fbt 1965, M. Kaddour Yahiaoui est reclass\u00e9", "en qualit\u00e9 d'attach\u00e9 de pr\u00e9fecture de 2\u00ba classe, 2\u00ba \u00e9chelon."], "label": "Text", "position": 6}, {"bbox_text": [[93.0, 456.0, 516.0, 467.0]], "bbox_layout": [78.3203125, 443.22265625, 531.9921875, 478.26171875], "text": ["L'int\u00e9ress\u00e9 est mis \u00e0 la disposition du pr\u00e9fet d'Oran."], "label": "Text", "position": 7}, {"bbox_text": [[91.0, 503.0, 574.0, 510.0], [78.0, 520.0, 574.0, 527.0], [81.0, 537.0, 242.0, 549.0]], "bbox_layout": [71.62109375, 486.2890625, 589.6875, 555.5078125], "text": ["Par arr\u00eat\u00e9 du 11 ao\u00fbt 1965, M. Mouloud Benchellal est", "radi\u00e9 du cadre des secr\u00e9taires administratifs de pr\u00e9fecture", "(pr\u00e9fecture d'Alger)."], "label": "Text", "position": 8}, {"bbox_text": [[93.0, 565.0, 545.0, 574.0]], "bbox_layout": [79.140625, 551.9140625, 559.0625, 586.26953125], "text": ["Ledit arr\u00eat\u00e9 prend effet \u00e0 compter du 1er juillet 1965."], "label": "Text", "position": 9}, {"bbox_text": [[81.0, 624.0, 576.0, 631.0], [110.0, 641.0, 356.0, 650.0]], "bbox_layout": [72.71484375, 610.703125, 591.328125, 664.19921875], "text": ["Arr\u00eat\u00e9 du 16 ao\u00fbt 1965 portant d\u00e9l\u00e9gation dans les fonctions", "de chef de cabinet de pr\u00e9fet."], "label": "Text", "position": 10}, {"bbox_text": [[96.0, 684.0, 576.0, 695.0], [81.0, 702.0, 576.0, 710.0], [81.0, 720.0, 326.0, 730.0]], "bbox_layout": [71.89453125, 667.783203125, 587.5, 742.8125], "text": ["Par arr\u00eat\u00e9 du 16 ao\u00fbt 1965, M. Norine Benkritly est d\u00e9l\u00e9gu\u00e9,", "\u00e0 compter du 2 ao\u00fbt 1965, dans les fonctions de chef de", "cabinet du pr\u00e9fet de Tlemcen."], "label": "Text", "position": 11}, {"bbox_text": [[622.0, 16.0, 1050.0, 31.0]], "bbox_layout": [613.984375, 4.61181640625, 1059.453125, 44.991455078125], "text": ["MINISTERE DES FINANCES ET DU PLAN"], "label": "SectionHeader", "position": 12}, {"bbox_text": [[589.0, 63.0, 1085.0, 75.0], [621.0, 81.0, 1086.0, 90.0], [621.0, 96.0, 793.0, 110.0]], "bbox_layout": [581.171875, 50.75439453125, 1098.828125, 121.51123046875], "text": ["D\u00e9cret n\u00ba 65-225 du 7 septembre 1965 portant virement de", "cr\u00e9dit du minist\u00e8re de la sant\u00e9 publique au minist\u00e8re de", "l'\u00e9ducation nationale."], "label": "Text", "position": 13}, {"bbox_text": [[605.0, 124.0, 1086.0, 140.0], [607.0, 147.0, 1041.0, 158.0]], "bbox_layout": [591.015625, 115.439453125, 1098.828125, 168.0810546875], "text": ["Le Chef du Gouvernement, Pr\u00e9sident du Conseil des ministres,", "Sur le rapport du ministre des finances et du plan,"], "label": "Text", "position": 14}, {"bbox_text": [[607.0, 166.0, 1086.0, 179.0], [592.0, 184.0, 795.0, 198.0]], "bbox_layout": [583.359375, 155.51513671875, 1097.734375, 208.2421875], "text": ["Vu l'ordonnance n\u00ba 65-182 du 10 juillet 1965 portant consti-", "tution du Gouvernement,"], "label": "Text", "position": 15}, {"bbox_text": [[607.0, 204.0, 1087.0, 216.0], [592.0, 221.0, 931.0, 235.0]], "bbox_layout": [583.359375, 192.685546875, 1097.734375, 244.47265625], "text": ["Vu la loi de finances compl\u00e9mentaire pour 1965 n\u00ba 65-93", "du 8 avril 1965, notamment son article 4,"], "label": "Text", "position": 16}, {"bbox_text": [[608.0, 241.0, 1089.0, 254.0], [593.0, 259.0, 1089.0, 273.0], [593.0, 278.0, 1090.0, 287.0], [593.0, 294.0, 736.0, 308.0]], "bbox_layout": [581.171875, 229.94140625, 1101.015625, 315.908203125], "text": ["Vu le d\u00e9cret n\u00ba 65-102 du 13 avril 1965 portant r\u00e9partition", "des cr\u00e9dits ouverts au ministre de la sant\u00e9 publique, des", "anciens moudjahidine et des affaires sociales par la loi de", "finances sus-vis\u00e9e,"], "label": "Text", "position": 17}, {"bbox_text": [[610.0, 314.0, 1091.0, 325.0], [595.0, 330.0, 1090.0, 342.0], [593.0, 347.0, 804.0, 361.0]], "bbox_layout": [583.359375, 302.744140625, 1101.015625, 372.3046875], "text": ["Vu le d\u00e9cret n\u00ba 65-104 du 13 avril 1965 portant r\u00e9partition des", "cr\u00e9dits ouverts au ministre de l'\u00e9ducation nationale par la", "loi de finances sus-vis\u00e9e,"], "label": "Text", "position": 18}, {"bbox_text": [[610.0, 368.0, 1090.0, 379.0], [593.0, 385.0, 902.0, 399.0]], "bbox_layout": [585.0, 357.08984375, 1101.5625, 409.21875], "text": ["Vu le d\u00e9cret n\u00ba 65-188 du 13 juillet 1965 relatif \u00e0 la facult\u00e9", "mixte de m\u00e9decine et de pharmacle."], "label": "Text", "position": 19}, {"bbox_text": [[686.0, 407.0, 759.0, 417.0]], "bbox_layout": [674.6875, 395.712890625, 765.78125, 428.701171875], "text": ["D\u00e9cr\u00e8te :"], "label": "Text", "position": 20}, {"bbox_text": [[611.0, 427.0, 1091.0, 438.0], [597.0, 444.0, 1091.0, 454.0], [596.0, 459.0, 1092.0, 473.0], [596.0, 478.0, 1091.0, 487.0], [596.0, 495.0, 896.0, 506.0]], "bbox_layout": [586.640625, 414.853515625, 1104.296875, 517.568359375], "text": ["Article 18\". - Est annul\u00e9 sur 1965, un cr\u00e9dit de trois millions", "deux cent soixante dix huit mille cinq cent cinquante dinarm", "trente sept centimes (3.278.550,87 DA) applicable au budget", "du minist\u00e8re de la sant\u00e9 publique et aux chapitres \u00e9qum\u00e9r\u00e9s", "\u00e0 l'\u00e9tat A annex\u00e9 au pr\u00e9sent d\u00e9cret."], "label": "Text", "position": 21}, {"bbox_text": [[614.0, 516.0, 1092.0, 524.0], [597.0, 531.0, 1094.0, 542.0], [596.0, 549.0, 1094.0, 559.0], [596.0, 566.0, 1093.0, 575.0], [596.0, 583.0, 894.0, 594.0]], "bbox_layout": [588.828125, 502.353515625, 1104.296875, 607.119140625], "text": ["Art. 2. - Est ouvert sur 1965, un cr\u00e9dit de trois millions", "deux cent soixante dix huit mille cinq cent cinquante dinars", "trente sept centimes (3.278.550,37 DA) applicable au budget du", "minist\u00e8re de l'\u00e9ducation nationale et aux chapitres \u00e9num\u00e9r\u00e9s", "\u00e0 l'Etat B annex\u00e9 au pr\u00e9sent d\u00e9cret."], "label": "Text", "position": 22}, {"bbox_text": [[614.0, 604.0, 1094.0, 612.0], [597.0, 621.0, 1094.0, 629.0], [597.0, 638.0, 1094.0, 646.0], [600.0, 655.0, 1094.0, 662.0], [599.0, 671.0, 957.0, 681.0]], "bbox_layout": [592.65625, 590.537109375, 1105.9375, 695.302734375], "text": ["Art. 3. - Le ministre des finances et du plan, le ministre", "de la sant\u00e9 publique et le ministre de l'\u00e9ducation nationale", "sont charg\u00e9s, chacun en ce qui le concerne, de l'ex\u00e9cution du", "pr\u00e9sent d\u00e9cret qui sera publi\u00e9 au Journal officiel de la R\u00e9pu-", "blique alg\u00e9rienne d\u00e9mocratique et populaire."], "label": "Text", "position": 23}, {"bbox_text": [[753.0, 710.0, 939.0, 721.0]], "bbox_layout": [619.453125, 679.74609375, 952.265625, 728.45703125], "text": ["Houari BOUMEDIENE."], "label": "Text", "position": 24}, {"bbox_text": [[521.0, 742.0, 652.0, 757.0]], "bbox_layout": [513.0859375, 732.3828125, 661.328125, 767.421875], "text": ["ETAT \u00ab A \u00bb"], "label": "SectionHeader", "position": 25}, {"bbox_text": [[888.0, 796.0, 1054.0, 811.0], [938.0, 815.0, 1005.0, 828.0], [514.0, 819.0, 662.0, 833.0], [155.0, 823.0, 255.0, 837.0], [470.0, 860.0, 705.0, 874.0], [544.0, 906.0, 633.0, 920.0], [510.0, 930.0, 666.0, 943.0], [540.0, 959.0, 638.0, 973.0], [450.0, 982.0, 728.0, 994.0], [342.0, 1011.0, 836.0, 1022.0], [187.0, 1015.0, 226.0, 1025.0], [1009.0, 1020.0, 1066.0, 1033.0], [372.0, 1030.0, 835.0, 1041.0], [342.0, 1052.0, 837.0, 1061.0], [186.0, 1053.0, 228.0, 1066.0], [995.0, 1060.0, 1067.0, 1074.0], [372.0, 1068.0, 835.0, 1079.0], [541.0, 1089.0, 639.0, 1103.0], [468.0, 1108.0, 715.0, 1119.0], [1003.0, 1123.0, 1068.0, 1136.0], [187.0, 1132.0, 229.0, 1145.0], [342.0, 1132.0, 796.0, 1141.0], [343.0, 1155.0, 811.0, 1163.0], [186.0, 1156.0, 228.0, 1169.0], [996.0, 1163.0, 1068.0, 1177.0], [373.0, 1170.0, 535.0, 1186.0], [552.0, 1172.0, 793.0, 1182.0], [547.0, 1191.0, 635.0, 1205.0], [499.0, 1211.0, 685.0, 1222.0], [543.0, 1230.0, 641.0, 1243.0], [476.0, 1248.0, 710.0, 1262.0], [985.0, 1267.0, 1068.0, 1281.0], [344.0, 1273.0, 770.0, 1283.0], [146.0, 1276.0, 269.0, 1290.0], [543.0, 1294.0, 641.0, 1305.0], [442.0, 1312.0, 744.0, 1322.0], [1007.0, 1324.0, 1069.0, 1339.0], [345.0, 1336.0, 755.0, 1344.0], [188.0, 1338.0, 229.0, 1352.0], [965.0, 1363.0, 1070.0, 1375.0], [571.0, 1367.0, 815.0, 1379.0]], "bbox_layout": [74.765625, 776.1328125, 1105.390625, 1399.0625], "text": ["CREDITS ANNULES", "EN D.A.", "LIBELLE S", "CHAPITRES", "Minist\u00e8re de la sant\u00e9 publique", "THERE IN", "Moyens des services", "4\u00e8me Partie", "Mat\u00e9riel et remboursement de frais", "Etablissements d'enseignement m\u00e9dical sup\u00e9rieur - Rembour-", "84-20", "8.070.00", "sement de frais .", "Etablissements d'enseignement m\u00e9dical sup\u00e9rieur - Mat\u00e9riel", "34-27", "497.751,37", "et fonctionnement .", "6\u00e8me Partie", "Subventions de fonctionnement", "40.000,00", "36-22", "Participation au fonctionnement de l'universit\u00e9 ... .....", "Centres d'\u0153uvres pour \u00e9tudiants en sciences m\u00e9dicales", "36-51", "450.000,00", "Fonctionnement . .", ". . .", "TITRE IV", "Interventions publiques", "3\u00e8me Partie", "Action \u00e9ducative et culturelle", "2.274.729,00", "Bourses d'enseignement m\u00e9dical sup\u00e9rieur ........", "43-41 article 1 \u00b0r", "6\u00e8me Partie", "Action sociale - assistance et solidarit\u00e9", "10.000,00", "\u0152uvres sociales en faveur des \u00e9tudiants ........", "46-21", "zt 3.278.560,37", "Total des cr\u00e9dits annul\u00e9s ... ."], "label": "Table", "position": 26}]}, {"index": 4, "page": [{"bbox_text": [[480.0, 14.0, 609.0, 29.0]], "bbox_layout": [467.421875, 4.5050048828125, 624.6875, 38.5186767578125], "text": ["ETAT \u00ab B \u00bb"], "label": "Caption", "position": 0}, {"bbox_text": [[841.0, 43.0, 1005.0, 58.0], [890.0, 61.0, 955.0, 75.0], [473.0, 66.0, 613.0, 80.0], [112.0, 72.0, 210.0, 86.0], [412.0, 107.0, 675.0, 122.0], [499.0, 154.0, 590.0, 166.0], [468.0, 170.0, 623.0, 184.0], [497.0, 199.0, 594.0, 212.0], [424.0, 216.0, 669.0, 229.0], [298.0, 246.0, 792.0, 258.0], [144.0, 249.0, 183.0, 262.0], [947.0, 255.0, 1018.0, 270.0], [330.0, 264.0, 588.0, 276.0], [590.0, 264.0, 676.0, 275.0], [300.0, 292.0, 791.0, 304.0], [144.0, 296.0, 184.0, 309.0], [947.0, 302.0, 1018.0, 316.0], [330.0, 310.0, 750.0, 324.0], [504.0, 338.0, 591.0, 351.0], [458.0, 356.0, 639.0, 369.0], [499.0, 385.0, 599.0, 397.0], [429.0, 401.0, 669.0, 413.0], [938.0, 429.0, 1020.0, 444.0], [301.0, 430.0, 646.0, 444.0], [147.0, 436.0, 187.0, 450.0], [501.0, 459.0, 599.0, 473.0], [401.0, 476.0, 700.0, 490.0], [958.0, 504.0, 1022.0, 519.0], [305.0, 505.0, 681.0, 519.0], [148.0, 511.0, 187.0, 525.0], [918.0, 546.0, 1024.0, 560.0], [540.0, 547.0, 755.0, 561.0]], "bbox_layout": [30.7421875, 19.9072265625, 1062.1875, 592.421875], "text": ["CREDITS OUVERTS", "EN D.A.", "LIBELLES", "CHAPITRES", "Minist\u00e8re de l'\u00e9ducation nationale", "ENFRE III", "Moyens des services", "6\u00e8me Partie", "Subventions de fonctionnement", "Etablissements d'enseignement sup\u00e9rieur - Subventions de", "36-21", "543.821 ,37", "fonctionnement et de mat\u00e9riel", "...........", "Centre national des \u0153uvres sociales et universitaires - Sub-", "36-31", "450.000,00", "ventions de fonctionnement .", "THIRE IV", "Interventions publiques", "3\u00e8me Partie", "Actions \u00e9ducative et culturelle", "2.274.729,00", "Bourses diverses d'enseignement public ....", "43-01", "6\u00e8me Partie", "Action sociale - Assistance et solidarit\u00e9", "10.000,00", "\u0152uvres sociales en faveur des \u00e9tudiants .....", "46-21", "= 3.278.550,00", "Total des cr\u00e9dits ouverts ..."], "label": "Table", "position": 1}, {"bbox_text": [[45.0, 614.0, 540.0, 622.0], [76.0, 631.0, 539.0, 639.0], [77.0, 647.0, 253.0, 660.0]], "bbox_layout": [37.8515625, 600.44921875, 557.1484375, 673.0859375], "text": ["D\u00e9cret n\u00ba 65-226 du 7 septembre 1965 portant virement de", "cr\u00e9dit du minist\u00e8re de la sant\u00e9 publique au minist\u00e8re des", "anciens moudjahidine."], "label": "SectionHeader", "position": 2}, {"bbox_text": [[60.0, 696.0, 541.0, 704.0]], "bbox_layout": [52.75390625, 682.48046875, 553.59375, 716.8359375], "text": ["Le Chef du Gouvernement, Pr\u00e9sident du Conseil des ministres,"], "label": "Text", "position": 3}, {"bbox_text": [[62.0, 726.0, 495.0, 732.0]], "bbox_layout": [50.29296875, 710.5078125, 500.546875, 744.1796875], "text": ["Sur le rapport du ministre des finances et du plan,"], "label": "Text", "position": 4}, {"bbox_text": [[62.0, 758.0, 541.0, 765.0], [48.0, 777.0, 255.0, 786.0]], "bbox_layout": [39.08203125, 742.63671875, 552.5, 795.44921875], "text": ["Vu l'ordonnance n\u00ba 65-182 du 10 juillet 1965 portant consti-", "tution du Gouvernement,"], "label": "Text", "position": 5}, {"bbox_text": [[63.0, 806.0, 542.0, 815.0], [48.0, 825.0, 393.0, 835.0]], "bbox_layout": [38.9453125, 792.5390625, 553.3203125, 845.3515625], "text": ["Vu la loi de finances compl\u00e9mentaire pour 1965 n\u00b0 05-93", "du 8 avril 1965, notamment son article 4,"], "label": "Text", "position": 6}, {"bbox_text": [[65.0, 854.0, 544.0, 860.0], [49.0, 870.0, 545.0, 878.0], [51.0, 887.0, 543.0, 894.0], [48.0, 905.0, 123.0, 919.0]], "bbox_layout": [38.26171875, 838.33984375, 555.78125, 928.06640625], "text": ["Vu le d\u00e9cr\u00e8t n\u00ba 65-102 du 13 avril 1965 portant r\u00e9partition", "des cr\u00e9dits ouverts au ministre de la sante publique, des anciens", "moudjahidine et des affaires sociales par la loi de finances", "sus-vis\u00e9e,"], "label": "Text", "position": 7}, {"bbox_text": [[653.0, 607.0, 728.0, 621.0]], "bbox_layout": [622.1875, 599.423828125, 732.96875, 633.095703125], "text": ["D\u00e9cr\u00e8te :"], "label": "Text", "position": 8}, {"bbox_text": [[670.0, 627.0, 1053.0, 641.0], [580.0, 629.0, 670.0, 640.0], [563.0, 645.0, 1054.0, 658.0], [564.0, 661.0, 1054.0, 673.0], [564.0, 679.0, 773.0, 693.0]], "bbox_layout": [558.203125, 617.5390625, 1067.109375, 702.48046875], "text": ["- Est annul\u00e9 sur 1965, un cr\u00e9dit d'un million", "Article 1er.", "de dinars (1.000.000 D.A.) applicable au budget du minist\u00e8re", "de la sant\u00e9 publique et aux chapitres \u00e9num\u00e9r\u00e9s \u00e0 l'\u00e9tat \u00ab A \u00bb", "annex\u00e9 au pr\u00e9sent d\u00e9cret."], "label": "Text", "position": 9}, {"bbox_text": [[643.0, 697.0, 1056.0, 711.0], [580.0, 698.0, 637.0, 711.0], [565.0, 717.0, 1057.0, 726.0], [867.0, 731.0, 1057.0, 742.0], [565.0, 732.0, 866.0, 744.0], [565.0, 749.0, 1055.0, 759.0], [563.0, 767.0, 634.0, 780.0]], "bbox_layout": [556.5625, 688.291015625, 1069.84375, 789.98046875], "text": ["- Est quvert sur 1965, un cr\u00e9dit d'un million de", "Art. 2.", "dinars (1.000.000 D.A.) applicable au budget du minist\u00e8re des", "34-64 \u00ab Am\u00e9nagement", "anciens moudjahidine, au chapitre", "et fonctionnement des centres et foyers des pupilles de la", "nation \u00bb."], "label": "Text", "position": 10}, {"bbox_text": [[581.0, 786.0, 653.0, 799.0], [656.0, 786.0, 1058.0, 794.0], [566.0, 802.0, 1057.0, 813.0], [565.0, 817.0, 1057.0, 831.0], [566.0, 837.0, 1057.0, 845.0], [566.0, 854.0, 960.0, 863.0]], "bbox_layout": [558.75, 773.3984375, 1072.03125, 878.1640625], "text": ["Art. 3. -", "Le ministre des finances et du plan, le ministre", "de la sant\u00e1 publique et le ministre des anciens moudjahidine", "sont charg\u00e9s, chacun en ce qui le concerne, de l'ex\u00e9cution", "du pr\u00e9sent d\u00e9cret qui sera publi\u00e9 au Journal officiel de la", "R\u00e9publique alg\u00e9rienne d\u00e9mocratique et populaire."], "label": "Text", "position": 11}, {"bbox_text": [[720.0, 891.0, 904.0, 906.0]], "bbox_layout": [673.046875, 882.7734375, 913.984375, 917.8125], "text": ["Houari BOUMEDIENE."], "label": "Text", "position": 13}, {"bbox_text": [[491.0, 938.0, 620.0, 952.0]], "bbox_layout": [469.0625, 929.94140625, 638.90625, 964.98046875], "text": ["ETAT \u00abA\u00bb"], "label": "SectionHeader", "position": 14}, {"bbox_text": [[855.0, 978.0, 1019.0, 994.0], [901.0, 997.0, 971.0, 1010.0], [487.0, 1001.0, 627.0, 1015.0], [125.0, 1008.0, 224.0, 1023.0], [438.0, 1043.0, 676.0, 1055.0], [511.0, 1088.0, 603.0, 1102.0], [480.0, 1110.0, 635.0, 1125.0], [511.0, 1139.0, 607.0, 1153.0], [402.0, 1165.0, 716.0, 1174.0], [980.0, 1184.0, 1050.0, 1199.0], [313.0, 1195.0, 755.0, 1203.0], [156.0, 1198.0, 198.0, 1213.0], [510.0, 1220.0, 610.0, 1234.0], [430.0, 1245.0, 690.0, 1256.0], [515.0, 1271.0, 605.0, 1285.0], [313.0, 1298.0, 809.0, 1304.0], [1051.0, 1312.0, 1068.0, 1326.0], [982.0, 1314.0, 1038.0, 1328.0], [313.0, 1326.0, 768.0, 1334.0], [159.0, 1328.0, 198.0, 1345.0], [973.0, 1356.0, 1038.0, 1370.0], [549.0, 1365.0, 765.0, 1375.0]], "bbox_layout": [40.5859375, 966.85546875, 1074.21875, 1390.17578125], "text": ["CREDITS ANNULES", "EN D.A.", "LIBELLES", "CHAPITRES", "Minist\u00e8re de la sant\u00e9 publique", "THERE III", "Moyens des services", "4\u00e8me Partie", "Mat\u00e9riel et fonctionnement des services", "500.000 ?", "Administration centrale - Mat\u00e9riel et fonctionnement i", "34-02", "TITRE VIII", "D\u00e9penses sur ressources affect\u00e9es", "l\u00e8re Partie", "Emploi du produit des jeux, du pari mutuel et de la loterie", "r", "500.000", "\u0152uvres sociales du minist\u00e8re des la sant\u00e9 publique .....", "81-31", "1,000.000", "Total des cr\u00e9dits annul\u00e9s ..."], "label": "Table", "position": 15}]}, {"index": 5, "page": [{"bbox_text": [[149.0, 22.0, 489.0, 39.0], [154.0, 46.0, 487.0, 64.0]], "bbox_layout": [142.8515625, 12.30224609375, 508.4765625, 75.71044921875], "text": ["MINISTERE DE L'AGRICULTURE", "ET DE LA REFORME AGRAIRE"], "label": "SectionHeader", "position": 0}, {"bbox_text": [[70.0, 95.0, 564.0, 114.0], [100.0, 112.0, 431.0, 130.0]], "bbox_layout": [58.359375, 86.81396484375, 579.296875, 140.99365234375], "text": ["Arr\u00eat\u00e9 du 2 septembre 1965 r\u00e9glementant l'exercice de la chasse", "pour la campagne cyn\u00e9g\u00e9tique 1965-1966."], "label": "SectionHeader", "position": 1}, {"bbox_text": [[82.0, 161.0, 501.0, 175.0]], "bbox_layout": [69.84375, 152.5244140625, 518.59375, 187.5634765625], "text": ["Le ministre de l'agriculture et de la r\u00e9forme agraire,"], "label": "Text", "position": 2}, {"bbox_text": [[83.0, 187.0, 563.0, 206.0], [66.0, 205.0, 563.0, 223.0], [66.0, 221.0, 564.0, 242.0]], "bbox_layout": [57.94921875, 181.2353515625, 580.9375, 250.1123046875], "text": ["Vu la loi n\u00ba 62-157 du 31 d\u00e9cembre 1962 tendant \u00e0 la", "reconduction de la l\u00e9gislation en vigueur au 31 d\u00e9cembre 1962,", "sauf dans ses dispositions contraires \u00e0 la souverainet\u00e9 nationale,"], "label": "Text", "position": 3}, {"bbox_text": [[84.0, 250.0, 564.0, 270.0], [67.0, 269.0, 294.0, 284.0]], "bbox_layout": [56.85546875, 243.4423828125, 580.9375, 296.5966796875], "text": ["Vu la loi du 3 mai 1844 sur la police de la chasse, modifi\u00e9e", "par la loi du 1er mai 1924,"], "label": "Text", "position": 4}, {"bbox_text": [[83.0, 299.0, 564.0, 316.0], [66.0, 315.0, 215.0, 331.0]], "bbox_layout": [57.5390625, 290.439453125, 578.75, 342.568359375], "text": ["Vu l'avis du comit\u00e9 sup\u00e9rieur de la chasse, en sa r\u00e9union", "du 23 juillet 1965,"], "label": "Text", "position": 5}, {"bbox_text": [[82.0, 346.0, 564.0, 362.0], [67.0, 360.0, 410.0, 381.0]], "bbox_layout": [57.67578125, 335.556640625, 579.84375, 387.001953125], "text": ["Sur proposition du chef de service des for\u00eats et de la", "d\u00e9fense et restauration des sols (D.R.S.),"], "label": "Text", "position": 6}, {"bbox_text": [[159.0, 393.0, 224.0, 407.0]], "bbox_layout": [154.19921875, 382.041015625, 239.82421875, 416.396484375], "text": ["Arr\u00eate :"], "label": "Text", "position": 7}, {"bbox_text": [[83.0, 420.0, 562.0, 438.0], [67.0, 437.0, 561.0, 456.0], [66.0, 452.0, 561.0, 475.0], [66.0, 472.0, 244.0, 486.0]], "bbox_layout": [57.12890625, 411.09375, 580.390625, 497.40234375], "text": ["Article 1\u00bar. - L'ouverture de la chasse \u00e0 tir du gibier", "s\u00e9dentaire aura lieu sur tout le territoire national du dimanche", "12 septembre 1965 \u00e0 7 heures, au dimanche 2 janvier 1966", "au coucher du soleil.,"], "label": "Text", "position": 8}, {"bbox_text": [[81.0, 500.0, 561.0, 520.0], [66.0, 518.0, 562.0, 535.0], [66.0, 534.0, 561.0, 555.0], [66.0, 552.0, 471.0, 570.0]], "bbox_layout": [55.625, 492.44140625, 577.109375, 580.80078125], "text": ["La chasse n'est autoris\u00e9e pendant cette p\u00e9riode que les", "mardi, jeudi, samedi et jours f\u00e9ri\u00e9s. Elle reste interdite les", "autres jours de la semaine et lors des \u00e9lections dans les", "communes o\u00f9 des op\u00e9rations \u00e9lectorales ont lieu."], "label": "Text", "position": 9}, {"bbox_text": [[81.0, 581.0, 561.0, 601.0], [65.0, 596.0, 561.0, 619.0], [63.0, 618.0, 560.0, 632.0], [64.0, 633.0, 498.0, 649.0]], "bbox_layout": [55.078125, 573.7890625, 576.015625, 660.09765625], "text": ["Art. 2. - Les pr\u00e9fets pourront, sur la totalit\u00e9 ou sur une", "partie de leur d\u00e9partement retarder l'ouverture de la chasse", "et avancer la cloture de la chasse pour toutes esp\u00e8ces de", "gibier par arr\u00eat\u00e9 publi\u00e9 au moins dix jours \u00e0 l'avance."], "label": "Text", "position": 10}, {"bbox_text": [[81.0, 662.0, 560.0, 681.0], [64.0, 677.0, 561.0, 700.0], [63.0, 695.0, 560.0, 714.0], [63.0, 712.0, 560.0, 731.0]], "bbox_layout": [54.94140625, 654.453125, 576.015625, 739.39453125], "text": ["Art. 3. - Nul ne pourra chasser s'il n'est en possession", "du permis national de chasse et s'il n'est propri\u00e9taire ou", "possesseur du terrain, ou titulaire d'un droit de chasse sur", "ce terrain ou s'il n'a obtenu l'autorisation des ayants-droit."], "label": "Text", "position": 11}, {"bbox_text": [[77.0, 742.0, 560.0, 760.0], [63.0, 758.0, 561.0, 779.0], [63.0, 774.0, 561.0, 796.0], [62.0, 793.0, 560.0, 811.0], [62.0, 807.0, 327.0, 828.0]], "bbox_layout": [53.84765625, 733.06640625, 574.921875, 836.46484375], "text": ["Art. 4. - Il est formellement interdit de chasser la nuit", "et de d\u00e9tenir ou employer pour chasser, des filets, panneaux,", "appeaux, appelants, lacets, collets et engins de toutes esp\u00e8ces,", "sauf en ce qui concerne le lapin qui peut \u00eatre captur\u00e9 au", "moyen de fur\u00eats et de bourses."], "label": "Text", "position": 12}, {"bbox_text": [[77.0, 840.0, 558.0, 858.0], [62.0, 856.0, 557.0, 876.0]], "bbox_layout": [53.7109375, 830.8203125, 572.1875, 883.6328125], "text": ["La chasse \u00e0 la grive est autoris\u00e9e au poste avec appeaux", "et appelants. Le miroir est autoris\u00e9 pour la chasse \u00e0 l'alouette."], "label": "Text", "position": 13}, {"bbox_text": [[77.0, 887.0, 558.0, 904.0], [62.0, 902.0, 559.0, 923.0]], "bbox_layout": [53.02734375, 878.671875, 572.1875, 931.484375], "text": ["La chasse en temps de neige est interdite sauf pour le", "gibier d'eau dans les marais, sur les \u00e9tangs, fleuves et rivi\u00e8res."], "label": "Text", "position": 14}, {"bbox_text": [[78.0, 932.0, 558.0, 952.0], [62.0, 948.0, 558.0, 970.0], [62.0, 965.0, 557.0, 987.0], [61.0, 983.0, 466.0, 1002.0]], "bbox_layout": [51.66015625, 925.83984375, 571.09375, 1010.09765625], "text": ["Art. 5. - Il est formellement interdit de faire usage de", "chiens l\u00e9vriers pur-sang ou crois\u00e9s, et de chiens de race", "espagnole dits \u00ab galgos \u00bb pour quelque chasse que se soit,", "m\u00eame pour la destruction des animaux nuisibles."], "label": "Text", "position": 15}, {"bbox_text": [[77.0, 1013.0, 557.0, 1031.0], [60.0, 1028.0, 557.0, 1050.0], [59.0, 1047.0, 132.0, 1061.0]], "bbox_layout": [50.703125, 1004.453125, 570.546875, 1073.671875], "text": ["La chasse ou la poursuite du gibier \u00e0 partir d'automobile,", "d'avion ou d'h\u00e9licoppt\u00e8re est interdite sur tout le territoire", "national."], "label": "Text", "position": 16}, {"bbox_text": [[76.0, 1075.0, 557.0, 1096.0], [59.0, 1092.0, 557.0, 1111.0], [58.0, 1109.0, 556.0, 1128.0], [58.0, 1128.0, 318.0, 1143.0]], "bbox_layout": [49.47265625, 1068.02734375, 569.453125, 1153.65234375], "text": ["Art. 6. - Aucun chasseur ne pourra abattre plus de 8 pi\u00e8ces", "de gibier, dont 2 li\u00e8vres au maximum ; les chasseurs devront", "se pr\u00eater \u00e0 la visite de leurs carniers par les agents charg\u00e9s", "de la surveillance de la chasse."], "label": "Text", "position": 17}, {"bbox_text": [[70.0, 1156.0, 556.0, 1175.0], [58.0, 1171.0, 555.0, 1193.0], [58.0, 1190.0, 334.0, 1207.0]], "bbox_layout": [48.65234375, 1148.0078125, 568.90625, 1215.859375], "text": ["Art. 7. - Sont interdits la mise en vente, la commercialisation", "et l'achat de tout gibier tu\u00e9 autrement qu'au fusil ou dont", "la chasse n'est pas encore ouverte."], "label": "Text", "position": 18}, {"bbox_text": [[74.0, 1218.0, 479.0, 1237.0], [479.0, 1224.0, 554.0, 1237.0], [57.0, 1235.0, 555.0, 1255.0], [56.0, 1250.0, 554.0, 1273.0], [56.0, 1270.0, 293.0, 1284.0]], "bbox_layout": [48.37890625, 1210.21484375, 567.8125, 1295.83984375], "text": ["La recherche du gibier pourra \u00eatre effectuee", "dans les", "magasins, h\u00f4tels et restaurants et, d'une fa\u00e7on g\u00e9n\u00e9rale, dans", "tous les lieux o\u00f9 peut \u00eatre entrepos\u00e9 le gibier destin\u00e9 \u00e0 la", "consommation ou \u00e0 la vente."], "label": "Text", "position": 19}, {"bbox_text": [[166.0, 1298.0, 554.0, 1316.0], [74.0, 1299.0, 166.0, 1312.0], [56.0, 1312.0, 554.0, 1333.0], [58.0, 1329.0, 537.0, 1351.0]], "bbox_layout": [47.83203125, 1288.828125, 567.8125, 1353.9453125], "text": ["Sont interdits en tout temps et sur tout le", "Art. 8. -", "territoire national, la chasse, la destruction, la capture, le", "coiportage, la vente et l'achat des esp\u00e8ces rares suivantes :"], "label": "Text", "position": 20}, {"bbox_text": [[72.0, 1353.0, 232.0, 1367.0]], "bbox_layout": [66.8359375, 1342.1484375, 247.890625, 1377.1875], "text": ["- Cerf de barbarie"], "label": "Text", "position": 21}, {"bbox_text": [[71.0, 1368.0, 415.0, 1388.0]], "bbox_layout": [66.69921875, 1360.60546875, 428.359375, 1397.01171875], "text": ["- Gazelles et antilopes de toutes esp\u00e8ces"], "label": "Text", "position": 22}, {"bbox_text": [[73.0, 1388.0, 162.0, 1398.0]], "bbox_layout": [68.4765625, 1380.4296875, 177.20703125, 1410.0], "text": ["- Mouflon"], "label": "Text", "position": 23}, {"bbox_text": [[603.0, 22.0, 1083.0, 42.0], [588.0, 38.0, 924.0, 57.0]], "bbox_layout": [578.4375, 13.92578125, 1095.0, 66.14013671875], "text": ["Aucune d\u00e9pouille ou partie de d\u00e9pouille desdites esp\u00e8ces", "ne pourra \u00eatre mise en vente ou achet\u00e9e."], "label": "Text", "position": 24}, {"bbox_text": [[603.0, 68.0, 1084.0, 89.0], [587.0, 83.0, 1083.0, 107.0], [587.0, 102.0, 1083.0, 122.0], [587.0, 116.0, 1084.0, 140.0], [586.0, 136.0, 742.0, 150.0]], "bbox_layout": [575.15625, 59.7265625, 1098.28125, 161.5869140625], "text": ["Art. 9. - Sont interdites la chasse, la destruction ou la", "commercialisation des oiseaux suivants : cigognes, outardes", "oubara, vautours, chouettes. Il en est de m\u00eame pour tous", "les oiseaux utiles dont la taille est inf\u00e9rieure \u00e0 celle de la", "grive ou du merle."], "label": "Text", "position": 25}, {"bbox_text": [[602.0, 163.0, 1083.0, 186.0], [587.0, 181.0, 1083.0, 200.0], [587.0, 195.0, 911.0, 216.0]], "bbox_layout": [576.25, 156.54052734375, 1097.1875, 224.990234375], "text": ["Il est d\u00e9fendu en tout temps d'enlever les nids et de", "prendre les \u0153ufs, de capturer ou de d\u00e9truire les couv\u00e9es des", "perdrix, de cailles et des oiseaux utiles."], "label": "Text", "position": 26}, {"bbox_text": [[602.0, 226.0, 1083.0, 247.0], [586.0, 242.0, 1083.0, 263.0], [585.0, 260.0, 1083.0, 280.0], [586.0, 277.0, 727.0, 291.0]], "bbox_layout": [576.25, 218.4912109375, 1098.28125, 303.7744140625], "text": ["Art. 10. - La chasse au gibier d'eau est autoris\u00e9e jusqu'au", "27 mars au coucher du soleil; cette chasse \u00e9tant limit\u00e9e", "\u00e0 une zone de 30 m\u00e8tres des bords des oueds, lacs, canaux,", "\u00e9tangs et marais."], "label": "Text", "position": 27}, {"bbox_text": [[601.0, 306.0, 1083.0, 326.0], [585.0, 323.0, 960.0, 341.0]], "bbox_layout": [579.53125, 299.326171875, 1097.1875, 351.11328125], "text": ["La chasse \u00e0 la b\u00e9casse et \u00e0 la palombe est autoris\u00e9e", "jusqu'\u00e0 la m\u00eame date dans les bois et for\u00eats."], "label": "Text", "position": 28}, {"bbox_text": [[601.0, 352.0, 1083.0, 372.0], [585.0, 368.0, 1083.0, 388.0], [585.0, 385.0, 889.0, 405.0]], "bbox_layout": [576.25, 344.78515625, 1098.28125, 413.3203125], "text": ["La pass\u00e9e, au poste et sans chien, est autoris\u00e9e pendant", "l'heure qui pr\u00e9c\u00e9de imm\u00e9diatement le lever du soleil et pendant", "l'heure qui suit le coucher du soleil."], "label": "Text", "position": 29}, {"bbox_text": [[600.0, 414.0, 1081.0, 436.0], [585.0, 430.0, 1082.0, 454.0], [585.0, 447.0, 1083.0, 470.0], [585.0, 466.0, 818.0, 481.0]], "bbox_layout": [576.25, 406.650390625, 1100.46875, 492.275390625], "text": ["Art. 11. - Les propri\u00e9taires et exploitants pourront, sur", "leurs propres fonds seulement, repousser ou d\u00e9truire en tout", "temps, sans permis de chasse et par tous les moyens, les", "animaux nuisibles suivants :"], "label": "Text", "position": 30}, {"bbox_text": [[630.0, 493.0, 1081.0, 516.0], [600.0, 497.0, 626.0, 506.0], [584.0, 511.0, 1080.0, 532.0], [585.0, 527.0, 1080.0, 550.0], [585.0, 545.0, 1080.0, 565.0], [585.0, 560.0, 1080.0, 584.0], [585.0, 581.0, 677.0, 593.0]], "bbox_layout": [576.25, 486.97265625, 1097.1875, 605.41015625], "text": ["Chacal, renard, zorille, chat sauvage, mangouste (ou", "8)", "raton), genette (ou civette), lapin, porc \u00e9pic et sanglier. La", "chasse du singe est interdite sauf pour les propri\u00e9taires ou", "exploitants de vergers ou de champs de mais et sorgho qui", "peuvent les detruire au moyen d'arme \u00e0 feu pour prot\u00e9ger", "les r\u00e9coltes."], "label": "Text", "position": 31}, {"bbox_text": [[599.0, 608.0, 1080.0, 629.0], [582.0, 625.0, 1079.0, 645.0], [582.0, 642.0, 1080.0, 662.0], [582.0, 656.0, 1079.0, 680.0], [582.0, 675.0, 1079.0, 695.0], [582.0, 691.0, 986.0, 710.0]], "bbox_layout": [575.15625, 599.765625, 1096.09375, 716.8359375], "text": ["b) Les oiseaux rapaces, les corbeaux et corneilles, les gangas,", "les gu\u00e9piers, les gros-becs et moineaux, s'ils apportent une", "menace imminente et directe. Les grives, \u00e9tourneaux et", "alouettes peuvent \u00eatre tir\u00e9s en tout temps, mais sans chien", "et \u00e0 l'aff\u00fbt, par les propri\u00e9taires ou exploitants dans les", "oliveraies, vignes et terrains charges de r\u00e9colte. -"], "label": "Text", "position": 32}, {"bbox_text": [[598.0, 719.0, 1079.0, 740.0], [582.0, 736.0, 1079.0, 756.0], [582.0, 754.0, 733.0, 768.0]], "bbox_layout": [575.15625, 711.19140625, 1092.8125, 779.04296875], "text": ["Art. 12. - Dans chaque d\u00e9partement, le pr\u00e9fet est charge", "d'organiser en tout temps la destruction des animaux nuisibles", "d\u00e9sign\u00e9s ci-apr\u00e8s :"], "label": "Text", "position": 33}, {"bbox_text": [[581.0, 782.0, 1078.0, 802.0], [581.0, 797.0, 989.0, 819.0]], "bbox_layout": [572.96875, 774.08203125, 1091.71875, 826.89453125], "text": ["sanglier, chacal, lapin de garenne, ainsi que la protection", "du gibier des esp\u00e8ces rares en voie de disparition."], "label": "Text", "position": 34}, {"bbox_text": [[597.0, 830.0, 689.0, 841.0], [693.0, 830.0, 1058.0, 848.0], [1059.0, 835.0, 1077.0, 845.0], [581.0, 844.0, 1079.0, 866.0], [581.0, 863.0, 1078.0, 881.0], [581.0, 877.0, 1076.0, 901.0], [581.0, 896.0, 1078.0, 915.0], [581.0, 911.0, 818.0, 930.0]], "bbox_layout": [572.421875, 820.56640625, 1095.546875, 937.63671875], "text": ["Art. 13. -", "Les battues administratives destin\u00e9es \u00e0", "la", "destruction, par arme \u00e0 feu, des animaux nuisibles vis\u00e9s \u00e0", "l'article 12 sont d\u00e9cid\u00e9es et organis\u00e9es par le pr\u00e9fet soit \u00e0 la", "demande des collectivit\u00e9s locales int\u00e9ress\u00e9es, soit sur les pro-", "positions du conservateur des for\u00eats et de la d\u00e9fense et", "restauration des sols (D.R.S.)."], "label": "Text", "position": 35}, {"bbox_text": [[596.0, 941.0, 1076.0, 961.0], [582.0, 956.0, 1077.0, 979.0], [578.0, 976.0, 1078.0, 993.0], [579.0, 990.0, 1077.0, 1012.0], [580.0, 1010.0, 896.0, 1024.0]], "bbox_layout": [569.6875, 933.359375, 1091.71875, 1034.0234375], "text": ["En dehors de la p\u00e9riode d'ouverture g\u00e9n\u00e9rale de la chasse", "(12 septembre 1965 au 2 janvier 1966) aucune battue ne peut \u00eatre", "men\u00e9e sauf celles d\u00e9cid\u00e9es par le pr\u00e9fet conformement au pr\u00e9sent", "article, ou celles d\u00e9cid\u00e9es par les autorit\u00e9s communales dans", "les limites de leurs pouvoirs de police."], "label": "Text", "position": 36}, {"bbox_text": [[595.0, 1034.0, 1076.0, 1058.0], [577.0, 1053.0, 1077.0, 1073.0], [578.0, 1068.0, 1076.0, 1091.0], [578.0, 1088.0, 792.0, 1102.0]], "bbox_layout": [568.59375, 1030.4296875, 1091.71875, 1113.3203125], "text": ["La conduite et le contr\u00f4le de ces battues appartiennent", "\u00e0 l'administration des for\u00eats et de la d\u00e9fense et restauration", "des sols (D.R.S.) qui doit \u00eatre avis\u00e9e quatre jours avant le", "d\u00e9roulement de la battue."], "label": "Text", "position": 37}, {"bbox_text": [[594.0, 1115.0, 1075.0, 1135.0], [578.0, 1132.0, 1076.0, 1152.0], [578.0, 1147.0, 1075.0, 1171.0], [577.0, 1167.0, 1075.0, 1184.0], [577.0, 1182.0, 1074.0, 1202.0], [577.0, 1201.0, 904.0, 1215.0]], "bbox_layout": [568.59375, 1108.359375, 1089.53125, 1226.796875], "text": ["Art. 14. - La charge financi\u00e8re des battues administratives", "incombe aux collectivit\u00e9s int\u00e9ress\u00e9s. Celles-ci disposent librement", "du gibier tu\u00e9. En dehors de la p\u00e9riode d'ouverture de la chasse,", "celui-ci ne peut \u00eatre colport\u00e9 que moyennant un permis de", "colportage d\u00e9livr\u00e9 par l'administration des for\u00eats et de la", "d\u00e9fense et restauration des sols (D.R.S.)."], "label": "Text", "position": 38}, {"bbox_text": [[593.0, 1227.0, 1074.0, 1248.0], [577.0, 1245.0, 1072.0, 1264.0], [577.0, 1263.0, 830.0, 1277.0]], "bbox_layout": [571.875, 1221.15234375, 1087.34375, 1290.37109375], "text": ["Art. 15. - Dans chaque d\u00e9partement, le conservateur des", "for\u00eats et de la detense et restauration des sols (D.R.S.) terri-", "torialement comp\u00e9tent peut :"], "label": "Text", "position": 39}, {"bbox_text": [[591.0, 1279.0, 1072.0, 1303.0], [614.0, 1300.0, 715.0, 1313.0]], "bbox_layout": [583.90625, 1274.47265625, 1087.34375, 1327.28515625], "text": ["- d\u00e9clarer r\u00e9serve de chasse tous bois ou cantons forestiers", "domaniaux ;"], "label": "ListItem", "position": 40}, {"bbox_text": [[609.0, 1317.0, 1072.0, 1340.0], [592.0, 1323.0, 609.0, 1333.0], [643.0, 1334.0, 1072.0, 1357.0], [614.0, 1338.0, 643.0, 1348.0], [611.0, 1353.0, 1070.0, 1372.0]], "bbox_layout": [580.078125, 1310.703125, 1090.078125, 1373.0859375], "text": ["d\u00e9clarer reserve de chasse, moyennant accord de l'autorit\u00e9", "l", "tutelle tous bois ou cantons forestiers soumis au", "de", "r\u00e9gime forestier, appartenant \u00e0 des collectivit\u00e9s publiques ;"], "label": "ListItem", "position": 41}, {"bbox_text": [[610.0, 1371.0, 1071.0, 1395.0], [614.0, 1393.0, 764.0, 1398.0], [768.0, 1393.0, 828.0, 1398.0]], "bbox_layout": [581.71875, 1361.2890625, 1086.25, 1410.0], "text": ["proposer au pr\u00e9fet toute r\u00e9serve de chasse n'entrant pas", "ACHO LAN ACTAMANION", "et donal"], "label": "ListItem", "position": 42}]}, {"index": 6, "page": [{"bbox_text": [[55.0, 17.0, 536.0, 32.0], [40.0, 35.0, 534.0, 49.0], [40.0, 51.0, 537.0, 66.0], [41.0, 67.0, 536.0, 81.0], [41.0, 86.0, 536.0, 98.0], [40.0, 101.0, 535.0, 116.0], [40.0, 119.0, 535.0, 133.0], [40.0, 135.0, 535.0, 147.0], [40.0, 151.0, 535.0, 165.0], [40.0, 169.0, 535.0, 179.0], [40.0, 184.0, 534.0, 198.0]], "bbox_layout": [31.015625, 7.2607421875, 553.046875, 207.3876953125], "text": ["Art. 16. - Aucun gibier ne peut \u00eatre captur\u00e9 et transport\u00e9", "\u00e0 l'\u00e9tat vif sans autorisation sp\u00e9ciale d\u00e9livr\u00e9e par le conser-", "vateur des for\u00eats et de la d\u00e9fense et restauration des sols", "(D.R.S.) territorialement comp\u00e9tent et apr\u00e8s avis de la direction", "des for\u00eats et de la d\u00e9fense et restauration des sols (D.R.S.) s'il", "s'agit d'une esp\u00e8ce de gibier surabondante dans un secteur", "donn\u00e9 ; des titres de transport sont d\u00e9livr\u00e9s en nombre", "correspondant au nombre d'animaux dont la capture est", "autoris\u00e9e. L'exportation de ce gibier vivant peut \u00eatre accord\u00e9e,", "sous r\u00e9serve du visa des services v\u00e9t\u00e9rinaires, par le minist\u00e8re", "du commerce, su vu des titres de transport correspondants."], "label": "Text", "position": 0}, {"bbox_text": [[55.0, 209.0, 536.0, 221.0], [40.0, 226.0, 535.0, 240.0], [40.0, 242.0, 270.0, 257.0]], "bbox_layout": [30.60546875, 196.9580078125, 547.578125, 265.4931640625], "text": ["Art. 17. - Les associations de chasse r\u00e9guli\u00e8rement constituees", "pourront obtenir de louer par voie d'amodiation les lots de", "chasse en for\u00eats domaniales."], "label": "Text", "position": 1}, {"bbox_text": [[55.0, 268.0, 537.0, 281.0], [40.0, 285.0, 535.0, 296.0], [40.0, 301.0, 504.0, 315.0]], "bbox_layout": [30.46875, 256.943359375, 545.9375, 325.8203125], "text": ["Des licences individuelles de chasse peuvent \u00eatre d\u00e9livr\u00e9es", "par les conservateurs des for\u00eats et de la d\u00e9fense et restauration", "des sols (D.R.S.). Ces licences sont de deux cat\u00e9gories :"], "label": "Text", "position": 2}, {"bbox_text": [[41.0, 326.0, 537.0, 338.0], [40.0, 342.0, 537.0, 356.0], [40.0, 360.0, 282.0, 374.0]], "bbox_layout": [29.921875, 315.732421875, 547.578125, 384.951171875], "text": ["- Cat\u00e9gorie A : licence dite r\u00e9gionale, valable pour toutes", "les for\u00eats soumises \u00e0 la conservation, non r\u00e9serv\u00e9es, et d\u00e9livr\u00e9e", "contre redevance de 60 dinars."], "label": "Text", "position": 3}, {"bbox_text": [[42.0, 381.0, 534.0, 396.0], [40.0, 399.0, 436.0, 413.0]], "bbox_layout": [29.921875, 371.787109375, 544.296875, 423.916015625], "text": ["- Cat\u00e9gorie B : licence dite locale valable pour un lot d\u00e9ter-", "min\u00e9 et dont la redevance est fix\u00e9e \u00e0 30 dinars."], "label": "Text", "position": 4}, {"bbox_text": [[56.0, 424.0, 535.0, 438.0], [41.0, 441.0, 536.0, 455.0], [40.0, 458.0, 536.0, 472.0], [40.0, 474.0, 536.0, 487.0], [40.0, 492.0, 425.0, 505.0]], "bbox_layout": [30.05859375, 414.853515625, 547.578125, 516.201171875], "text": ["Art. 18. - Des lots de chasse en for\u00eats domaniales sont", "r\u00e9serv\u00e9s au minist\u00e8re du tourisme. Les licences sont d\u00e9livr\u00e9es,", "jusqu'\u00e0 concurrence de 500 fusils, par le conservateur des", "for\u00eats et de la d\u00e9fense et restauration des sols (D.R.S.), \u00e0", "Alger, contre redevance de 30 dinars par fusil."], "label": "Text", "position": 5}, {"bbox_text": [[127.0, 520.0, 536.0, 534.0], [56.0, 521.0, 124.0, 534.0], [40.0, 537.0, 536.0, 551.0], [40.0, 554.0, 538.0, 568.0], [117.0, 571.0, 506.0, 585.0], [40.0, 572.0, 109.0, 585.0], [505.0, 572.0, 537.0, 583.0], [40.0, 588.0, 537.0, 603.0], [40.0, 605.0, 210.0, 619.0]], "bbox_layout": [30.7421875, 509.53125, 548.9453125, 627.96875], "text": ["- Les poudres et munitions ne pourront \u00e9tre", "Art. 19.", "acquises et vendues que par les commer\u00e7ants autoris\u00e9s par", "le pr\u00e9fet, au vu d'un extrait des r\u00f4les apur\u00e9, d\u00e9livr\u00e9 par le", "des contributions diverses. Ces commer\u00e7ants", "receveur", " ne", "pourront d\u00e9livrer les poudres et munitions qu'aux d\u00e9tenteurs", "de permis de chasse."], "label": "Text", "position": 6}, {"bbox_text": [[55.0, 633.0, 537.0, 647.0], [40.0, 651.0, 538.0, 665.0], [41.0, 668.0, 538.0, 682.0], [41.0, 684.0, 226.0, 697.0]], "bbox_layout": [30.87890625, 623.0078125, 550.3125, 708.6328125], "text": ["Il est express\u00e9ment interdit aux chasseurs de se servir de", "bourres de papier, d'\u00e9toupe, de palmier ou de toute autre", "mati\u00e8re inflammable ; ils ne pourront faire usage que de", "bourres incombustibles."], "label": "Text", "position": 7}, {"bbox_text": [[574.0, 17.0, 1055.0, 30.0], [559.0, 35.0, 1055.0, 49.0], [558.0, 50.0, 1056.0, 65.0], [559.0, 67.0, 688.0, 81.0]], "bbox_layout": [547.265625, 8.45703125, 1069.296875, 90.322265625], "text": ["Art, 20. - Les infractions au pr\u00e9sent arr\u00eat\u00e9 seront r\u00e9prim\u00e9es", "conform\u00e9ment \u00e0 la l\u00e9gislation en vigueur. Elles sont recherch\u00e9es", "et constat\u00e9es par tous les agents investis de pouvoirs de", "police judiciaire."], "label": "Text", "position": 8}, {"bbox_text": [[574.0, 95.0, 1056.0, 109.0], [559.0, 114.0, 1056.0, 127.0], [558.0, 129.0, 1057.0, 144.0], [558.0, 147.0, 702.0, 159.0]], "bbox_layout": [546.171875, 85.703125, 1071.484375, 172.01171875], "text": ["Tout agent verbalisateur recoit une prime de trente dinars.", "apr\u00e8s recouvrement du montant de la transaction ou de la", "condamnation ; cette prime est support\u00e9e \u00e0 titre de frais", "par le d\u00e9linquant."], "label": "Text", "position": 9}, {"bbox_text": [[574.0, 175.0, 1055.0, 189.0], [559.0, 190.0, 1056.0, 208.0], [559.0, 208.0, 1057.0, 222.0], [559.0, 226.0, 1057.0, 240.0], [559.0, 241.0, 770.0, 256.0]], "bbox_layout": [548.90625, 164.40185546875, 1070.9375, 265.1513671875], "text": ["Art. 21. - Le chef de service des for\u00eats et de la d\u00e9fense", "et restauration des sols (D.R.S.) et les pr\u00e9fets, sont charg\u00e9s,", "chacun en ce qui le concerne, de l'ex\u00e9cution du pr\u00e9sent arr\u00eat\u00e9.", "qui sera publi\u00e9 au Journal officiel de la R\u00e9publique alg\u00e9rienne", "d\u00e9mocratique et populaire."], "label": "Text", "position": 10}, {"bbox_text": [[574.0, 270.0, 857.0, 285.0]], "bbox_layout": [559.296875, 260.361328125, 862.578125, 295.05859375], "text": ["Fait \u00e0 Alger, le 2 septembre 1965,"], "label": "Text", "position": 11}, {"bbox_text": [[736.0, 301.0, 875.0, 315.0]], "bbox_layout": [729.375, 289.4140625, 885.0, 323.427734375], "text": ["Ahmed MAHSAS."], "label": "Text", "position": 12}, {"bbox_text": [[665.0, 374.0, 955.0, 390.0]], "bbox_layout": [653.90625, 363.2421875, 967.03125, 401.015625], "text": ["MINISTERE DU COMMERCE"], "label": "SectionHeader", "position": 13}, {"bbox_text": [[560.0, 438.0, 1058.0, 453.0], [590.0, 456.0, 765.0, 470.0]], "bbox_layout": [545.8984375, 425.791015625, 1070.9375, 479.287109375], "text": ["Arr\u00eat\u00e9s du 20 juillet 1965 portant d\u00e9l\u00e9gation dans les fonctions", "d'inspecteur principal."], "label": "Text", "position": 14}, {"bbox_text": [[574.0, 490.0, 1057.0, 507.0], [559.0, 505.0, 1060.0, 526.0], [559.0, 525.0, 660.0, 537.0]], "bbox_layout": [549.453125, 481.162109375, 1070.390625, 549.013671875], "text": ["Par arr\u00eat\u00e9 du 20 juillet 1965, M. Ali Belhalfaoui est d\u00e9l\u00e9gu\u00e9", "dans les fonctions d'inspecteur principal du service des enqu\u00eates", "\u00e9conomiques."], "label": "Text", "position": 15}, {"bbox_text": [[574.0, 554.0, 1058.0, 568.0], [559.0, 571.0, 896.0, 585.0]], "bbox_layout": [554.921875, 544.736328125, 1070.390625, 596.865234375], "text": ["Il percevra \u00e0 ce titre, une r\u00e9mun\u00e9ration calcul\u00e9e par r\u00e9f\u00e9rence", "\u00e0 l'\u00e9chelon de d\u00e9but soit l'indice brut 515."], "label": "Text", "position": 16}, {"bbox_text": [[574.0, 604.0, 1058.0, 622.0], [560.0, 621.0, 1057.0, 638.0], [559.0, 640.0, 663.0, 654.0]], "bbox_layout": [551.09375, 595.322265625, 1070.9375, 664.541015625], "text": ["Par arr\u00eat\u00e9 du 20 juillet 1965 M. Ahmed Zagga\u00ef est d\u00e9l\u00e9gu\u00e9.", "dans les fonctions d'inspecteur principal du service des enqu\u00eates", "\u00e9conomiques."], "label": "Text", "position": 17}, {"bbox_text": [[574.0, 669.0, 1059.0, 683.0], [559.0, 686.0, 931.0, 701.0]], "bbox_layout": [552.1875, 659.580078125, 1073.125, 710.0], "text": ["Il percevra \u00e0 ce titre une r\u00e9mun\u00e9ration calcul\u00e9e par r\u00e9f\u00e9rence", "\u00e0 l'\u00e9chelon de d\u00e9but soit l'indice brut de 515."], "label": "Text", "position": 18}, {"bbox_text": [[301.0, 754.0, 378.0, 771.0], [408.0, 754.0, 449.0, 771.0], [476.0, 756.0, 773.0, 773.0]], "bbox_layout": [292.6953125, 744.6875, 788.75, 785.1953125], "text": ["A VIS", "E T", "COMMUNICATIONS"], "label": "SectionHeader", "position": 19}, {"bbox_text": [[40.0, 839.0, 537.0, 857.0], [70.0, 855.0, 537.0, 873.0], [70.0, 875.0, 427.0, 889.0]], "bbox_layout": [29.1015625, 828.76953125, 551.6796875, 897.98828125], "text": ["Avis n\u00ba 30 Z.F. donnant une huiti\u00e8me liste des agriculteurs", "fran\u00e7ais ayant demande \u00e0 transf\u00e9rer en France le produit", "de la r\u00e9alisation de leur derni\u00e8re recolte."], "label": "SectionHeader", "position": 20}, {"bbox_text": [[55.0, 900.0, 534.0, 915.0], [41.0, 916.0, 537.0, 933.0], [40.0, 935.0, 537.0, 949.0], [40.0, 948.0, 537.0, 968.0], [40.0, 968.0, 537.0, 982.0], [40.0, 983.0, 535.0, 1001.0], [40.0, 1002.0, 92.0, 1015.0]], "bbox_layout": [29.6484375, 888.2421875, 548.9453125, 1024.453125], "text": ["L'avis n\u00ba 16 Z.F. publi\u00e9 au Journal officiel n\u00ba 17 du 13 f\u00e9-", "vrier 1964 a d\u00e9fini les conditions dans lesquelles los agriculteurs", "fran\u00e7ais dont les bens ont \u00e9t\u00e9 nationalis\u00e9s, par application", "du d\u00e9cret n\u00ba 63-388 du 1er octobre 1963 seraient autoris\u00e9s \u00e0", "transf\u00e9rer en France le produit de la r\u00e9alisation de leur", "r\u00e9coite de vins et c\u00e9r\u00e9ales, d\u00e9duction faite des passifs d'exploi-", "tation."], "label": "Text", "position": 21}, {"bbox_text": [[574.0, 842.0, 1057.0, 856.0], [559.0, 861.0, 1057.0, 875.0], [559.0, 877.0, 643.0, 891.0]], "bbox_layout": [553.828125, 832.1875, 1070.390625, 901.40625], "text": ["Le pr\u00e9sent avis a pour objet de publier une huiti\u00e8me liste", "des agriculteurs fran\u00e7ais ayant demand\u00e9 \u00e0 b\u00e9n\u00e9ficier de ces", "conditions."], "label": "Text", "position": 22}, {"bbox_text": [[573.0, 906.0, 1056.0, 920.0], [559.0, 922.0, 1058.0, 938.0], [560.0, 940.0, 1057.0, 954.0], [560.0, 956.0, 1058.0, 973.0]], "bbox_layout": [550.0, 895.078125, 1072.03125, 982.0703125], "text": ["Il est rappel\u00e9 que les cr\u00e9anciers des personnes figurant sur", "cette liste doivent faire conna\u00eetre, sous quinzaine, \u00e0 la banque", "de ces derni\u00e8res par lettre recommand\u00e9e avec accus\u00e9 de r\u00e9cep-", "tion, leurs cr\u00e9ances en en indiquant la nature et l'\u00e9ch\u00e9ance."], "label": "Text", "position": 23}, {"bbox_text": [[573.0, 985.0, 1060.0, 999.0], [559.0, 1002.0, 752.0, 1017.0]], "bbox_layout": [550.0, 976.42578125, 1076.40625, 1026.50390625], "text": ["Les diligences pour le recouvrement des sommes dues imme", "combent aux cr\u00e9anciers."], "label": "Text", "position": 24}, {"bbox_text": [[465.0, 1043.0, 630.0, 1057.0]], "bbox_layout": [441.9921875, 1034.53125, 649.84375, 1073.671875], "text": ["I. - Cr\u00e9dit lyonnais,"], "label": "SectionHeader", "position": 25}, {"bbox_text": [[228.0, 1103.0, 344.0, 1117.0], [629.0, 1104.0, 714.0, 1120.0], [891.0, 1104.0, 974.0, 1118.0], [39.0, 1157.0, 425.0, 1172.0], [592.0, 1159.0, 685.0, 1173.0], [808.0, 1159.0, 897.0, 1173.0], [37.0, 1174.0, 493.0, 1191.0], [592.0, 1177.0, 653.0, 1191.0], [808.0, 1178.0, 874.0, 1191.0], [39.0, 1192.0, 501.0, 1206.0], [590.0, 1193.0, 732.0, 1207.0], [807.0, 1193.0, 924.0, 1206.0], [39.0, 1207.0, 509.0, 1222.0], [591.0, 1211.0, 653.0, 1223.0], [807.0, 1211.0, 868.0, 1223.0], [37.0, 1224.0, 478.0, 1238.0], [592.0, 1226.0, 686.0, 1240.0], [807.0, 1226.0, 897.0, 1240.0], [37.0, 1242.0, 511.0, 1256.0], [591.0, 1243.0, 664.0, 1257.0], [807.0, 1243.0, 879.0, 1256.0], [37.0, 1258.0, 487.0, 1275.0], [806.0, 1258.0, 885.0, 1272.0], [589.0, 1260.0, 670.0, 1274.0], [37.0, 1273.0, 457.0, 1290.0], [590.0, 1276.0, 658.0, 1290.0], [807.0, 1276.0, 874.0, 1290.0], [37.0, 1291.0, 518.0, 1306.0], [807.0, 1292.0, 874.0, 1306.0], [591.0, 1293.0, 658.0, 1307.0], [37.0, 1309.0, 457.0, 1323.0], [806.0, 1309.0, 875.0, 1323.0], [590.0, 1310.0, 659.0, 1323.0], [37.0, 1326.0, 464.0, 1342.0], [590.0, 1327.0, 676.0, 1340.0], [805.0, 1327.0, 892.0, 1340.0], [37.0, 1342.0, 434.0, 1359.0], [591.0, 1342.0, 695.0, 1358.0], [806.0, 1343.0, 908.0, 1357.0], [37.0, 1360.0, 188.0, 1374.0], [589.0, 1360.0, 639.0, 1374.0], [805.0, 1361.0, 860.0, 1374.0], [38.0, 1377.0, 187.0, 1391.0], [806.0, 1377.0, 942.0, 1391.0], [591.0, 1378.0, 638.0, 1391.0], [195.0, 1380.0, 448.0, 1390.0]], "bbox_layout": [25.0, 1076.9140625, 1075.3125, 1408.6328125], "text": ["DEMANDEUR", "DOMAINE", "ADRESSE", "Mme Vve Combes \u00e9pouse Cladt ..........................", "A\u00efn Youcef", "A\u00efn Youcef", "M. Verdoux Edmond ", "Remchi", "Tlemcen", "M. Dusseau Victor .", "Sidi Ali Boussidi", "Sidi-Bel-Abb\u00e8s", "Mme Vve Antras Victor .", "Remchi", "Remchi", "Les Consorts Collet .", "A\u00efn Youcef", "A\u00efn Youcef", "Mme Aubert Leonce .", "Hachems", "Hachems", "M. Bos Eug\u00e8ne ", "Matemore", "Matemore", "M. Burriel Lucien .", "Maoussa", "Maoussa", "Mme Soldadier Genevi\u00e8ve ", "Maoussa", "Maoussa", "Mme Schneberger H\u00e9l\u00e8ne .", "Boutlelis", "Boutlelis", "M. Creyssels Marcel .", "Boudouaou", "Boudouaou", "M. Suet Alphonse ", "A\u00efn El Arba", "Ain El Arba", "M. Duplessy L\u00e9on", "Rallei", "Skikda", "M. Schwab Emile", "A\u00efn T\u00e9mouchent", "Terga", ".."], "label": "Table", "position": 26}]}, {"index": 7, "page": [{"bbox_text": [[403.0, 22.0, 745.0, 37.0]], "bbox_layout": [398.515625, 12.430419921875, 755.390625, 47.982177734375], "text": ["II. - Cr\u00e9dit foncier d'Alg\u00e9rie et de Tunisie."], "label": "PageHeader", "position": 0}, {"bbox_text": [[264.0, 72.0, 377.0, 86.0], [656.0, 72.0, 743.0, 85.0], [918.0, 72.0, 998.0, 86.0], [75.0, 137.0, 462.0, 152.0], [619.0, 138.0, 717.0, 152.0], [835.0, 141.0, 931.0, 155.0], [76.0, 156.0, 524.0, 170.0], [621.0, 156.0, 711.0, 170.0], [835.0, 157.0, 965.0, 170.0], [106.0, 170.0, 540.0, 191.0], [76.0, 172.0, 101.0, 183.0], [621.0, 173.0, 720.0, 187.0], [835.0, 175.0, 875.0, 187.0], [75.0, 189.0, 549.0, 203.0], [622.0, 189.0, 700.0, 203.0], [835.0, 190.0, 875.0, 203.0], [75.0, 205.0, 542.0, 223.0], [621.0, 206.0, 652.0, 220.0], [835.0, 207.0, 889.0, 221.0], [74.0, 221.0, 549.0, 241.0], [622.0, 222.0, 703.0, 235.0], [835.0, 225.0, 914.0, 238.0], [75.0, 240.0, 488.0, 254.0], [622.0, 240.0, 672.0, 253.0], [835.0, 241.0, 882.0, 254.0], [75.0, 254.0, 512.0, 275.0], [622.0, 256.0, 692.0, 270.0], [835.0, 259.0, 875.0, 271.0], [75.0, 272.0, 456.0, 289.0], [622.0, 273.0, 670.0, 287.0], [834.0, 274.0, 900.0, 289.0], [307.0, 300.0, 758.0, 319.0], [779.0, 303.0, 843.0, 318.0], [77.0, 333.0, 551.0, 347.0], [622.0, 333.0, 670.0, 347.0], [834.0, 333.0, 985.0, 347.0], [77.0, 348.0, 558.0, 367.0], [835.0, 350.0, 888.0, 366.0], [622.0, 351.0, 691.0, 365.0], [106.0, 366.0, 560.0, 380.0], [835.0, 366.0, 1083.0, 380.0], [77.0, 367.0, 100.0, 378.0], [622.0, 367.0, 726.0, 380.0], [76.0, 383.0, 557.0, 399.0], [835.0, 383.0, 1085.0, 397.0], [622.0, 385.0, 665.0, 397.0], [75.0, 399.0, 552.0, 416.0], [622.0, 400.0, 690.0, 414.0], [835.0, 400.0, 990.0, 414.0], [76.0, 416.0, 471.0, 432.0], [835.0, 416.0, 885.0, 432.0], [622.0, 417.0, 702.0, 431.0], [76.0, 430.0, 472.0, 451.0], [835.0, 432.0, 1083.0, 447.0], [622.0, 435.0, 706.0, 449.0], [75.0, 450.0, 397.0, 463.0], [835.0, 450.0, 903.0, 464.0], [622.0, 451.0, 706.0, 464.0], [81.0, 488.0, 98.0, 501.0], [484.0, 492.0, 672.0, 506.0], [76.0, 520.0, 323.0, 534.0], [622.0, 521.0, 676.0, 535.0], [835.0, 521.0, 889.0, 535.0], [76.0, 537.0, 376.0, 554.0], [622.0, 539.0, 689.0, 553.0], [835.0, 539.0, 903.0, 553.0], [77.0, 553.0, 567.0, 573.0], [107.0, 572.0, 565.0, 586.0], [836.0, 589.0, 1086.0, 604.0], [106.0, 590.0, 146.0, 603.0], [156.0, 590.0, 556.0, 605.0], [622.0, 590.0, 795.0, 604.0], [77.0, 605.0, 535.0, 624.0], [835.0, 606.0, 889.0, 620.0], [622.0, 608.0, 677.0, 621.0], [379.0, 647.0, 777.0, 662.0], [74.0, 675.0, 389.0, 694.0], [835.0, 677.0, 1018.0, 691.0], [622.0, 679.0, 802.0, 691.0], [198.0, 725.0, 444.0, 739.0], [605.0, 725.0, 825.0, 739.0], [687.0, 749.0, 1084.0, 763.0], [606.0, 750.0, 678.0, 760.0], [86.0, 759.0, 557.0, 774.0], [604.0, 784.0, 810.0, 799.0], [196.0, 789.0, 448.0, 805.0], [603.0, 814.0, 1086.0, 828.0], [89.0, 819.0, 332.0, 833.0], [588.0, 831.0, 1087.0, 845.0], [89.0, 840.0, 568.0, 858.0], [589.0, 848.0, 1086.0, 862.0], [74.0, 858.0, 567.0, 876.0], [589.0, 865.0, 1086.0, 879.0], [73.0, 874.0, 568.0, 893.0], [589.0, 881.0, 841.0, 898.0], [73.0, 893.0, 240.0, 906.0], [604.0, 912.0, 1084.0, 925.0], [119.0, 915.0, 217.0, 931.0], [264.0, 918.0, 343.0, 931.0], [591.0, 930.0, 1085.0, 940.0], [118.0, 940.0, 314.0, 954.0], [588.0, 945.0, 1085.0, 959.0], [588.0, 961.0, 1084.0, 976.0], [118.0, 963.0, 452.0, 977.0], [589.0, 977.0, 718.0, 995.0], [87.0, 985.0, 566.0, 1001.0], [98.0, 1001.0, 565.0, 1020.0], [73.0, 1002.0, 98.0, 1012.0], [604.0, 1009.0, 1084.0, 1020.0], [73.0, 1018.0, 567.0, 1035.0], [588.0, 1024.0, 1085.0, 1038.0], [71.0, 1035.0, 564.0, 1053.0], [589.0, 1043.0, 826.0, 1055.0], [88.0, 1057.0, 567.0, 1076.0], [73.0, 1075.0, 569.0, 1091.0], [603.0, 1076.0, 1085.0, 1088.0], [72.0, 1094.0, 142.0, 1107.0], [604.0, 1106.0, 1086.0, 1117.0], [588.0, 1122.0, 1086.0, 1136.0], [71.0, 1138.0, 565.0, 1153.0], [588.0, 1140.0, 1085.0, 1152.0], [255.0, 1156.0, 378.0, 1170.0], [588.0, 1156.0, 717.0, 1170.0], [625.0, 1178.0, 1085.0, 1192.0], [84.0, 1183.0, 565.0, 1202.0], [625.0, 1197.0, 1085.0, 1208.0], [588.0, 1198.0, 621.0, 1208.0], [174.0, 1207.0, 462.0, 1222.0], [588.0, 1214.0, 903.0, 1226.0], [210.0, 1230.0, 423.0, 1246.0], [603.0, 1243.0, 1036.0, 1254.0], [148.0, 1254.0, 487.0, 1268.0], [603.0, 1266.0, 1084.0, 1275.0], [170.0, 1276.0, 462.0, 1290.0], [605.0, 1288.0, 1084.0, 1300.0], [177.0, 1293.0, 457.0, 1307.0], [84.0, 1314.0, 565.0, 1333.0], [603.0, 1318.0, 1083.0, 1328.0], [70.0, 1332.0, 254.0, 1346.0]], "bbox_layout": [59.7265625, 23.49609375, 1101.5625, 1346.42578125], "text": ["DEMANDEUR", "DOMAINE", "ADRESSE", "M. Guennebaud Jacques ", "Mouza\u00efaville", "Mouza\u00efaville", "M. Darre Henri ", "Bensekrane", "A\u00efn T\u00e9mouchent", "Delot Charles .", "M", "Mostaganem", "Oran", "Mme Lacet Henriette ", "El Malah", "Oran", "Mme Vve Curetti Emile .", "Foy", "Skikda", "Mme Vve Hugonnot ", "Jemmapes", "Jemmapes", "M. Tourmemire Georges .", "Tiaret", "Tiaret", "M. Marty Fernand ", "Bethioua", "Oran", "M. Domerck Victor .", "Nador", "Mascars", "III. - Banque nationale pour le commerce et l'Industrie", "Afrique.", "M. Marcenaro Antoine .", "Gdyel", "11, rue Cols, Paris", "M. Mepah Louis ", "Tassin", "Hennaya", "Cochet Armand .", "Saint Jean L'Herm (Hte-Gar.)", "M.", "Beni Ouzane", "M. Rostain Paul ", "48, rue du Bourget, Narbonne", "Oran", "M. Domas Andr\u00e9 ", "Medjana", "Bordj Bou Arreridj", "M. Gravier Fernand .", "Valmy", "El Kerma", "M. Monticelli L\u00e9on ", "Vernet Les Bains (Pyr. Orient.)", "Misserghin", "M. Rostaing Henri .", "Tlemcen", "A\u00efn Sebra", " -", "IV. - Soci\u00e9t\u00e9 g\u00e9n\u00e9rale.", "M. Albert Alfred ... .. .", "Tenira", "Tenira", "M. Combes Henri ", "Maoussa", "Maoussa", "Mme Vve Berger Alice, agissant en qualit\u00e9 de g\u00e9rante de la", "Soci\u00e9t\u00e9 civile et particuli\u00e8re d'exploitation, Domaine Saint-", "89, rue Ben M'Hidi Larbi, Oran", "Jean", "..", "Oued Tletat El Braya", "M. Granie Louis .", "Tassin", "Tassin", "V. - Compagnie fran\u00e7aise de cr\u00e9dit et de banque", "Mme Vve Rouquette .........................", "Hammam Bou Hadjar", "Hammam Bou Hadjar", "MARCHES. - Appels d'offres", "Base de l'appel d'offres :", "et transport \u00e0 pied d'\u0153uvre de tout venant.", "Concasse", "MINISTERE DU TRAVAIL ET DES AFFAIRES SOCIALES", "Pr\u00e9sentation des offres :", "Sous-direction de l'action sociale", "Les entrepreneurs pourront recevoir les dossiers n\u00e9cessaires", "I. - Objet de l'appel d'offres,", "\u00e0 la pr\u00e9sentation de leurs offres en faisant la demande \u00e0 :", "Dans le cadre de l'aide aux n\u00e9cessiteux, le minist\u00e8re du", "M. l'ing\u00e9nieur en chef de la circonscription des travaux publics", "travail et des affaires sociales (sous-direction de l'action sociale)", "et de l'hydraulique du d\u00e9partement d'Annaba, 12, boulevard", "lance un appel d'offres pour la fourniture de cent mille", "du 1er Novembre 1954, Annaba.", "couvertures (100.000).", "La date limite de r\u00e9ception des offres est fix\u00e9e au 20 sep-", "Dimension :", "220 \u00d7 180", "tembre 1965 \u00e0 17 heures ; elles devront \u00eatre adress\u00e9es \u00e0", "Poids minimum : 1,6 kg", "l'ing\u00e9nieur en chef du service des \u00e9tudes g\u00e9n\u00e9rales et grands", "travaux hydrauliques, B.P. n\u00ba 1, 225, boulevard Colonel Bougara,", "Composition mixte : 50 % laine minimum.", "El-Biar (Alger).", "Les offres devront \u00eatre adress\u00e9es au minist\u00e8re du travail", "des affaires sociales (sous-direction de l'action sociale)", "et", "Les offres pourront \u00eatre adress\u00e9es par la poste, sous pli", "28, rue Hassiba Ben Bouali, Alger, par voie postale et sous", "recommand\u00e9 ou d\u00e9pos\u00e9es dans les bureaux de l'ing\u00e9nieur en", "pli recommand\u00e9 cachet\u00e9 avant le 15 septembre 1965, 18heures.", "chef pr\u00e9cit\u00e9, contre r\u00e9c\u00e9piss\u00e9.", "Toute information suppl\u00e9mentaire et relative au pr\u00e9sent", "appel d'offres pourra \u00eatre demand\u00e9e \u00e0 l'adresse ci-dessus", "Les offres des entreprises devront etre accompagn\u00e9es :", "indiqu\u00e9e.", "- d'une note indiquant leurs moyens techniques, le lieu,", "la date, la nature et l'importance des travaux qu'elles ont", "Service des \u00e9tudes g\u00e9n\u00e9rales et des grands travaux hydrauliques", "ex\u00e9cut\u00e9s, \u00e0 cette note sera joint le certificat de qualification", "El-Biar (Alger)", "professionnelle ;", "de l'attestation d\u00e9livr\u00e9e par la caisse de compensation", "Un appel d'offres ouvert est lanc\u00e9 pour l'op\u00e9ration suivante :", "allocations familiales et cong\u00e9s pay\u00e9s certifiant que", "des", "Caisse alg\u00e9rienne de d\u00e9veloppement", "l'entrepreneur a rempli ses obligations.", "Op\u00e9ration n\u00ba 12.11.0.6.19.03", "Les dossiers pourront \u00eatre consult\u00e9s dans les bureaux,", "Construction du barrage de Bou-Namoussa", "- soit, de l'ing\u00e9nieur en chef de la circonscription d'Annaba,", "Construction des C.D. n\u00ba 105 et 118", "- soit, de l'ing\u00e9nieur en chef du S.E.G.G.T.H. \u00e0 El-Biar.", "autour de la retenue du barrage", "Fourniture de tout venant dont le co\u00fbt approximatif est", "Le d\u00e9lai pendant lequel les candidats seront engag\u00e9s par", "evalu\u00e9 \u00e0 : 600.000 DA."], "label": "Form", "position": 1}]}]