[{"index": 1, "page": [{"bbox_text": [[229.0, 38.0, 836.0, 56.0]], "bbox_layout": [218.338623046875, 28.36669921875, 849.8779296875, 71.6943359375], "text": ["DECRETS, ARRETES, DECISIONS ET CIRCULAIRES"], "label": "SectionHeader", "position": 0}, {"bbox_text": [[68.0, 109.0, 488.0, 125.0]], "bbox_layout": [56.84326171875, 97.92236328125, 503.92578125, 137.40478515625], "text": ["MINISTERE DE LA DEFENSE NATIONALE"], "label": "SectionHeader", "position": 1}, {"bbox_text": [[33.0, 170.0, 519.0, 181.0], [64.0, 185.0, 520.0, 197.0]], "bbox_layout": [27.1209716796875, 158.93310546875, 533.5205078125, 212.685546875], "text": ["D\u00e9cret n\u00ba 65-274 du 11 novembre 1965 portant cr\u00e9ation de", "l'Institut national de sant\u00e9 de l'Arm\u00e9e nationale populaire."], "label": "Text", "position": 2}, {"bbox_text": [[47.0, 231.0, 519.0, 242.0], [34.0, 249.0, 67.0, 260.0]], "bbox_layout": [27.3760986328125, 219.6875, 531.4794921875, 271.1328125], "text": ["Le Chef du Gouvernement, Pr\u00e9sident du Conseil des minis-", "tres."], "label": "Text", "position": 3}, {"bbox_text": [[49.0, 276.0, 519.0, 286.0], [34.0, 292.0, 522.0, 303.0], [34.0, 308.0, 519.0, 319.0]], "bbox_layout": [26.1004638671875, 262.0703125, 534.541015625, 332.314453125], "text": ["Vu la loi n\u00ba 62-157 du 31 d\u00e9cembre 1962 tendant \u00e0 la recon-", "duction de la l\u00e9gislation en vigueur au 31 d\u00e9cembre 1962, sauf", "dans ses dispositions contraires \u00e0 la souverainet\u00e9 nationale ;"], "label": "Text", "position": 4}, {"bbox_text": [[51.0, 335.0, 524.0, 347.0], [33.0, 352.0, 363.0, 365.0]], "bbox_layout": [26.3555908203125, 323.59375, 533.01025390625, 374.697265625], "text": ["Vu la loi du 30 d\u00e9cembre 1909 constituant en universit\u00e9 les", "\u00e9coles d'enseignement sup\u00e9rieur d'Alger ;"], "label": "Text", "position": 5}, {"bbox_text": [[50.0, 381.0, 520.0, 391.0], [36.0, 396.0, 464.0, 408.0]], "bbox_layout": [26.993408203125, 367.34375, 536.58203125, 418.7890625], "text": ["Vu le d\u00e9cret du 28 d\u00e9cembre 1885, modifi\u00e9, sur l'organisation", "des facult\u00e9s et des \u00e9coles d'enseignement sup\u00e9rieur ;"], "label": "Text", "position": 6}, {"bbox_text": [[51.0, 423.0, 522.0, 435.0], [33.0, 440.0, 341.0, 453.0]], "bbox_layout": [26.1004638671875, 412.802734375, 536.07177734375, 464.248046875], "text": ["Vu le d\u00e9cret n\u00ba 65-188 du 13 juillet 1965 relatif \u00e0 la facult\u00e9", "mixte de m\u00e9decine et de pharmacie ;"], "label": "Text", "position": 7}, {"bbox_text": [[35.0, 469.0, 306.0, 481.0]], "bbox_layout": [34.2645263671875, 457.236328125, 318.193359375, 491.591796875], "text": ["Le Conseil des ministres entendu,"], "label": "Text", "position": 8}, {"bbox_text": [[122.0, 502.0, 196.0, 515.0]], "bbox_layout": [103.531494140625, 490.390625, 213.59130859375, 524.0625], "text": ["D\u00e9cr\u00e8te :"], "label": "Text", "position": 9}, {"bbox_text": [[51.0, 530.0, 522.0, 543.0], [34.0, 548.0, 467.0, 560.0]], "bbox_layout": [26.483154296875, 519.1015625, 536.58203125, 571.9140625], "text": ["Article 1\u00ba. - Il est cr\u00e9\u00e9 un institut national de sant\u00e9 de", "l'arm\u00e9e nationale populaire dont le si\u00e8ge est \u00e0 Alger."], "label": "Text", "position": 10}, {"bbox_text": [[48.0, 576.0, 390.0, 588.0]], "bbox_layout": [37.708740234375, 564.560546875, 400.8544921875, 598.916015625], "text": ["Art. 2. - Le dit institut a pour mission :"], "label": "Text", "position": 11}, {"bbox_text": [[51.0, 604.0, 521.0, 615.0], [72.0, 618.0, 521.0, 632.0], [72.0, 637.0, 188.0, 649.0]], "bbox_layout": [42.811279296875, 592.587890625, 533.5205078125, 660.439453125], "text": ["- d'assurer le recrutement et l'\u00e9ducation physique et mili-", "taire des personnels du service de sant\u00e9 de l'arm\u00e9e natio-", "nale populaire,"], "label": "ListItem", "position": 12}, {"bbox_text": [[52.0, 665.0, 524.0, 674.0], [74.0, 679.0, 495.0, 693.0]], "bbox_layout": [40.770263671875, 651.71875, 537.6025390625, 703.84765625], "text": ["- de collaborer \u00e0 l'enseignement technique donn\u00e9 aux \u00e9l\u00e8ves", "par les \u00e9tablissements vis\u00e9s \u00e0 l'article 3 ci-dessous,"], "label": "ListItem", "position": 13}, {"bbox_text": [[52.0, 708.0, 522.0, 720.0], [72.0, 725.0, 523.0, 737.0], [74.0, 742.0, 160.0, 756.0]], "bbox_layout": [41.025390625, 697.51953125, 536.58203125, 764.00390625], "text": ["- de compl\u00e9ter cet enseignement par une formation profes-", "sionnelle m\u00e9dicale militaire sp\u00e9ciale, th\u00e9orique, pratique", "et clinique."], "label": "ListItem", "position": 14}, {"bbox_text": [[51.0, 769.0, 523.0, 780.0], [37.0, 787.0, 523.0, 797.0], [35.0, 802.0, 523.0, 813.0], [35.0, 819.0, 524.0, 829.0], [35.0, 834.0, 523.0, 845.0], [37.0, 852.0, 449.0, 862.0]], "bbox_layout": [28.26904296875, 758.359375, 537.6025390625, 872.6953125], "text": ["Art. 3. - Les \u00e9l\u00e8ves de l'institut national de sant\u00e9 de l'arm\u00e9e", "nationale populaire suivent, selon le cas, les cours de la facult\u00e9", "de m\u00e9decine et de pharmacie, de la facult\u00e9 des sciences, de", "la facult\u00e9 de droit et des sciences \u00e9conomiques, des \u00e9coles et", "instituts v\u00e9t\u00e9rinaires, de l'institut d'odonto-stomatologie ou des", "\u00e9tablissements de formation para-m\u00e9dicale d'Alger."], "label": "Text", "position": 15}, {"bbox_text": [[51.0, 879.0, 110.0, 892.0], [114.0, 879.0, 523.0, 888.0], [36.0, 894.0, 523.0, 907.0], [34.0, 913.0, 294.0, 924.0]], "bbox_layout": [26.3555908203125, 866.3671875, 534.541015625, 934.21875], "text": ["Art. 4.", "- L'enseignement clinique est assur\u00e9 par l'h\u00f4pital", "central d'instruction de l'arm\u00e9e nationale populaire qui a rang", "de centre hospitalier universitaire."], "label": "Text", "position": 16}, {"bbox_text": [[51.0, 941.0, 523.0, 950.0], [36.0, 956.0, 524.0, 966.0], [37.0, 974.0, 523.0, 982.0], [34.0, 989.0, 314.0, 1000.0]], "bbox_layout": [26.483154296875, 927.20703125, 534.541015625, 1011.46484375], "text": ["Art. 5. - Le ministre de la d\u00e9fense nationale fixe le nombre", "et la r\u00e9partition des chaires et des postes d'enseignement", "confi\u00e9s aux professeurs agr\u00e9g\u00e9s en exercice dans le service de", "sant\u00e9 de l'arm\u00e9e nationale populaire."], "label": "Text", "position": 17}, {"bbox_text": [[51.0, 1015.0, 524.0, 1027.0], [36.0, 1034.0, 429.0, 1043.0]], "bbox_layout": [26.993408203125, 1004.453125, 534.541015625, 1055.8984375], "text": ["Art. 6. - L'institut national de sant\u00e9 de l'arm\u00e9e nationale", "populaire regoit les cat\u00e9gories d'\u00e9l\u00e8ves suivantes :"], "label": "Text", "position": 18}, {"bbox_text": [[51.0, 1062.0, 524.0, 1070.0], [35.0, 1076.0, 523.0, 1088.0], [36.0, 1094.0, 194.0, 1107.0]], "bbox_layout": [26.483154296875, 1047.51953125, 535.5615234375, 1115.37109375], "text": ["a) les \u00e9l\u00e8ves officiers m\u00e9decins, pharmaciens, dentistes et", "v\u00e9t\u00e9rinaires, choisis parmi les \u00e9tudiants des facult\u00e9s, \u00e9coles", "et instituts alg\u00e9riens."], "label": "Text", "position": 19}, {"bbox_text": [[49.0, 1122.0, 524.0, 1130.0]], "bbox_layout": [37.8363037109375, 1109.7265625, 535.5615234375, 1143.3984375], "text": ["b) les \u00e9l\u00e8ves officiers d'administration du service de sant\u00e9."], "label": "Text", "position": 20}, {"bbox_text": [[50.0, 1150.0, 525.0, 1158.0], [35.0, 1165.0, 523.0, 1177.0], [36.0, 1184.0, 72.0, 1194.0]], "bbox_layout": [26.8658447265625, 1137.75390625, 537.6025390625, 1206.97265625], "text": ["c) les m\u00e9decins officiers, pharmaciens officiers, chirurgiens", "dentistes officiers et v\u00e9t\u00e9rinaires officiers en stage d'applica-", "tion."], "label": "Text", "position": 21}, {"bbox_text": [[50.0, 1211.0, 525.0, 1219.0], [36.0, 1225.0, 525.0, 1238.0], [36.0, 1242.0, 525.0, 1253.0], [36.0, 1258.0, 314.0, 1271.0]], "bbox_layout": [26.3555908203125, 1197.2265625, 537.09228515625, 1281.484375], "text": ["d) les infirmiers \u00e9l\u00e8ves sous-officiers et les sous-officiers", "du service de sant\u00e9 en stage d'application et de pr\u00e9paration", "au brevet de ma\u00eetre infirmier ainsi que les sous-officiers", "d'administration du service de sant\u00e9."], "label": "Text", "position": 22}, {"bbox_text": [[50.0, 1286.0, 523.0, 1298.0], [34.0, 1304.0, 524.0, 1313.0]], "bbox_layout": [25.7177734375, 1274.47265625, 539.13330078125, 1325.91796875], "text": ["e) les infirmiers \u00e9l\u00e8ves sous-officiers et les sous-officiers", "du service de sant\u00e9 en stage de formation d'infirmier-major."], "label": "Text", "position": 23}, {"bbox_text": [[69.0, 1331.0, 524.0, 1343.0], [34.0, 1347.0, 249.0, 1360.0]], "bbox_layout": [24.697265625, 1319.58984375, 533.01025390625, 1371.03515625], "text": ["les \u00e9l\u00e8ves infirmi\u00e8res dipl\u00f4m\u00e9es du service de sant\u00e9 de", "l'arm\u00e9e nationale populaire."], "label": "Text", "position": 24}, {"bbox_text": [[556.0, 104.0, 1028.0, 115.0], [542.0, 121.0, 1025.0, 131.0], [542.0, 138.0, 741.0, 150.0]], "bbox_layout": [530.869140625, 93.3935546875, 1040.712890625, 162.44140625], "text": ["Le ministre de la d\u00e9fense nationale fixe annuellement le", "nombre d'\u00e9l\u00e8ves par cat\u00e9gorie et les conditions, titres et dipl\u00f4-", "mes exig\u00e9s des candidats."], "label": "Text", "position": 25}, {"bbox_text": [[557.0, 166.0, 1029.0, 176.0], [542.0, 182.0, 1028.0, 191.0], [542.0, 199.0, 1029.0, 208.0]], "bbox_layout": [533.42041015625, 155.087890625, 1041.22314453125, 223.28125], "text": ["Art. 7. - Les \u00e9l\u00e8ves sous-officiers et assimil\u00e9s sont group\u00e9s", "dans une \u00e9cole de sous-officiers annex\u00e9e dite centre de forma-", "tion du personnel para-m\u00e9dical de l'arm\u00e9e nationale populaire."], "label": "Text", "position": 26}, {"bbox_text": [[557.0, 227.0, 1030.0, 236.0], [541.0, 244.0, 889.0, 254.0]], "bbox_layout": [531.37939453125, 216.953125, 1041.22314453125, 266.689453125], "text": ["Les \u00e9l\u00e8ves officiers sont group\u00e9s dans une \u00e9cole d'officiers", "et les officiers dans une \u00e9cole d'application."], "label": "Text", "position": 27}, {"bbox_text": [[558.0, 270.0, 1029.0, 281.0], [542.0, 288.0, 1029.0, 297.0], [542.0, 304.0, 1029.0, 313.0], [542.0, 321.0, 1029.0, 329.0], [542.0, 336.0, 1029.0, 346.0], [542.0, 353.0, 1028.0, 362.0], [542.0, 370.0, 695.0, 382.0]], "bbox_layout": [530.869140625, 260.01953125, 1044.794921875, 391.787109375], "text": ["Art. 8. - L'h\u00f4pital central d'instruction de l'arm\u00e9e nationale", "populaire, le centre de recherches et d'\u00e9tudes scientifiques", "de l'arm\u00e9e nationale populaire, le mus\u00e9e du service de sant\u00e9", "de l'arm\u00e9e de lib\u00e9ration nationale et de l'arm\u00e9e nationale", "populaire, une compagnie m\u00e9dicale et des publications compl\u00e8-", "tent les moyens de l'institut national de sant\u00e9 de l'arm\u00e9e", "nationale populaire."], "label": "Text", "position": 28}, {"bbox_text": [[557.0, 396.0, 1028.0, 406.0], [543.0, 413.0, 1029.0, 423.0], [542.0, 428.0, 1028.0, 439.0], [542.0, 446.0, 1030.0, 456.0], [542.0, 462.0, 693.0, 476.0]], "bbox_layout": [533.9306640625, 385.1171875, 1043.7744140625, 484.4140625], "text": ["Art. 9. - Le ministre de la d\u00e9fense nationale fixe les statuts", "et r\u00e8glements relatifs aux service int\u00e9rieur, programme et", "r\u00e8gles d'administration et de gestion de l'institut national", "de sant\u00e9 de l'arm\u00e9e nationale populaire et des centres et", "formations annexes."], "label": "Text", "position": 29}, {"bbox_text": [[558.0, 490.0, 1031.0, 500.0], [542.0, 507.0, 1029.0, 515.0], [542.0, 522.0, 1031.0, 532.0], [543.0, 540.0, 1025.0, 548.0], [543.0, 555.0, 1031.0, 565.0], [542.0, 572.0, 1031.0, 580.0], [542.0, 589.0, 619.0, 603.0]], "bbox_layout": [532.91015625, 478.427734375, 1043.7744140625, 609.853515625], "text": ["Art. 10. - Le ministre de la d\u00e9fense nationale, le ministre", "des finances et du plan, le ministre de l'\u00e9ducation nationale", "et le ministre de la sant\u00e9 publique sont charg\u00e9s, chacun en", "ce qui le concerne, de l'ex\u00e9cution du pr\u00e9sent d\u00e9cret qui prendra", "effet \u00e0 compter du 1\u00aa novembre 1964 et qui sera publi\u00e9 au", "Journal officiel de la R\u00e9publique alg\u00e9rienne d\u00e9mocratique et", "populaire."], "label": "Text", "position": 30}, {"bbox_text": [[558.0, 616.0, 830.0, 627.0]], "bbox_layout": [545.15625, 604.892578125, 840.693359375, 639.248046875], "text": ["Fait \u00e0 Alger, le 11 novembre 1965."], "label": "Text", "position": 31}, {"bbox_text": [[817.0, 639.0, 1000.0, 654.0]], "bbox_layout": [805.3857421875, 629.84375, 1013.1591796875, 664.8828125], "text": ["Houari BOUMEDIENE."], "label": "Text", "position": 32}, {"bbox_text": [[577.0, 721.0, 996.0, 734.0]], "bbox_layout": [560.97412109375, 707.7734375, 1008.56689453125, 748.28125], "text": ["MINISTERE DES FINANCES ET DU PLAN"], "label": "SectionHeader", "position": 33}, {"bbox_text": [[542.0, 779.0, 1025.0, 787.0], [573.0, 795.0, 1017.0, 803.0]], "bbox_layout": [535.46142578125, 765.87890625, 1039.18212890625, 821.42578125], "text": ["D\u00e9cret n\u00ba 65-254 du 14 octobre 1965 portant virement de cr\u00e9-", "dit au minist\u00e8re de la d\u00e9fense nationale (rectificatif)."], "label": "Text", "position": 34}, {"bbox_text": [[646.0, 837.0, 920.0, 849.0]], "bbox_layout": [640.57373046875, 825.3515625, 934.06982421875, 860.390625], "text": ["(J.O. N\u00ba 86 DU 19 OCTOBRE 1965)"], "label": "Text", "position": 35}, {"bbox_text": [[559.0, 867.0, 739.0, 879.0]], "bbox_layout": [543.115234375, 856.11328125, 752.9296875, 889.78515625], "text": ["Page 901, 2\u00e8me colonne,"], "label": "Text", "position": 36}, {"bbox_text": [[633.0, 894.0, 729.0, 907.0]], "bbox_layout": [610.97900390625, 884.82421875, 741.19384765625, 918.49609375], "text": ["Au lieu de :"], "label": "Text", "position": 37}, {"bbox_text": [[559.0, 922.0, 1031.0, 934.0], [545.0, 940.0, 1031.0, 948.0], [544.0, 955.0, 1031.0, 966.0], [543.0, 973.0, 923.0, 982.0]], "bbox_layout": [533.9306640625, 910.1171875, 1042.75390625, 994.375], "text": ["Art. 2. - Est ouvert sur 1965, un cr\u00e9dit de deux millions", "deux cent mille dinars (2.200.000 DA), applicable au budget", "du minist\u00e8re de la d\u00e9fense nationale, chapitre 32-23 \u00ab Habil-", "lement campement - couchage ameublement \u00bb."], "label": "Text", "position": 38}, {"bbox_text": [[633.0, 1001.0, 680.0, 1013.0]], "bbox_layout": [618.6328125, 990.09765625, 689.658203125, 1023.76953125], "text": ["Lire :"], "label": "Text", "position": 39}, {"bbox_text": [[559.0, 1029.0, 1031.0, 1038.0], [545.0, 1043.0, 1032.0, 1056.0], [543.0, 1062.0, 1031.0, 1070.0], [543.0, 1076.0, 949.0, 1088.0]], "bbox_layout": [535.9716796875, 1015.390625, 1043.7744140625, 1099.6484375], "text": ["Art. 2. - Est ouvert sur 1965, un cr\u00e9dit de deux millions", "deux cent mille dinars (2.200.000 DA), applicable au budget", "du minist\u00e8re de la d\u00e9fense nationale, chapitre 32-22 \u00ab Habil-", "lement - campement - couchage ameublement \u00bb."], "label": "Text", "position": 40}, {"bbox_text": [[561.0, 1106.0, 778.0, 1117.0]], "bbox_layout": [553.3203125, 1096.73828125, 819.2626953125, 1130.41015625], "text": ["(Le reste sans changement)."], "label": "Text", "position": 41}, {"bbox_text": [[545.0, 1161.0, 1031.0, 1171.0], [574.0, 1178.0, 1031.0, 1186.0]], "bbox_layout": [533.9306640625, 1149.375, 1045.8154296875, 1202.1875], "text": ["Arr\u00eat\u00e9 du 21 septembre 1965 portant cr\u00e9ation d'une recette", "des contributions diverses d\u00e9nomm\u00e9e \u00ab Alger-soci\u00e9t\u00e9s \u00bb."], "label": "Text", "position": 42}, {"bbox_text": [[559.0, 1221.0, 854.0, 1233.0]], "bbox_layout": [552.2998046875, 1210.8984375, 866.2060546875, 1244.5703125], "text": ["Le ministre des finances et du plan,"], "label": "Text", "position": 43}, {"bbox_text": [[559.0, 1250.0, 1031.0, 1260.0], [543.0, 1267.0, 1031.0, 1276.0], [543.0, 1282.0, 1031.0, 1294.0], [545.0, 1300.0, 589.0, 1313.0]], "bbox_layout": [533.9306640625, 1239.609375, 1043.7744140625, 1322.5], "text": ["Vu la loi n\u00ba 62-157 du 31 d\u00e9cembre 1962 tendant \u00e0 la", "reconduction de la l\u00e9gislation en vigueur au 31 d\u00e9cembre 1962,", "sauf dans ses dispositions contraires \u00e0 la souverainet\u00e9 natio-", "nale ;"], "label": "Text", "position": 44}, {"bbox_text": [[795.0, 1325.0, 1029.0, 1336.0], [736.0, 1326.0, 795.0, 1337.0], [593.0, 1327.0, 735.0, 1340.0], [543.0, 1342.0, 792.0, 1358.0]], "bbox_layout": [534.44091796875, 1315.48828125, 1043.26416015625, 1368.30078125], "text": ["du 10 juillet 1965 portant", "65-182", "l'ordonnance n\u00ba", "constitution du Gouvernement ;"], "label": "Text", "position": 45}]}, {"index": 2, "page": [{"bbox_text": [[41.0, 21.0, 518.0, 31.0], [27.0, 37.0, 518.0, 47.0], [27.0, 54.0, 141.0, 67.0]], "bbox_layout": [19.51953125, 10.166015625, 533.359375, 80.5810546875], "text": ["Vu l'arr\u00eat\u00e9 du 20 janvier 1959, fixant la consistance des", "recettes des contributions diverses et l'ensemble des textes qui", "l'ont modifi\u00e9 :"], "label": "Text", "position": 0}, {"bbox_text": [[41.0, 83.0, 520.0, 91.0], [28.0, 99.0, 518.0, 108.0], [27.0, 115.0, 249.0, 127.0]], "bbox_layout": [19.1328125, 70.194091796875, 534.1328125, 140.3955078125], "text": ["Vu l'arr\u00eat\u00e9 du 9 ao\u00fbt 1965 portant cr\u00e9ation d'une inspection", "centrale des imp\u00f4ts directs, d\u00e9nomm\u00e9e \u00ab inspection centrale", "des imp\u00f4ts directs-soci\u00e9t\u00e9s \u00bb."], "label": "Text", "position": 1}, {"bbox_text": [[116.0, 143.0, 181.0, 157.0]], "bbox_layout": [103.56640625, 134.921875, 195.49609375, 168.0810546875], "text": ["Arr\u00eate :"], "label": "Text", "position": 2}, {"bbox_text": [[42.0, 173.0, 518.0, 182.0], [27.0, 190.0, 517.0, 199.0], [27.0, 206.0, 518.0, 215.0], [27.0, 221.0, 317.0, 235.0]], "bbox_layout": [17.328125, 159.61669921875, 531.8125, 244.6435546875], "text": ["Article 1\u00bar - Il est cr\u00e9\u00e9 \u00e0 Alger une recette des contributions", "diverses, d\u00e9nomm\u00e9e \u00abrecette des contributions diverses-soci\u00e9t\u00e9s \u00bb", "charg\u00e9e du recouvrement des imp\u00f4ts directs et taxes assimil\u00e9es", "des soci\u00e9t\u00e9s et organismes suivants :"], "label": "Text", "position": 3}, {"bbox_text": [[68.0, 250.0, 519.0, 260.0], [41.0, 253.0, 57.0, 262.0], [27.0, 266.0, 518.0, 278.0], [27.0, 284.0, 148.0, 297.0]], "bbox_layout": [17.0703125, 235.751953125, 531.5546875, 307.36328125], "text": ["soci\u00e9t\u00e9s p\u00e9troli\u00e8res et para-p\u00e9troli\u00e8res situ\u00e9es dans les", "8)", "d\u00e9partements suivants : Alger, Tizi Ouzou, El Asnam, M\u00e9d\u00e9a,", "Oasis, Saoura ;"], "label": "Text", "position": 4}, {"bbox_text": [[68.0, 311.0, 518.0, 322.0], [41.0, 313.0, 58.0, 323.0], [27.0, 329.0, 518.0, 337.0], [27.0, 344.0, 167.0, 358.0]], "bbox_layout": [16.8125, 298.1298828125, 531.296875, 368.203125], "text": ["soci\u00e9t\u00e9s de capitaux autres que celles vis\u00e9es ci-dessus,", "b)", "coop\u00e9ratives et leurs unions situ\u00e9es dans la circonscription", "du Grand Alger ;"], "label": "Text", "position": 5}, {"bbox_text": [[72.0, 372.0, 520.0, 382.0], [41.0, 375.0, 56.0, 386.0], [27.0, 390.0, 519.0, 399.0], [27.0, 407.0, 138.0, 420.0]], "bbox_layout": [18.359375, 359.140625, 536.453125, 429.7265625], "text": ["soci\u00e9t\u00e9s nationales, offices, \u00e9tablissements publics of", "C)", "groupements professionnels, situ\u00e9s dans la circonscription du", "Grand Alger ;"], "label": "Text", "position": 6}, {"bbox_text": [[72.0, 434.0, 518.0, 444.0], [42.0, 436.0, 59.0, 446.0], [27.0, 450.0, 344.0, 464.0]], "bbox_layout": [20.421875, 421.005859375, 531.8125, 473.134765625], "text": ["personnes morales du d\u00e9cret du 18 mars 1963, situ\u00e9es", "d)", "dans la circonscription du Grand Alger."], "label": "Text", "position": 7}, {"bbox_text": [[501.0, 476.0, 518.0, 485.0], [136.0, 477.0, 500.0, 490.0], [42.0, 480.0, 110.0, 491.0], [28.0, 495.0, 519.0, 505.0], [28.0, 512.0, 519.0, 522.0], [28.0, 529.0, 520.0, 537.0], [28.0, 545.0, 520.0, 554.0], [28.0, 560.0, 520.0, 570.0], [29.0, 576.0, 330.0, 590.0]], "bbox_layout": [20.55078125, 465.78125, 535.9375, 598.57421875], "text": ["le", "Le directeur de l'administration g\u00e9n\u00e9rale,", "Art. 2.", "directeur des imp\u00f4ts et de l'organisation fonci\u00e8re, le directeur", "du Tr\u00e9sor et du cr\u00e9dit, le directeur du budget et du contr\u00f4le", "sont charg\u00e9s, chacun en ce qui le concerne, de l'ex\u00e9cution du", "pr\u00e9sent arr\u00eat\u00e9 qui sera publi\u00e9 au Journal officiel de la", "R\u00e9publique alg\u00e9rienne d\u00e9mocratique et populaire et qui prendra", "effet \u00e0 compter du 1er d\u00e9cembre 1965."], "label": "Text", "position": 8}, {"bbox_text": [[41.0, 605.0, 315.0, 617.0]], "bbox_layout": [28.54296875, 593.61328125, 328.65625, 627.96875], "text": ["Fait \u00e0 Alger, le 21 septembre 1965,"], "label": "Text", "position": 9}, {"bbox_text": [[214.0, 632.0, 330.0, 646.0]], "bbox_layout": [199.34375, 624.716796875, 349.796875, 659.755859375], "text": ["Ahmed KAID."], "label": "Text", "position": 10}, {"bbox_text": [[30.0, 690.0, 520.0, 700.0], [58.0, 707.0, 407.0, 717.0]], "bbox_layout": [20.55078125, 676.328125, 535.9375, 729.140625], "text": ["Arr\u00eat\u00e9 du 22 octobre 1965 portant cr\u00e9ation d'une inspection", "centrale des taxes sur le chiffre d'affaires."], "label": "Text", "position": 11}, {"bbox_text": [[42.0, 750.0, 341.0, 765.0]], "bbox_layout": [32.41015625, 739.90234375, 356.5, 773.57421875], "text": ["Le ministre des finances et du plan,"], "label": "Text", "position": 12}, {"bbox_text": [[500.0, 778.0, 520.0, 788.0], [44.0, 780.0, 501.0, 790.0], [29.0, 795.0, 520.0, 809.0], [29.0, 814.0, 520.0, 824.0]], "bbox_layout": [19.51953125, 767.24609375, 535.9375, 835.09765625], "text": ["la", "Vu la loi n\u00ba 62-157 du 31 d\u00e9cembre 1962 tendant \u00e0 ", "reconduction de la l\u00e9gislation en vigueur au 31 d\u00e9cembre 1962,", "sauf dans ses dispositions contraires \u00e0 la souverainet\u00e9 nationale;"], "label": "Text", "position": 13}, {"bbox_text": [[285.0, 840.0, 458.0, 854.0], [459.0, 840.0, 520.0, 852.0], [80.0, 841.0, 212.0, 855.0], [223.0, 841.0, 278.0, 854.0], [44.0, 842.0, 66.0, 855.0], [29.0, 857.0, 278.0, 871.0]], "bbox_layout": [19.90625, 828.76953125, 532.328125, 880.21484375], "text": ["du 10 juillet 1965", "portant", "l'ordonnance n\u00ba", "65-182", "Vu", "constitution du Gouvernement ;"], "label": "Text", "position": 14}, {"bbox_text": [[44.0, 885.0, 521.0, 897.0], [30.0, 901.0, 521.0, 915.0], [30.0, 919.0, 429.0, 930.0]], "bbox_layout": [20.421875, 874.5703125, 535.421875, 943.7890625], "text": ["Vu la d\u00e9p\u00eache n\u00ba 427/F/ORG du 25 ao\u00fbt i960, fixant la", "consistance des contr\u00f4les du service des imp\u00f4ts indirects et", "des taxes sur le chiffre d'affaires du Grand Alger,"], "label": "Text", "position": 15}, {"bbox_text": [[120.0, 948.0, 184.0, 961.0]], "bbox_layout": [110.78515625, 936.77734375, 193.43359375, 970.44921875], "text": ["Arr\u00eate :"], "label": "Text", "position": 16}, {"bbox_text": [[44.0, 976.0, 521.0, 990.0], [30.0, 991.0, 521.0, 1005.0], [30.0, 1008.0, 522.0, 1023.0]], "bbox_layout": [22.61328125, 964.8046875, 534.90625, 1035.390625], "text": ["Article 1*r. - Il est cr\u00e9\u00e9 \u00e0 Alger une inspection centrale", "des taxes sur le chiffre d'affaires, d\u00e9nomm\u00e9e \u00ab inspection", "centrale des taxes sur le chiffre d'affaires-soci\u00e9t\u00e9s \u00bb charg\u00e9e"], "label": "Text", "position": 17}, {"bbox_text": [[538.0, 16.0, 1028.0, 25.0], [538.0, 31.0, 707.0, 45.0]], "bbox_layout": [532.4375, 4.5263671875, 1042.28125, 59.432373046875], "text": ["de l'assiette des taxes sur le chiffre d'affaires des soci\u00e9t\u00e9s et", "organismes suivants :"], "label": "Text", "position": 18}, {"bbox_text": [[555.0, 58.0, 1030.0, 71.0], [539.0, 77.0, 1028.0, 88.0], [538.0, 92.0, 722.0, 106.0]], "bbox_layout": [529.859375, 47.977294921875, 1040.734375, 119.033203125], "text": ["1er secteur : soci\u00e9t\u00e9s p\u00e9troli\u00e8res et para-p\u00e9troli\u00e8res situ\u00e9es", "dans les d\u00e9partements suivants : Alger, Tizi Ouzou, El Asnam,", "M\u00e9d\u00e9a, Oasis, Saoura ;"], "label": "Text", "position": 19}, {"bbox_text": [[554.0, 120.0, 1029.0, 132.0], [539.0, 138.0, 1027.0, 149.0], [539.0, 154.0, 777.0, 166.0]], "bbox_layout": [525.734375, 109.287109375, 1042.796875, 179.7021484375], "text": ["2\u00e8me secteur : soci\u00e9t\u00e9s de capitaux autres que celles vis\u00e9es", "ci-dessus, coop\u00e9ratives et leurs unions situ\u00e9es dans la cir-", "conscription du Grand Alger ;"], "label": "Text", "position": 20}, {"bbox_text": [[555.0, 181.0, 1032.0, 193.0], [539.0, 198.0, 1031.0, 211.0], [538.0, 215.0, 731.0, 228.0]], "bbox_layout": [526.765625, 169.443359375, 1044.859375, 239.345703125], "text": ["3\u00e8me secteur : soci\u00e9t\u00e9s nationales, offices, \u00e9tablissements", "publics et groupements professionnels, situ\u00e9s dans la circons-", "cription du Grand Alger."], "label": "Text", "position": 21}, {"bbox_text": [[555.0, 244.0, 1029.0, 254.0], [538.0, 259.0, 915.0, 273.0]], "bbox_layout": [528.828125, 230.966796875, 1042.796875, 283.779296875], "text": ["4\u00e8me secteur : personnes morales du d\u00e9cret du 18 mars 1963,", "situ\u00e9es dans la circonscription du Grand Alger."], "label": "Text", "position": 22}, {"bbox_text": [[555.0, 287.0, 1027.0, 301.0], [541.0, 303.0, 1028.0, 318.0], [541.0, 319.0, 1028.0, 333.0], [541.0, 338.0, 1028.0, 348.0], [541.0, 352.0, 1028.0, 366.0], [541.0, 371.0, 1028.0, 381.0], [541.0, 385.0, 839.0, 399.0]], "bbox_layout": [530.375, 275.9130859375, 1043.3125, 409.560546875], "text": ["Art. 2. - Le directeur de l'administration g\u00e9n\u00e9rale, le direc-", "teur des imp\u00f4ts et de l'organisation fonci\u00e8re, le directeur du", "Tr\u00e9sor et du cr\u00e9dit, le directeur du budget et du contr\u00f4le", "sont charg\u00e9s, chacun en ce qui le concerne, de l'ex\u00e9cution", "du pr\u00e9sent arr\u00eat\u00e9 qui sera publi\u00e9 au Journal officiel de la", "R\u00e9publique alg\u00e9rienne d\u00e9mocratique et populaire et qui prendra", "effet \u00e0 compter du 1er d\u00e9cembre 1965."], "label": "Text", "position": 23}, {"bbox_text": [[555.0, 413.0, 806.0, 427.0]], "bbox_layout": [548.9375, 402.20703125, 820.5625, 437.24609375], "text": ["Fait \u00e0 Alger, le 22 octobre 1965,"], "label": "Text", "position": 24}, {"bbox_text": [[727.0, 441.0, 840.0, 455.0]], "bbox_layout": [719.09375, 431.943359375, 852.53125, 466.298828125], "text": ["Ahmed KAID."], "label": "SectionHeader", "position": 25}, {"bbox_text": [[542.0, 498.0, 1033.0, 511.0], [572.0, 514.0, 1034.0, 528.0], [572.0, 530.0, 1033.0, 543.0], [572.0, 547.0, 1034.0, 561.0], [572.0, 564.0, 637.0, 578.0]], "bbox_layout": [533.984375, 485.60546875, 1047.953125, 587.63671875], "text": ["Arr\u00eat\u00e9 du 23 octobre 1965 fixant le prix de vente moyen de", "l'hectolitre de vin \u00e0 retenir pour le calcul, en mati\u00e8re de", "vignes. des b\u00e9n\u00e9fices forfaitaires imposables, au titre de", "l'ann\u00e9e 1965 \u00e0 l'imp\u00f4t sur les b\u00e9n\u00e9fices de l'exploitation", "agricole."], "label": "Text", "position": 26}, {"bbox_text": [[556.0, 609.0, 862.0, 623.0]], "bbox_layout": [545.84375, 598.3984375, 874.1875, 632.75390625], "text": ["Le ministre des finances et du plan,"], "label": "Text", "position": 27}, {"bbox_text": [[557.0, 636.0, 1031.0, 650.0], [542.0, 654.0, 1032.0, 668.0], [541.0, 670.0, 1033.0, 684.0], [542.0, 689.0, 587.0, 702.0]], "bbox_layout": [535.53125, 626.42578125, 1046.40625, 712.734375], "text": ["Vu la loi n\u00ba 62-157 du 31 d\u00e9cembre 1962 tendant \u00e0 la", "reconduction de la l\u00e9gislation en vigueur au 31 d\u00e9cembre 1962,", "sauf dans ses dispositions contraires \u00e0 la souverainet\u00e9 natio-", "nale ;"], "label": "Text", "position": 28}, {"bbox_text": [[559.0, 716.0, 1033.0, 730.0], [542.0, 732.0, 750.0, 746.0]], "bbox_layout": [535.015625, 703.671875, 1045.890625, 756.484375], "text": ["Vu l'ordonnance n\u00ba 65-182 du 10 juillet 1965 portant consti-", "tution du Gouvernement ;"], "label": "Text", "position": 29}, {"bbox_text": [[557.0, 760.0, 1033.0, 775.0], [542.0, 778.0, 600.0, 791.0]], "bbox_layout": [537.078125, 750.15625, 1045.890625, 801.6015625], "text": ["Vu le code des imp\u00f4ts directs et notamment son article", "95 \u00a7 6,"], "label": "Text", "position": 30}, {"bbox_text": [[632.0, 806.0, 698.0, 820.0]], "bbox_layout": [615.453125, 796.640625, 709.703125, 830.3125], "text": ["Arr\u00eate :"], "label": "Text", "position": 31}, {"bbox_text": [[557.0, 835.0, 1034.0, 847.0], [543.0, 851.0, 1037.0, 865.0], [542.0, 870.0, 1035.0, 880.0], [545.0, 884.0, 1035.0, 898.0], [544.0, 901.0, 1035.0, 913.0], [544.0, 917.0, 1035.0, 931.0], [543.0, 933.0, 1035.0, 944.0], [544.0, 949.0, 1035.0, 963.0]], "bbox_layout": [534.5, 823.984375, 1051.5625, 973.8671875], "text": ["Article unique. - Le prix de vente moyen de l'hectolitre de vin", "dont la d\u00e9termination est pr\u00e9vue par l'article 95 \u00a7 6 du code", "des imp\u00f4ts directs pour le calcul des b\u00e9n\u00e9fices forfaitaires", "en ce qui concerne les vignes, est fix\u00e9, en vue de l'\u00e9tablis-", "sement de l'imp\u00f4t sur les b\u00e9n\u00e9fices de l'exploitation agricole", "au titre de l'ann\u00e9e 1965, conform\u00e9ment aux indications du", "tableau annex\u00e9 au pr\u00e9sent arr\u00eat\u00e9 qui sera publi\u00e9 au Journal", "officiel de la R\u00e9publique alg\u00e9rienne d\u00e9mocratique et populaire."], "label": "Text", "position": 32}, {"bbox_text": [[559.0, 977.0, 830.0, 991.0]], "bbox_layout": [549.453125, 967.5390625, 838.609375, 1002.578125], "text": ["Fait \u00e0 Alger, le 23 octobre 1965."], "label": "Text", "position": 33}, {"bbox_text": [[812.0, 1006.0, 923.0, 1019.0]], "bbox_layout": [802.109375, 995.56640625, 934.515625, 1029.23828125], "text": ["Ahmed KAID."], "label": "Text", "position": 34}, {"bbox_text": [[485.0, 1032.0, 578.0, 1046.0]], "bbox_layout": [474.6875, 1021.54296875, 593.6875, 1055.21484375], "text": ["ANNEXE"], "label": "SectionHeader", "position": 35}, {"bbox_text": [[48.0, 1055.0, 207.0, 1068.0], [214.0, 1055.0, 1009.0, 1066.0], [48.0, 1071.0, 1007.0, 1084.0], [432.0, 1087.0, 626.0, 1099.0]], "bbox_layout": [37.953125, 1043.41796875, 1027.328125, 1109.90234375], "text": ["Tableau pr\u00e9sentant", "par r\u00e9gion, le prix de vente moyen de l'hectolitre de vin \u00e0 retenir pour le calcul, en mati\u00e8re", "de vignes, des b\u00e9n\u00e9fices forfaitaires imposables au titre de l'ann\u00e9e 1965 (revenus de 1964) \u00e0 l'imp\u00f4t sur les b\u00e9n\u00e9fices", "de l'exploitation agricole."], "label": "Text", "position": 36}, {"bbox_text": [[386.0, 1108.0, 677.0, 1122.0]], "bbox_layout": [378.0078125, 1098.10546875, 697.84375, 1131.77734375], "text": ["(Code des impots directs, Art. 95-6)"], "label": "Text", "position": 37}, {"bbox_text": [[952.0, 1139.0, 1014.0, 1153.0], [437.0, 1142.0, 500.0, 1155.0], [934.0, 1156.0, 1034.0, 1169.0], [418.0, 1158.0, 518.0, 1172.0], [927.0, 1172.0, 1039.0, 1186.0], [411.0, 1174.0, 432.0, 1187.0], [433.0, 1174.0, 525.0, 1187.0], [689.0, 1177.0, 770.0, 1191.0], [175.0, 1179.0, 255.0, 1193.0], [954.0, 1188.0, 1013.0, 1201.0], [440.0, 1192.0, 498.0, 1205.0], [947.0, 1205.0, 1018.0, 1217.0], [432.0, 1207.0, 504.0, 1220.0], [139.0, 1248.0, 292.0, 1262.0], [590.0, 1257.0, 872.0, 1271.0], [449.0, 1275.0, 487.0, 1290.0], [176.0, 1277.0, 238.0, 1290.0], [237.0, 1277.0, 257.0, 1290.0], [549.0, 1292.0, 887.0, 1306.0], [104.0, 1297.0, 329.0, 1312.0], [32.0, 1318.0, 271.0, 1332.0], [548.0, 1323.0, 918.0, 1337.0], [31.0, 1337.0, 402.0, 1350.0], [577.0, 1340.0, 661.0, 1354.0], [48.0, 1355.0, 136.0, 1369.0], [547.0, 1372.0, 812.0, 1387.0], [33.0, 1375.0, 314.0, 1388.0]], "bbox_layout": [16.0390625, 1117.24609375, 1064.96875, 1403.84765625], "text": ["Prix de", "Prix de", "vente moyen", "vente moyen", "de l'hectolitre", "de", "L'hectolitre", "REGIONS", "REGIONS", "de vin", "de vin", "(en DA.)", "(en DA.)", "REGION D'ALGER", "DEPARTEMENT DE TIZI-OUZOU", "42,80", "Groupe", "I", "Arrondissements d'Azazga et Tizi-Ouzou.", "DEPARTEMENT D'ALGER", "Arrondissements d'Alger, Blida.", "A l'exception des communes class\u00e9es dans le", "A l'exception des communes class\u00e9es dans le", "groupe II.", "groupe II.", "Arrondissement de Bordj Menaiel.", "Arrondissement de Dar El Beida."], "label": "Form", "position": 38}]}, {"index": 3, "page": [{"bbox_text": [[493.0, 20.0, 555.0, 36.0], [1000.0, 23.0, 1060.0, 38.0], [476.0, 39.0, 575.0, 53.0], [981.0, 40.0, 1078.0, 54.0], [470.0, 57.0, 580.0, 71.0], [234.0, 58.0, 313.0, 75.0], [978.0, 58.0, 1081.0, 72.0], [742.0, 60.0, 821.0, 74.0], [495.0, 73.0, 553.0, 86.0], [1003.0, 75.0, 1058.0, 89.0], [488.0, 91.0, 560.0, 103.0], [1000.0, 91.0, 1060.0, 105.0], [250.0, 105.0, 278.0, 112.0], [506.0, 128.0, 542.0, 142.0], [602.0, 128.0, 863.0, 145.0], [234.0, 130.0, 317.0, 145.0], [165.0, 150.0, 383.0, 165.0], [602.0, 153.0, 874.0, 169.0], [94.0, 170.0, 275.0, 184.0], [602.0, 173.0, 967.0, 191.0], [93.0, 190.0, 457.0, 206.0], [615.0, 191.0, 688.0, 205.0], [109.0, 208.0, 281.0, 224.0], [602.0, 210.0, 811.0, 226.0], [94.0, 228.0, 298.0, 241.0], [602.0, 230.0, 968.0, 247.0], [94.0, 249.0, 255.0, 262.0], [615.0, 249.0, 707.0, 262.0], [631.0, 273.0, 936.0, 293.0], [149.0, 275.0, 400.0, 291.0], [602.0, 294.0, 953.0, 312.0], [94.0, 298.0, 321.0, 311.0], [601.0, 316.0, 852.0, 331.0], [157.0, 325.0, 391.0, 341.0], [602.0, 335.0, 967.0, 354.0], [94.0, 345.0, 433.0, 360.0], [437.0, 347.0, 455.0, 357.0], [615.0, 353.0, 686.0, 366.0], [107.0, 365.0, 259.0, 379.0], [603.0, 371.0, 854.0, 390.0], [135.0, 393.0, 413.0, 404.0], [603.0, 394.0, 965.0, 408.0], [615.0, 410.0, 967.0, 427.0], [92.0, 413.0, 287.0, 427.0], [614.0, 428.0, 968.0, 441.0], [91.0, 433.0, 452.0, 445.0], [614.0, 444.0, 966.0, 459.0], [105.0, 451.0, 159.0, 464.0], [701.0, 459.0, 966.0, 473.0], [616.0, 460.0, 694.0, 471.0], [91.0, 469.0, 443.0, 482.0], [614.0, 477.0, 696.0, 490.0], [105.0, 485.0, 378.0, 500.0], [668.0, 502.0, 897.0, 516.0], [91.0, 506.0, 331.0, 519.0], [599.0, 522.0, 810.0, 537.0], [91.0, 527.0, 310.0, 540.0], [599.0, 543.0, 770.0, 557.0], [503.0, 560.0, 539.0, 575.0], [227.0, 561.0, 320.0, 575.0], [658.0, 570.0, 906.0, 584.0], [153.0, 581.0, 387.0, 595.0], [598.0, 590.0, 902.0, 604.0], [92.0, 602.0, 453.0, 612.0], [598.0, 611.0, 814.0, 626.0], [102.0, 620.0, 150.0, 633.0], [598.0, 632.0, 965.0, 646.0], [91.0, 639.0, 296.0, 653.0], [612.0, 649.0, 671.0, 663.0], [144.0, 659.0, 394.0, 673.0], [599.0, 669.0, 834.0, 682.0], [91.0, 679.0, 451.0, 692.0], [599.0, 689.0, 784.0, 702.0], [103.0, 697.0, 238.0, 710.0], [87.0, 717.0, 367.0, 730.0], [739.0, 725.0, 825.0, 739.0], [1013.0, 728.0, 1049.0, 743.0], [88.0, 737.0, 453.0, 752.0], [678.0, 745.0, 885.0, 760.0], [103.0, 754.0, 189.0, 768.0], [598.0, 767.0, 816.0, 781.0], [498.0, 781.0, 538.0, 795.0], [216.0, 782.0, 328.0, 796.0], [598.0, 787.0, 791.0, 802.0], [145.0, 803.0, 397.0, 817.0], [627.0, 813.0, 935.0, 827.0], [87.0, 823.0, 366.0, 839.0], [598.0, 834.0, 932.0, 848.0], [87.0, 844.0, 268.0, 859.0], [658.0, 857.0, 884.0, 871.0], [196.0, 871.0, 339.0, 889.0], [597.0, 878.0, 800.0, 892.0], [598.0, 897.0, 964.0, 914.0], [230.0, 903.0, 308.0, 917.0], [499.0, 904.0, 537.0, 918.0], [609.0, 917.0, 691.0, 929.0], [164.0, 922.0, 368.0, 938.0], [654.0, 936.0, 902.0, 952.0], [87.0, 943.0, 271.0, 957.0], [595.0, 955.0, 813.0, 972.0], [86.0, 963.0, 449.0, 977.0], [595.0, 977.0, 961.0, 992.0], [100.0, 982.0, 181.0, 995.0], [609.0, 995.0, 691.0, 1008.0], [86.0, 1001.0, 366.0, 1015.0], [650.0, 1015.0, 904.0, 1029.0], [85.0, 1020.0, 287.0, 1034.0], [595.0, 1037.0, 821.0, 1051.0], [117.0, 1039.0, 415.0, 1058.0], [595.0, 1057.0, 774.0, 1071.0], [83.0, 1061.0, 338.0, 1075.0], [595.0, 1075.0, 817.0, 1092.0], [83.0, 1080.0, 245.0, 1098.0], [595.0, 1097.0, 839.0, 1111.0], [142.0, 1103.0, 389.0, 1117.0], [83.0, 1121.0, 326.0, 1138.0], [594.0, 1121.0, 808.0, 1135.0], [82.0, 1141.0, 449.0, 1161.0], [593.0, 1141.0, 804.0, 1155.0], [95.0, 1159.0, 178.0, 1173.0], [594.0, 1159.0, 817.0, 1176.0], [135.0, 1180.0, 393.0, 1197.0], [592.0, 1183.0, 956.0, 1195.0], [593.0, 1199.0, 960.0, 1214.0], [80.0, 1201.0, 422.0, 1215.0], [430.0, 1204.0, 448.0, 1213.0], [620.0, 1216.0, 719.0, 1229.0], [95.0, 1218.0, 166.0, 1230.0], [654.0, 1235.0, 898.0, 1249.0], [80.0, 1237.0, 448.0, 1251.0], [94.0, 1254.0, 185.0, 1268.0], [743.0, 1258.0, 819.0, 1271.0], [1006.0, 1258.0, 1046.0, 1272.0], [220.0, 1275.0, 304.0, 1289.0], [495.0, 1276.0, 531.0, 1290.0], [617.0, 1277.0, 921.0, 1292.0], [159.0, 1295.0, 366.0, 1309.0], [593.0, 1299.0, 958.0, 1312.0], [77.0, 1314.0, 352.0, 1328.0], [592.0, 1319.0, 799.0, 1332.0], [79.0, 1335.0, 264.0, 1349.0], [592.0, 1340.0, 958.0, 1354.0], [78.0, 1354.0, 397.0, 1372.0], [606.0, 1358.0, 690.0, 1372.0]], "bbox_layout": [71.66796875, 5.0390625, 1096.75, 1387.44140625], "text": ["Prix d\u00ea", "PHx de", "vente moyen", "vente moven", "de l'heetolitre", "REGIONS", "de l'hectolitre", "REGIONS", "de vin", "de vin", "(en DA.)", "(en DA)", "-------", "45.60", "Arrondissement de Mohammadia.", "Groupe II", "DEPARTEMENT D'ALGER", "Arrondissement de Sidi Bel Abbes.", "Arrondissement d'Alger.", "A l'exception de la commune class\u00e9e dans le", "Communes de Birkhadem - Dou\u00e9ra - Draria", "groupe I.", "- Mahelma - Saoula.", "Arrondissement de T\u00e9lagh.", "Arrondissement de Blida.", "A l'exception de la commune elassee dans le", "Commune de Kol\u00e9a.", "groupe III.", "DEPARTEMENT DE MOSTAGANEM", "DEPARTEMENT D'EL ASNAM", "Arrontlissements de Sidi Ali et Ighil Izane.", "Arrondissement de Cherchell.", "Arrondissement de Mostaganem.", "DEPARTEMENT DE MEDEA", "A l'exception de la commune class\u00e9e dans le", "Arrondissements de Bou Saada, Tablat", "et", "group\u00e9 I.", "Sour El Ghozlane.", "Arrondissement d'Oued Rhiou.", "DEPARTEMENT DE TISI-QUEOU", "A l'exception des communes d\u00e9sign\u00e9es ci-", "apr\u00e8s pour lesquelles est applicable le prix", "Arrondissement d'Azazga.", "retenu en ce qui concerne le groupe III de", "Communes d'Azazga - Bousgu\u00ean - Yakouren -", "la r\u00e9gion d'Alger : El Hamadena - Sidi-", "Mekla.", "Ben Ali, Mazouna Mediouna =", "M'Hamed", "Arrondissements de Bouira - Dra El Mizan", "Quarizane.", "Larba Na\u00eft Irathen et Lakhdatia.", "DEPARTEMENT DE SAIDA", "Arrondissement de Tizi-Ouzeu.", "Arrondissement de Saida.", "Commune de B\u00e9ni Douala.", "Commune de Daoud.", "48,00", "Groupe III", "DEPARTEMENT DE TIARET", "DEPARTEMENT DE MEDEA", "Arrondissements d'Aflou et de Tiaret.", "Arrondissement d'Ain Oussera et Ksar El Boti-", "Arrondissement de Frenda.", "khari.", "Communes d'A\u00efn Tahir - Rachidia - Quled", "Arrondissement de M\u00e9des.", "Djerad.", "DEPARTEMENT D'EL ASNAM", "Artondissement de Tissemsilt.", "Arrondissements d'A\u00efn Defla - Miliana - El-", "Commune d'Ain D\u00e9arit.", "Asnam et T\u00e9n\u00e8s.", "Arrendissement de Teniet El Had.", "Groupe III", "62,10", "A l'exception de la commune classee dans le", "DEPARTEMENT D'ORAN", "groupe IV.", "Arrondissement de T\u00e9lagh.", "56,30", "Groupe IV `", "Commune de Marhoum.", "DEPARTEMENT D'EL ASNAM", "DEPARTEMENT DE MOSTAGANEM", "Arrondissement de Teniet El Had.", "Arrondissements de Mascara et Tighennif.", "Commune de Lardjem.", "DEPARTEMENT DE SAIDA", "REGION D'ORAN", "Arrondissement de Sa\u00efda.", "A l'exception de la commune class\u00e9e dans le", "Groupe I", "56,10", "groupe II.", "DEPARTEMENT D'ORAN", "DEPARTEMENT DE TIARET", "Arrondissement d'Oran.", "Arrondissement de Frenda.", "A l'exception des communes classees dans le", "A l'exception des communes class\u00e9es dans le", "groupe II.", "groupe II.", "Arrondissement de Sidi Bel Abb\u00e8s.", "DEPARTEMENT DE TLEMCEN", "Commune de Ben Badis.", "Arrondissement de Beni Saf.", "DEPARTEMENT DE MOSTAGANEM", "Commune de Honaine.", "Arrondissement de Mostaganem.", "Arrondissement de Maghnia.", "Commune de Stidia.", "Arrondissement de Ghazaouet.", "DEPARTEMENT DE TIARET", "Arrendie ement de Tissemsilt.", "Arrondissement de Sebdou.", "A l'exception de la commune class\u00e9e dans le", "Commune de B\u00e9ni Senous.", "groune II.", "Arrondissement de Tlemcen.", "DE ARTEMENT DE TLEMCEN", "Communes de Hennaya - Ouled El Mimoun -", "Tlemcen - Sebra - B\u00e9ni Mester - Sidi Abdelli", "Arrondiesements de B\u00e9ni Saf - Sebdou", "et", "Bensekrane.", "Tlemcen.", "REGION DE CONSTANTINE", "A l'exception des communes class\u00e9es dans le", "groupe III.", "Groupe I", "42,80", "Groupe II", "89,10", ". DEPARTEMENT DE CONSTANTINE", "DEPARTEMENT D'ORAN", "Arrondissements de Collo - Djidjelli et El Milia", "Arrondissement d'A\u00efn-T\u00e9mouchent.", "Arrondissement de Skikda.", "Arrondissement d'Ornn.", "A l'exception des communes class\u00e9es dans le", "Communes de Bou Tl\u00e9lis - Oued Tlelat.", "groupe II."], "label": "TableOfContents", "position": 0}]}, {"index": 4, "page": [{"bbox_text": [[291.0, 9.0, 348.0, 18.0], [261.0, 10.0, 280.0, 18.0], [102.0, 11.0, 229.0, 20.0], [573.0, 11.0, 1045.0, 21.0], [448.0, 24.0, 508.0, 37.0], [558.0, 29.0, 770.0, 40.0], [430.0, 40.0, 529.0, 53.0], [574.0, 56.0, 1046.0, 66.0], [426.0, 58.0, 533.0, 71.0], [189.0, 64.0, 269.0, 78.0], [452.0, 73.0, 506.0, 86.0], [561.0, 74.0, 620.0, 86.0], [448.0, 90.0, 513.0, 102.0], [573.0, 101.0, 1046.0, 110.0], [562.0, 119.0, 629.0, 131.0], [117.0, 133.0, 345.0, 146.0], [707.0, 143.0, 1046.0, 154.0], [671.0, 145.0, 708.0, 158.0], [575.0, 147.0, 670.0, 159.0], [50.0, 157.0, 384.0, 166.0], [671.0, 161.0, 1047.0, 171.0], [561.0, 162.0, 670.0, 175.0], [120.0, 174.0, 346.0, 187.0], [561.0, 178.0, 1047.0, 187.0], [561.0, 194.0, 1048.0, 204.0], [50.0, 196.0, 416.0, 206.0], [562.0, 210.0, 655.0, 224.0], [65.0, 213.0, 151.0, 226.0], [466.0, 226.0, 502.0, 240.0], [191.0, 231.0, 276.0, 245.0], [576.0, 237.0, 1050.0, 248.0], [88.0, 253.0, 379.0, 265.0], [562.0, 255.0, 1049.0, 265.0], [51.0, 274.0, 373.0, 285.0], [52.0, 294.0, 217.0, 309.0], [52.0, 315.0, 264.0, 329.0], [643.0, 329.0, 977.0, 347.0], [52.0, 336.0, 407.0, 346.0], [646.0, 355.0, 976.0, 371.0], [68.0, 357.0, 333.0, 368.0], [117.0, 376.0, 354.0, 388.0], [121.0, 395.0, 349.0, 410.0], [55.0, 418.0, 384.0, 428.0], [564.0, 419.0, 1052.0, 429.0], [69.0, 435.0, 133.0, 448.0], [595.0, 436.0, 1053.0, 444.0], [595.0, 452.0, 1053.0, 462.0], [54.0, 455.0, 303.0, 466.0], [124.0, 473.0, 347.0, 486.0], [672.0, 494.0, 939.0, 507.0], [55.0, 497.0, 284.0, 506.0], [55.0, 515.0, 252.0, 529.0], [579.0, 531.0, 986.0, 542.0], [153.0, 567.0, 438.0, 579.0], [656.0, 567.0, 752.0, 579.0], [580.0, 601.0, 974.0, 612.0], [56.0, 629.0, 540.0, 637.0], [654.0, 636.0, 703.0, 649.0], [85.0, 647.0, 119.0, 658.0], [580.0, 665.0, 961.0, 675.0], [71.0, 695.0, 544.0, 704.0], [580.0, 705.0, 1053.0, 714.0], [55.0, 711.0, 543.0, 721.0], [56.0, 729.0, 541.0, 736.0], [657.0, 735.0, 751.0, 746.0], [57.0, 744.0, 209.0, 758.0], [580.0, 769.0, 1054.0, 776.0], [565.0, 786.0, 803.0, 796.0], [56.0, 801.0, 543.0, 809.0], [87.0, 819.0, 171.0, 833.0], [657.0, 820.0, 702.0, 830.0], [581.0, 849.0, 1057.0, 857.0], [566.0, 866.0, 811.0, 877.0], [73.0, 869.0, 542.0, 877.0], [57.0, 886.0, 543.0, 893.0], [582.0, 899.0, 990.0, 909.0], [57.0, 902.0, 544.0, 909.0], [57.0, 918.0, 543.0, 925.0], [658.0, 926.0, 755.0, 940.0], [72.0, 946.0, 543.0, 954.0], [583.0, 955.0, 963.0, 966.0], [58.0, 963.0, 243.0, 974.0], [657.0, 983.0, 704.0, 996.0], [57.0, 990.0, 543.0, 998.0], [58.0, 1006.0, 117.0, 1019.0], [584.0, 1012.0, 1014.0, 1021.0], [73.0, 1035.0, 544.0, 1043.0], [584.0, 1048.0, 980.0, 1056.0], [57.0, 1051.0, 121.0, 1065.0], [661.0, 1074.0, 756.0, 1088.0], [73.0, 1077.0, 545.0, 1087.0], [57.0, 1094.0, 482.0, 1105.0], [584.0, 1103.0, 863.0, 1116.0], [73.0, 1123.0, 545.0, 1132.0], [658.0, 1132.0, 707.0, 1145.0], [57.0, 1139.0, 123.0, 1152.0], [585.0, 1160.0, 873.0, 1172.0], [72.0, 1166.0, 517.0, 1177.0], [74.0, 1195.0, 546.0, 1205.0], [584.0, 1196.0, 1003.0, 1204.0], [61.0, 1213.0, 119.0, 1226.0], [662.0, 1223.0, 757.0, 1237.0], [74.0, 1240.0, 547.0, 1250.0], [585.0, 1253.0, 942.0, 1262.0], [61.0, 1256.0, 438.0, 1266.0], [59.0, 1284.0, 546.0, 1293.0], [659.0, 1286.0, 707.0, 1299.0], [60.0, 1300.0, 546.0, 1311.0], [584.0, 1315.0, 942.0, 1325.0], [60.0, 1318.0, 118.0, 1331.0]], "bbox_layout": [32.046875, -7.265625, 1067.1015625, 1343.0078125], "text": ["ance pour le prope", "", "rest es de propertie de more", "Mme Fatma bent Mohamed, \u00e9pouse Reguleg Mohamed, nee", "Prix de", "le 22 janvier 1933 \u00e0 Oran,", "vente moyen", "M. Bellouati Mustapha, n\u00e9 le 15 janvier 1940 \u00e0 El Harrach", "de l\u2019hectolitre", "REGIONS", "de vin", "(Alger),", "(en DA)", "M. Bouaria Maanane Abdeslam, n\u00e9 en 1940 \u00e0 B\u00e9ni-Chicar", "(Maroc),", "DEPARTEMENT D'ANNABA", "21 octobre 1965, acquiert la nationalit\u00e9", "du", "Par arr\u00eat\u00e9", "Arrondissements d'Annaba et d'El Kala.", "jouit de tous les droits attach\u00e9s \u00e0 la qualit\u00e9", "alg\u00e9rienne et", "DEPARTEMENT DE BETIF", "d'Alg\u00e9rien, dans les conditions de l'article 11 - 1\u00ba de la loi", "n\u00b0 63-96 du 27 mars 1963 portant code de la nationalit\u00e9", "Arrondissement d'Akbou - Bejala - Sidi Alch", "alg\u00e9rienne :", "et Bougaa.", "45,60", "Groupe II", "M. Kaddour ould Khelifa ben Mohammed, n\u00e9 le 12 d\u00e9cembre", "DEPARTEMENT DE CONSTANTINE", "1945 \u00e0 Sa\u00efda, qui s'appellera d\u00e9sormais : Meddah Kaddour.", "Arrondissement d'A\u00efn Be\u00efda - A\u00efn M'Lila.", "Constantine et Mila.", "Arrondissement de Skikda.", "MINISTERE DE L'AGRICULTURE", "Communes d'El Arrouch - Salah Bouchaour", "ET DE LA REFORME AGRAIRE", "Emj\u00e8s Edchich - Sidi Mesghich.", "DEPARTEMENT DE BATNA", "DEPARTEMENT D'ANNABA", "Arrondissements d'El Aouinet - Guelm.", "D\u00e9cret n\u00ba 65-248 du 4 octobre 1965 fixant les prix et modalit\u00e9s", "Tebessa.", "de paiement, de stockage et de r\u00e9troeession des l\u00e9gumes", "secs alg\u00e9riens pour la campagne 1965-1966 (rectificatif).", "Arrondissement de Souk Ahras.", "DEPARTEMENT DE SETIF", "(J.O. N\u00ba 83 DU 8 OCTOBRE 1965)", "Arrondissement de Kherrata.", "Arrondissement de S\u00e9tif.", "Page 887, deuxi\u00e8me colonne, article 4, 14\u00e8me ligne", "MINISTERE DE LA JUSTICE", "au lieu de :", "du 10,01 \u00e0 35 %, r\u00e9faction de 0,04 DA par point ;", "D\u00e9eret du 60 septembre 1965 portant nomination d'un magis-", "Lire :", "trat.", "de 10,01 \u00e0 35 %, r\u00e9faction de 0,04 DA par point ;", "Par d\u00e9cret du 20 septembre 1965, M. Zinelabdine est nomm\u00e9", "Page 888, deuxi\u00e8me colonne, article 11, 3\u00e8me et 4\u00e8me ligne", "substitut du procureur de la R\u00e9publique pr\u00e8s le tribunal de", "grande instance de Mascara, et class\u00e9 au 2\u00e8me grade, 1\u00ba", "au lieu de :", "groupe, ler \u00e9chelon.", "sur toutes les c\u00e9r\u00e9ales re\u00e7ues par eux, les taxes vis\u00e9es \u00e0", "l'article 10 du pr\u00e9sent d\u00e9cret ;", "Arr\u00eat\u00e9s du 21 octobre 1965 portant acquisition de la nationalit\u00e9", "alg\u00e9rienne.", "Lire :", "sur tous les l\u00e9gumes secs re\u00e7us par eux, les taxes vis\u00e9es \u00e0", "l'article 10 du pr\u00e9sent d\u00e9cret ;", "Par arr\u00eat\u00e9s du 21 octobre 1965, acqui\u00e8rent la nationalit\u00e9", "alg\u00e9rienne et jouissent de tous les droits attach\u00e9s \u00e0 la qualit\u00e9", "Page 888, deuxi\u00e8me colonne, article 11, 5\u00e8me ligne", "d'Alg\u00e9rien, dans les conditions de l'article 8 de la loi n\u00ba 63-06", "du 27 mars 1963 portant code de la nationalit\u00e9 alg\u00e9rienne :", "au lieu de :", "M. Gregeois Maurice Robert, n\u00e9 le 10 janvier 1934 \u00e0 Beauvais,", "sur toutes les quantit\u00e9s de c\u00e9r\u00e9ales r\u00e9troc\u00e9d\u00e9es :", "(Dpt de l'Oise) France,", "Lire :", "M. El-Aoussin Mohamed, n\u00e9 le 28 f\u00e9vrier 1926 \u00e0 Mers El Kebir", "(Oran),", "sur toutes le quantit\u00e9s de l\u00e9gumes secs r\u00e9troc\u00e9d\u00e9es :", "M. Abdelkader ben Mimoun ben Larbi, n\u00e9 le 8 f\u00e9vrier 1932", "Page 888, deuxi\u00e8me colonne, article 14, 4\u00e8me ligne", "a Oran,", "au lieu de :", "Mme Blasco-Ripoll Remedios, \u00e9pouse Violi Dominique, n\u00e9e", "le 31 ao\u00fbt 1903 \u00e0 Elche (province d'Alicante) Espagne,", "pr\u00e9vues \u00e0 l'article 2 au vu d'\u00e9tats ...", "M. Mohamed ben Ali ben Maati, n\u00e9 le 29 d\u00e9cembre 1938", "Lire :", "\u00e0 Oran,", "pr\u00e9vues \u00e0 l'article 12 au vu d'\u00e9tats ..", "M. Benabdellah Miloud, n\u00e9 le 17 octobre 1922 \u00e0 Oran,", "Mme Soussi Zaouia, n\u00e9e le 21 mars 1940 \u00e0 A\u00efn El Arba", "Page 888, deuxi\u00e8me colonne, article 15, premi\u00e8re ligne", "(Oran),", "au lieu de :", "Mlle L\u00e9m\u00e9e Monique Madeleine Anne-Marie Joseph, n\u00e9e le", "les stocks de l\u00e9gumes secs de la r\u00e9colte 1965 ...", "29 aout 1936 \u00e0 Vernon (Dpt de l'Eure) France,", "Mme Morin Marie Albertine Jos\u00e9phine, \u00e9pouse Kraouti Omar,", "Lire :", "n\u00e9e le 3 octobre 1939 \u00e0 Nantes (Dpt de la Loire-Atlantique)", "les stocks de l\u00e9gumes secs de la r\u00e9colte 1964", "France,"], "label": "TableOfContents", "position": 0}, {"bbox_text": [[76.0, 1345.0, 547.0, 1354.0], [62.0, 1361.0, 186.0, 1375.0]], "bbox_layout": [54.6875, 1332.578125, 560.3828125, 1386.7578125], "text": ["Mme Fatna bent Bouziane, n\u00e9e en 1917 \u00e0 Ouled M\u00e9ziane,", "Oujda (Maroc),"], "label": "Text", "position": 1}]}, {"index": 5, "page": [{"bbox_text": [[576.0, 9.0, 1053.0, 22.0], [54.0, 12.0, 542.0, 23.0], [562.0, 25.0, 1053.0, 39.0], [83.0, 28.0, 215.0, 42.0], [562.0, 43.0, 926.0, 57.0], [576.0, 65.0, 909.0, 80.0], [66.0, 72.0, 498.0, 86.0], [577.0, 87.0, 904.0, 101.0], [66.0, 102.0, 541.0, 113.0], [577.0, 109.0, 813.0, 123.0], [51.0, 119.0, 540.0, 132.0], [51.0, 133.0, 267.0, 149.0], [579.0, 133.0, 1053.0, 146.0], [598.0, 149.0, 664.0, 163.0], [69.0, 161.0, 543.0, 176.0], [578.0, 171.0, 1054.0, 186.0], [53.0, 179.0, 235.0, 193.0], [578.0, 193.0, 974.0, 207.0], [55.0, 207.0, 173.0, 222.0], [182.0, 207.0, 540.0, 219.0], [577.0, 221.0, 1054.0, 235.0], [51.0, 222.0, 304.0, 238.0], [562.0, 238.0, 1054.0, 255.0], [144.0, 254.0, 207.0, 267.0], [563.0, 255.0, 805.0, 269.0], [53.0, 282.0, 542.0, 295.0], [580.0, 291.0, 1054.0, 305.0], [52.0, 298.0, 258.0, 312.0], [562.0, 306.0, 1053.0, 320.0], [562.0, 324.0, 814.0, 337.0], [68.0, 327.0, 446.0, 340.0], [577.0, 352.0, 1054.0, 366.0], [68.0, 356.0, 541.0, 368.0], [562.0, 368.0, 1053.0, 383.0], [51.0, 370.0, 540.0, 384.0], [562.0, 385.0, 1054.0, 399.0], [97.0, 399.0, 541.0, 413.0], [562.0, 401.0, 833.0, 416.0], [69.0, 402.0, 95.0, 411.0], [53.0, 416.0, 542.0, 430.0], [577.0, 429.0, 1055.0, 444.0], [53.0, 432.0, 541.0, 445.0], [562.0, 445.0, 1054.0, 459.0], [52.0, 449.0, 542.0, 463.0], [562.0, 463.0, 1054.0, 476.0], [51.0, 465.0, 541.0, 479.0], [562.0, 478.0, 1053.0, 492.0], [51.0, 483.0, 103.0, 495.0], [562.0, 495.0, 690.0, 509.0], [97.0, 509.0, 540.0, 525.0], [68.0, 512.0, 84.0, 522.0], [98.0, 526.0, 524.0, 541.0], [52.0, 527.0, 94.0, 537.0], [524.0, 527.0, 542.0, 537.0], [576.0, 529.0, 1054.0, 543.0], [52.0, 543.0, 541.0, 557.0], [563.0, 546.0, 1054.0, 563.0], [51.0, 558.0, 541.0, 574.0], [562.0, 563.0, 681.0, 577.0], [51.0, 576.0, 543.0, 590.0], [579.0, 585.0, 1026.0, 599.0], [52.0, 591.0, 542.0, 607.0], [53.0, 608.0, 311.0, 622.0], [577.0, 609.0, 997.0, 623.0], [579.0, 630.0, 1055.0, 645.0], [69.0, 637.0, 540.0, 651.0], [598.0, 647.0, 665.0, 662.0], [988.0, 651.0, 1027.0, 659.0], [51.0, 654.0, 543.0, 668.0], [51.0, 669.0, 541.0, 683.0], [579.0, 671.0, 1036.0, 682.0], [50.0, 687.0, 218.0, 701.0], [578.0, 693.0, 1042.0, 707.0], [69.0, 714.0, 540.0, 729.0], [579.0, 715.0, 803.0, 729.0], [52.0, 730.0, 541.0, 744.0], [576.0, 743.0, 1054.0, 757.0], [51.0, 745.0, 541.0, 764.0], [562.0, 759.0, 778.0, 774.0], [50.0, 762.0, 260.0, 776.0], [577.0, 788.0, 1054.0, 803.0], [54.0, 791.0, 345.0, 805.0], [563.0, 806.0, 697.0, 819.0], [226.0, 820.0, 365.0, 835.0], [579.0, 840.0, 1056.0, 855.0], [563.0, 857.0, 1056.0, 871.0], [51.0, 865.0, 539.0, 879.0], [563.0, 875.0, 755.0, 887.0], [80.0, 882.0, 212.0, 896.0], [577.0, 903.0, 637.0, 915.0], [639.0, 903.0, 1054.0, 917.0], [562.0, 918.0, 1054.0, 933.0], [66.0, 924.0, 497.0, 943.0], [562.0, 936.0, 747.0, 949.0], [68.0, 952.0, 541.0, 971.0], [577.0, 955.0, 1054.0, 973.0], [50.0, 971.0, 254.0, 985.0], [598.0, 974.0, 764.0, 988.0], [577.0, 996.0, 1015.0, 1010.0], [68.0, 998.0, 540.0, 1016.0], [50.0, 1016.0, 541.0, 1031.0], [578.0, 1018.0, 1037.0, 1032.0], [50.0, 1033.0, 326.0, 1046.0], [577.0, 1041.0, 1054.0, 1054.0], [598.0, 1058.0, 725.0, 1071.0], [133.0, 1061.0, 207.0, 1074.0], [577.0, 1080.0, 803.0, 1094.0], [66.0, 1088.0, 541.0, 1105.0], [579.0, 1102.0, 924.0, 1116.0], [50.0, 1107.0, 541.0, 1121.0], [50.0, 1121.0, 428.0, 1138.0], [576.0, 1131.0, 1053.0, 1145.0], [562.0, 1148.0, 1053.0, 1163.0], [85.0, 1149.0, 541.0, 1168.0], [562.0, 1164.0, 1053.0, 1178.0], [86.0, 1169.0, 541.0, 1183.0], [561.0, 1180.0, 977.0, 1195.0], [87.0, 1185.0, 541.0, 1199.0], [84.0, 1201.0, 301.0, 1215.0], [576.0, 1208.0, 1054.0, 1223.0], [65.0, 1216.0, 541.0, 1233.0], [560.0, 1226.0, 869.0, 1239.0], [87.0, 1234.0, 314.0, 1248.0], [65.0, 1249.0, 542.0, 1265.0], [576.0, 1254.0, 1054.0, 1268.0], [86.0, 1267.0, 543.0, 1281.0], [561.0, 1271.0, 1053.0, 1284.0], [84.0, 1281.0, 541.0, 1298.0], [560.0, 1286.0, 1052.0, 1302.0], [83.0, 1299.0, 541.0, 1313.0], [560.0, 1304.0, 850.0, 1317.0]], "bbox_layout": [28.54296875, -2.822265625, 1063.328125, 1325.234375], "text": ["Art. 2. - Le comit\u00e9 central de d\u00e9veloppement rural plac\u00e9", "Arr\u00eat\u00e9 du 24 septembre 1965 relatif aux transports individuels", "sous l'autorit\u00e9 du ministre de l'agriculture et de la r\u00e9forme", "des l\u00e9gumes secs.", "agraire est compos\u00e9 des membres suivants :", "- le directeur de la production v\u00e9g\u00e9tale,", "Le ministre de l'agriculture et de la r\u00e9forme agraire,", "- le directeur de la production animale,", "Vu l'ordonnance du 12 juillet 1962 relative \u00e0 l'organisation", "- le directeur du g\u00e9nie rural,", "du march\u00e9 des c\u00e9r\u00e9ales en Alg\u00e9rie et de l'Office alg\u00e9rien inter-", "professionnel des c\u00e9r\u00e9ales ;", "- le directeur des for\u00eats et de la d\u00e9fense et restauration", "des sols,", "Vu l'arr\u00eat\u00e9 du 7 ao\u00fbt 1962 relatif \u00e0 l'organisation de 18", "- le directeur de l'Office national de la r\u00e9forme agraire,", "campagne de c\u00e9r\u00e9ales ;", "- le directeur des \u00e9tudes et de la planification.", "' Vu le d\u00e9cret", "n\u00ba 64-312 du 23 octobre 1964 concernant la", "Le comit\u00e9 central de d\u00e9veloppement rural peut faire appel", "r\u00e9glementation des l\u00e9gumes secs,", "\u00e0 toute personne qualifi\u00e9e par ses connaissances, des mati\u00e8res", "Arr\u00eate :", "inscrites \u00e0 son ordre du jour.", "Article 1er. - L'article 11 de l'arr\u00eat\u00e9 du 7 vo\u00fbt 1962 susvise", "Art. 3. - Le secr\u00e9tariai est assur\u00e9 par la direction des", "est compl\u00e9t\u00e9 comme suit :", "\u00e9tudes et de la planification qui dresse le proc\u00e8s-verbal des", "s\u00e9ances et en assure la diffusion.", "\u00ab 5\u00b0 - Transports individuels de l\u00e9gumes secs :", "Les r\u00e9unions du comit\u00e9 central de d\u00e9veloppement rural ont", "a) sans formalit\u00e9 pour les quantit\u00e9s n'\u00e9xc\u00e9dant pas cinq", "lieu au moins une fois par mois. L'ordre du jour est adress\u00e9", "kilos circulant dans le p\u00e9rim\u00e8tre de la commune du d\u00e9tenteur ;", "par le secr\u00e9tariat, en m\u00eame temps que les convocations au", "sous couvert d'un titre de mouvement d\u00e9livr\u00e9 par le chef", "moins 8 jours avant chaque s\u00e9ance.", "o)", "de la commune d'origine pour les quantit\u00e9s comprises entre", "Pour chaque s\u00e9ance, un ou plusieurs rapporteurs peuvent", "cinq kilos et vingt cinq kilos circulant dans le p\u00e9rim\u00e8tre de", "\u00eatre d\u00e9sign\u00e9s. Les discussions sont engagees sur la base des", "la commune du d\u00e9tenteur et pour celles \u00e0 destination des", "rapports pr\u00e9sent\u00e9s par eux. Les propositions de d\u00e9cision sont", "communes limitrophes lorsqu'elles n'exc\u00e8dent pas vingt cinq", "soumises \u00e0 l'agr\u00e9ment du ministre de l'agriculture et de la", "kilos ;", "r\u00e9forme agraire.", "sous couvert d'un titre de mouvement d\u00e9livr\u00e9 par le", "C)", "de section des c\u00e9r\u00e9ales, vis\u00e9 pr\u00e9alablement par", "chef", "le", "Art. 4. - Les comit\u00e9s d\u00e9partementaux de d\u00e9veloppement", "sous-pr\u00e9fet et compl\u00e9t\u00e9 par la mention, port\u00e9e par le chef", "rural plac\u00e9s sous l'autorit\u00e9 du pr\u00e9fet sont compos\u00e9s des mem-", "de la commune d'origine, de la date et de l'itin\u00e9raire du", "bres suivants :", "transport pour les quantit\u00e9s sup\u00e9rieures \u00e0 vingt cinq kilos", "- le commissaire d\u00e9partemental de la r\u00e9forme agraire,", "et celles n'exc\u00e9dant pas vingt cinq kilos si elles sont destin\u00e9es", "\u00e0 des communes non limitrophes.", "- le directeur d\u00e9partemental des services agricoles,", "- le conservateur des for\u00eats et de la d\u00e9fense et restauration", "Les titres de mouvement d\u00e9livr\u00e9s conform\u00e9ment aux dispo-", "des sols,", "", "sitions des paragraphes b) et c) ci-dessus, doivent \u00eatre d\u00e9poses", "au si\u00e8ge de la commune d\u00e8s l'arriv\u00e9e des l\u00e9gumes secs au", "- les directeurs des caisses de cr\u00e9dit agricole mutuel,", "lieu de destination. \u00bb", "- le directeur des services v\u00e9t\u00e9rinaires et de l'\u00e9levage,", "Art, 2. - Le directeur de l'Office alg\u00e9rien interprofessionnel", "- l'ing\u00e9nieur du g\u00e9nie rural.", "des c\u00e9r\u00e9ales est charg\u00e9 de l'ex\u00e9cution du pr\u00e9sent arr\u00eat\u00e9 qui", "La pr\u00e9sidence est assur\u00e9e \u00e0 tour de r\u00f4le, par chacun des", "sera publi\u00e9 au Journal officiel de la R\u00e9publique alg\u00e9rienne", "membres d\u00e9sign\u00e9s ci-dessus.", "d\u00e9mocratique et populaire.", "Le secr\u00e9tariat est assur\u00e9 par le directeur d\u00e9partemental des", ". Fait \u00e0 Alger, le 24 septembre 1965,", "services agricoles.", "Ahmed MAHSAS.", "Art. 5. - Les comit\u00e9s de d\u00e9veloppement rural \u00e0 l'\u00e9chelon", "d\u00e9partemental fonctionnent comme le comit\u00e9 de d\u00e9veloppement", "Arr\u00eat\u00e9 du 28 octobre 1965 portant cr\u00e9ation de comit\u00e9s de d\u00e9ve-", "rural \u00e0 l'\u00e9chelon central.", "loppement rural.", "Art. 6.", "- Les comit\u00e9s d'arrondissement de d\u00e9veloppement", "rural, plac\u00e9s sous l'autorit\u00e9 des sous-pr\u00e9fets sont compos\u00e9s", "Le ministre de l'agriculture et de la r\u00e9forme agraire,", "des membres suivants :", "Vu l'ordonnance n\u00ba 65-182 du 10 juillet 1965 portant consti-", "- l'ing\u00e9nieur des travaux des for\u00eats et de la d\u00e9fense et", "tution du Gouvernement ;", "restauration des sols,", "- le directeur des soci\u00e9t\u00e9s agricoles de pr\u00e9voyance,", "Vu le d\u00e9cret n\u00ba 65-234 du 22 septembre 1965 portant r\u00e9orga-", "nisation de l'administration centrale du minist\u00e8re de l'agri-", "- l'ing\u00e9nieur des services agricoles de l'arrondissement,", "culture et de la r\u00e9forme agraire,", "- le d\u00e9l\u00e9gu\u00e9 de l'arrondissement de l'Office national de la", "r\u00e9forme agraire,", "Arr\u00eate :", "- l'ing\u00e9nieur du g\u00e9nie rural,", "Article 1er. - Il est or\u00e9\u00e9 des comit\u00e9s de d\u00e9veloppement rurai", "- le directeur de l'agence locale de cr\u00e9dit.", "\u00e0 l'\u00e9chelon central, d\u00e9partemental et de l'arrondissement. Ces", "comit\u00e9s de d\u00e9veloppement rural sont charg\u00e9s :", "La pr\u00e9sidence est assur\u00e9e \u00e0 tour de r\u00f4le, par chacun des", "membres cit\u00e9s ci-dessus. Le secr\u00e9tariat est assur\u00e9 par l'ing\u00e9-", "d'\u00e9tudier et de suivre les projets de mise en valeur de", "nieur des services agricoles de l'arrondissement ou, \u00e0 d\u00e9faut,", "l'espace rural et les plans de r\u00e9novation rurale, ainsi que", "par le directeur des soci\u00e9t\u00e9s agricoles de pr\u00e9voyance.", "les programmes correspondants et toutes questions se", "rapportant \u00e0 leur ex\u00e9cution,", "Les dits comit\u00e9s fonctionnent comme les comit\u00e9s centraux et", "- de d\u00e9terminer les zones de d\u00e9veloppement et les m\u00e9thodes", "d\u00e9partementaux de d\u00e9veloppement rural.", "de r\u00e9alisation du reboisement,", "- d'examiner toutes les questions relatives \u00e0 la r\u00e9alisation", "Art. 7. - Le secr\u00e9taire g\u00e9n\u00e9ral du minist\u00e8re de l'agriculture", "de la r\u00e9forme agraire, ainsi qu'au fonctionnement des", "et de la r\u00e9forme agraire est charg\u00e9 de l'ex\u00e9cution du pr\u00e9sent", "organismes de tutelle de l'autogestion et des coop\u00e9ratives,", "arr\u00eat\u00e9 qui sera publi\u00e9 au Journal officiel de la R\u00e9publique", "de coordonner les projets de budgets des divers services", "alg\u00e9rienne d\u00e9mocratique et populaire."], "label": "Text", "position": 0}, {"bbox_text": [[575.0, 1332.0, 824.0, 1345.0]], "bbox_layout": [565.71875, 1321.640625, 832.609375, 1356.6796875], "text": ["Fait \u00e0 Alger, le 28 octobre 1965."], "label": "Text", "position": 1}, {"bbox_text": [[61.0, 1343.0, 540.0, 1359.0], [50.0, 1361.0, 333.0, 1375.0]], "bbox_layout": [44.17578125, 1334.62890625, 546.09765625, 1387.44140625], "text": ["La comp\u00e9tence de ces comit\u00e9s s'\u00e9tend aussi bien au secteur", "autog\u00e9r\u00e9 qu'au secteur priv\u00e9 agricole."], "label": "Text", "position": 3}]}, {"index": 6, "page": [{"bbox_text": [[175.0, 37.0, 421.0, 53.0], [197.0, 60.0, 443.0, 78.0], [147.0, 63.0, 177.0, 78.0], [187.0, 85.0, 411.0, 102.0]], "bbox_layout": [141.4765625, 27.4481201171875, 463.890625, 114.248046875], "text": ["MINISTERE DES POSTES", "TELECOMMUNICATIONS", "lai", "ET DES TRANSPORTS"], "label": "SectionHeader", "position": 0}, {"bbox_text": [[55.0, 147.0, 542.0, 161.0], [83.0, 164.0, 264.0, 178.0]], "bbox_layout": [47.275390625, 137.65625, 558.2265625, 188.759765625], "text": ["D\u00e9crets du 27 septembre 1965 portant nomination de sous-", "directeurs (rectificatif)."], "label": "Text", "position": 1}, {"bbox_text": [[162.0, 207.0, 431.0, 222.0]], "bbox_layout": [159.53515625, 197.8125, 437.74609375, 232.8515625], "text": ["(J.O. N\u00ba 82 DU 5 OCTOBRE 1965)"], "label": "SectionHeader", "position": 2}, {"bbox_text": [[197.0, 239.0, 378.0, 253.0]], "bbox_layout": [194.84375, 228.0615234375, 393.8125, 261.7333984375], "text": ["Page 881, l\u00e8re colonne,"], "label": "Text", "position": 3}, {"bbox_text": [[143.0, 267.0, 241.0, 281.0]], "bbox_layout": [82.853515625, 258.994140625, 257.025390625, 291.982421875], "text": ["Au lieu de :"], "label": "SectionHeader", "position": 4}, {"bbox_text": [[69.0, 296.0, 544.0, 310.0], [54.0, 310.0, 545.0, 328.0], [54.0, 329.0, 544.0, 343.0], [53.0, 344.0, 134.0, 359.0]], "bbox_layout": [47.140625, 285.654296875, 559.3046875, 371.279296875], "text": ["Par arr\u00eat\u00e9 du 27 septembre 1965, M. Arezki Amalou est", "nomm\u00e9 en qualit\u00e9 de sous-directeur des affaires communes", "et de l'exploitation \u00e0 la direction des postes et services", "financiers."], "label": "Text", "position": 5}, {"bbox_text": [[143.0, 374.0, 193.0, 387.0]], "bbox_layout": [129.078125, 363.92578125, 210.80078125, 396.23046875], "text": ["Lire :"], "label": "Text", "position": 6}, {"bbox_text": [[66.0, 401.0, 544.0, 417.0], [54.0, 417.0, 545.0, 431.0], [54.0, 436.0, 545.0, 449.0], [53.0, 451.0, 134.0, 464.0]], "bbox_layout": [44.71484375, 392.63671875, 557.95703125, 476.2109375], "text": ["Par d\u00e9cret du 27 septembre 1965, M. Arezki Amalou est", "nomm\u00e9 en qualit\u00e9 de sous-directeur des affaires communes", "et de l'exploitation \u00e0 la direction des postes et services", "financiers."], "label": "Text", "position": 7}, {"bbox_text": [[71.0, 479.0, 293.0, 493.0]], "bbox_layout": [68.029296875, 469.8828125, 307.5625, 502.87109375], "text": ["(Le reste sans changement)."], "label": "Text", "position": 8}, {"bbox_text": [[54.0, 523.0, 543.0, 540.0], [82.0, 542.0, 162.0, 555.0], [92.0, 557.0, 114.0, 565.0]], "bbox_layout": [46.33203125, 512.94921875, 556.33984375, 565.078125], "text": ["Arr\u00eat\u00e9 du 14 octobre 1965 portant autorisation d'exploiter une", "madrague.", "\n"], "label": "Text", "position": 9}, {"bbox_text": [[68.0, 586.0, 543.0, 600.0], [53.0, 604.0, 543.0, 618.0], [53.0, 617.0, 544.0, 636.0], [52.0, 636.0, 302.0, 650.0]], "bbox_layout": [44.17578125, 575.498046875, 557.41796875, 660.439453125], "text": ["Par arr\u00eat\u00e9 du 14 octobre 1965 la soci\u00e9t\u00e9 coop\u00e9rative des", "pecheurs du secteur socialiste d'Arzew (COPESCO) est autoris\u00e9e", "\u00e0 exploiter une madrague au N.E. de la pointe d'Arzew et au", "S.E. de l'\u00eelot du phare d'Arzew."], "label": "Text", "position": 10}, {"bbox_text": [[68.0, 665.0, 541.0, 679.0]], "bbox_layout": [56.708984375, 653.76953125, 555.53125, 688.125], "text": ["La position de cette madrague est d\u00e9termin\u00e9e comme suit :"], "label": "Text", "position": 11}, {"bbox_text": [[345.0, 693.0, 435.0, 705.0], [68.0, 701.0, 237.0, 717.0], [343.0, 710.0, 435.0, 722.0], [436.0, 711.0, 451.0, 721.0]], "bbox_layout": [59.0, 684.189453125, 483.02734375, 734.609375], "text": ["35\u00b0 52' 35\"", "1\u00ba) - Latitude entre", "35\u00b0 52\u2019 17\u201d", "k"], "label": "Table", "position": 12}, {"bbox_text": [[103.0, 738.0, 305.0, 754.0]], "bbox_layout": [82.9208984375, 728.96484375, 319.69140625, 762.63671875], "text": ["- Longitude : 0\u00b0 17' W \u00b7"], "label": "Text", "position": 13}, {"bbox_text": [[67.0, 767.0, 361.0, 781.0]], "bbox_layout": [62.7734375, 757.67578125, 377.37109375, 791.34765625], "text": ["2\u00ba) - Direction de la queue : ouest."], "label": "Text", "position": 14}, {"bbox_text": [[69.0, 796.0, 540.0, 809.0], [90.0, 814.0, 417.0, 828.0]], "bbox_layout": [60.751953125, 785.703125, 560.921875, 835.78125], "text": ["3\u00ba) - Profondeur de l'eau aux angles du corps de la madra-", "gue 30 m c\u00f4t\u00e9 du large, 24 m c\u00f4t\u00e9 terre."], "label": "Text", "position": 15}, {"bbox_text": [[67.0, 842.0, 461.0, 856.0]], "bbox_layout": [60.482421875, 830.8203125, 470.8984375, 864.4921875], "text": ["Ladite madrague aura les dimensions suivantes :"], "label": "Text", "position": 16}, {"bbox_text": [[96.0, 870.0, 483.0, 886.0], [494.0, 873.0, 540.0, 884.0], [95.0, 886.0, 480.0, 905.0], [502.0, 890.0, 541.0, 900.0], [96.0, 904.0, 407.0, 918.0], [486.0, 906.0, 543.0, 918.0]], "bbox_layout": [79.619140625, 862.94921875, 560.921875, 926.69921875], "text": ["Longueur du corps ", "400 m", "Largeur du corps .", "38 m", "Longueur de la queue .......................", "1000 m"], "label": "Table", "position": 17}, {"bbox_text": [[68.0, 931.0, 543.0, 949.0], [52.0, 949.0, 543.0, 963.0], [53.0, 963.0, 542.0, 981.0], [51.0, 982.0, 541.0, 996.0], [53.0, 997.0, 241.0, 1011.0]], "bbox_layout": [42.55859375, 923.10546875, 555.26171875, 1019.66796875], "text": ["Le point d'amarrage du c\u00f4t\u00e9 de terre de la ralingue de la", "queue devra \u00eatre marqu\u00e9 par une tache blanche d'un m\u00e8tre", "de diam\u00e8tre et par un poteau peint en blanc d'une hauteur", "de 1,50 m au-dessus du sol. La nuit, un feu rouge sera fixe", "au sommet de ce poteau."], "label": "Text", "position": 18}, {"bbox_text": [[67.0, 1025.0, 542.0, 1042.0], [51.0, 1043.0, 542.0, 1057.0], [51.0, 1059.0, 542.0, 1074.0], [51.0, 1075.0, 543.0, 1089.0], [52.0, 1090.0, 267.0, 1108.0]], "bbox_layout": [41.345703125, 1016.07421875, 556.609375, 1116.73828125], "text": ["Les permissionnaires seront tenus de placer aux angles les", "plus avanc\u00e9s en mer des filets formant le corps de la madrague", "de bou\u00e9es ou signaux attach\u00e9s aux orins de mouillage sous", "peine de r\u00e9pondre des dommages qui pourraient r\u00e9sulter du", "d\u00e9faut de cette pr\u00e9caution."], "label": "Text", "position": 19}, {"bbox_text": [[68.0, 1120.0, 541.0, 1136.0], [51.0, 1135.0, 543.0, 1153.0], [50.0, 1155.0, 542.0, 1167.0], [50.0, 1168.0, 541.0, 1185.0], [51.0, 1187.0, 517.0, 1201.0]], "bbox_layout": [40.671875, 1111.77734375, 555.53125, 1211.07421875], "text": ["Ils s'engagent en outre, \u00e0 entretenir \u00e0 leurs frais, constam-", "ment allum\u00e9s pendant la nuit, deux feux rouges plac\u00e9s sur", "les bateaux mouill\u00e9s aux extr\u00eamit\u00e9s de la partie flottante.", "depuis l'\u00e9poque \u00e0 laquelle les travaux de calaison seront entre-", "pris jusqu'\u00e0 entier ach\u00e8vement des travaux de d\u00e9calaison."], "label": "Text", "position": 20}, {"bbox_text": [[66.0, 1215.0, 542.0, 1229.0], [50.0, 1230.0, 543.0, 1248.0], [50.0, 1248.0, 542.0, 1262.0], [49.0, 1264.0, 377.0, 1278.0]], "bbox_layout": [41.2109375, 1205.4296875, 555.53125, 1288.3203125], "text": ["La zone de protection s'\u00e9tendra dans un rayon de 1 km", "autour du point d'intersection du corps et de la queue de la", "madrague. Les points o\u00f9 ce rayon rencontrera le roc seront", "marqu\u00e9s comme l'extr\u00eamit\u00e9 de la queue."], "label": "Text", "position": 21}, {"bbox_text": [[66.0, 1293.0, 541.0, 1307.0], [50.0, 1310.0, 541.0, 1324.0]], "bbox_layout": [41.884765625, 1283.359375, 554.9921875, 1333.4375], "text": ["Aucune madrague ne pourra \u00eatre install\u00e9e \u00e0 une distance", "inf\u00e9rieure \u00e0 trois milles de celle qui fait l'objet du dit arr\u00eat\u00e9."], "label": "Text", "position": 22}, {"bbox_text": [[65.0, 1338.0, 543.0, 1352.0], [50.0, 1355.0, 543.0, 1369.0], [50.0, 1372.0, 544.0, 1387.0], [51.0, 1389.0, 225.0, 1398.0]], "bbox_layout": [38.919921875, 1329.84375, 553.375, 1410.0], "text": ["L'exercice de la p\u00eache de la madrague commencera chaque", "ann\u00e9e au 1\u00ba septembre et fermera le 31 d\u00e9cembre. Pendant", "cette p\u00e9riode les p\u00eacheurs ne pourront tendre aucun filet dans", "la zone de protection."], "label": "Text", "position": 23}, {"bbox_text": [[580.0, 36.0, 1054.0, 49.0], [565.0, 53.0, 1054.0, 66.0], [565.0, 68.0, 1055.0, 82.0], [565.0, 86.0, 1054.0, 100.0], [565.0, 101.0, 1055.0, 116.0], [565.0, 119.0, 1055.0, 133.0], [565.0, 136.0, 1000.0, 147.0]], "bbox_layout": [556.5546875, 26.99951171875, 1067.1015625, 159.10888671875], "text": ["Ils pourront toutefois, caler des lignes de fonds ou des lignes", "courantes \u00e0 une distance de 300 m du corps de la madrague.", "La madrague devra \u00eatre d\u00e9clar\u00e9e chaque ann\u00e9e, imm\u00e9diatement", "apr\u00e8s la saison de p\u00eache. L'op\u00e9ration du d\u00e9calage commencera", "le 31 d\u00e9cembre et devra \u00eatre termin\u00e9e le 10 du mois suivant", "au plus tard. Celle de son r\u00e9tablissement \u00e0 la saison suivante", "pourra \u00eatre entreprise 10 jours avant le 1\u00bar septembre."], "label": "Text", "position": 24}, {"bbox_text": [[579.0, 163.0, 1053.0, 178.0], [565.0, 180.0, 1056.0, 193.0], [565.0, 197.0, 1055.0, 211.0], [564.0, 214.0, 1055.0, 226.0], [565.0, 231.0, 664.0, 245.0]], "bbox_layout": [555.4765625, 154.83154296875, 1070.3359375, 255.068359375], "text": ["Les dommages caus\u00e9s \u00e0 la madrague par les batiments, ba-", "teaux de p\u00eache ou autres, et \u00e0 ceux-ci par la madrague non", "pourvue des feux qui doivent y \u00eatre entretenus, seront constat\u00e9s", "par proc\u00e8s-verbaux dress\u00e9s conform\u00e9ment au d\u00e9cret-loi du 9", "janvier 1852."], "label": "Text", "position": 25}, {"bbox_text": [[579.0, 259.0, 1054.0, 273.0], [563.0, 278.0, 1054.0, 289.0], [564.0, 294.0, 999.0, 305.0]], "bbox_layout": [556.015625, 249.423828125, 1070.875, 316.93359375], "text": ["Lorsque la madrague sera install\u00e9e, avis en sera donn\u00e9 aux", "navigateurs aux frais du permissionnaire par insertion dans", "la presse et affiches timbr\u00e9es tir\u00e9es \u00e0 50 exemplaires."], "label": "Text", "position": 26}, {"bbox_text": [[669.0, 371.0, 954.0, 386.0]], "bbox_layout": [661.1328125, 359.82421875, 962.5234375, 399.6484375], "text": ["MINISTERE DU COMMERCE"], "label": "SectionHeader", "position": 27}, {"bbox_text": [[565.0, 433.0, 1054.0, 443.0], [595.0, 450.0, 782.0, 463.0]], "bbox_layout": [555.4765625, 419.98046875, 1068.1796875, 470.7421875], "text": ["Arr\u00eat\u00e9 du 28 octobre 1965 portant contingentement de certains", "produits \u00e0 l'exportation."], "label": "Text", "position": 28}, {"bbox_text": [[578.0, 493.0, 778.0, 507.0]], "bbox_layout": [567.3359375, 482.529296875, 796.4921875, 516.201171875], "text": ["Le ministre du commerce,"], "label": "Text", "position": 29}, {"bbox_text": [[580.0, 522.0, 1053.0, 533.0], [565.0, 540.0, 767.0, 553.0]], "bbox_layout": [560.328125, 512.607421875, 1065.484375, 562.685546875], "text": ["Vu l'ordonnance n\u00ba 65-182 du 10 juillet 1965 portant consti-", "tution du Gouvernement ;"], "label": "Text", "position": 30}, {"bbox_text": [[580.0, 567.0, 1053.0, 581.0], [565.0, 585.0, 825.0, 599.0]], "bbox_layout": [560.328125, 556.69921875, 1067.640625, 608.828125], "text": ["Vu le d\u00e9cret n\u00ba 64-342 du 2 d\u00e9cembre 1964 relatif aux attri-", "butions du ministre du commerce,"], "label": "Text", "position": 31}, {"bbox_text": [[655.0, 614.0, 719.0, 627.0]], "bbox_layout": [630.9453125, 604.55078125, 730.7265625, 637.5390625], "text": ["Arr\u00eate :"], "label": "Text", "position": 32}, {"bbox_text": [[579.0, 642.0, 1053.0, 655.0], [565.0, 660.0, 1056.0, 671.0], [565.0, 675.0, 1053.0, 689.0], [564.0, 693.0, 909.0, 705.0]], "bbox_layout": [559.7890625, 632.578125, 1069.2578125, 715.46875], "text": ["Article 1\u00ba. - Sont soumis \u00e0 autorisation pr\u00e9alable \u00e0 l'ex-", "portation vers tous pays \u00e0 dater de la publication du pr\u00e9sent", "arr\u00eat\u00e9 au Journal officiel de la R\u00e9publique alg\u00e9rienne d\u00e9mo-", "cratique et populaire, les produits ci-apr\u00e8s :"], "label": "Text", "position": 33}, {"bbox_text": [[580.0, 720.0, 1054.0, 733.0]], "bbox_layout": [571.109375, 709.82421875, 1067.640625, 743.49609375], "text": ["Ex OI. OI. - Chevaux, mulets, bardots vivants de boucherie."], "label": "Text", "position": 34}, {"bbox_text": [[649.0, 749.0, 1053.0, 763.0], [580.0, 751.0, 644.0, 761.0], [929.0, 765.0, 1054.0, 778.0], [811.0, 766.0, 930.0, 779.0], [603.0, 767.0, 671.0, 780.0], [671.0, 767.0, 695.0, 780.0], [699.0, 767.0, 759.0, 780.0], [760.0, 767.0, 810.0, 780.0], [563.0, 768.0, 589.0, 779.0], [563.0, 782.0, 1053.0, 795.0], [564.0, 800.0, 1053.0, 812.0], [565.0, 816.0, 1010.0, 828.0]], "bbox_layout": [554.3984375, 739.21875, 1070.3359375, 838.515625], "text": ["- Les demandes d'autorisation d'exportation \u00e9tablies", "Art. 2 . -", "destin\u00e9s \u00e0 la", "les produits", "mod\u00e8le", "01", "A.Z.F", "pour", "sur", "zone-franc, et sur mod\u00e8le 02 pour les produits destin\u00e9s aux", "pays autres que ceux de la zone-franc devront \u00eatre d\u00e9pos\u00e9es", "au minist\u00e8re de l'agriculture et de la r\u00e9forme agraire."], "label": "Text", "position": 35}, {"bbox_text": [[580.0, 846.0, 1053.0, 857.0], [565.0, 861.0, 1047.0, 875.0], [564.0, 879.0, 1051.0, 890.0]], "bbox_layout": [554.9375, 834.23828125, 1066.5625, 902.08984375], "text": ["Art. 3. - Le directeur du commerce ext\u00e9rieur est charge", "de l'ex\u00e9cution du pr\u00e9sent arr\u00eat\u00e9 qui sera publi\u00e9 au Journas", "officiel de la R\u00e9publique alg\u00e9rienne d\u00e9mocratique et populaire"], "label": "Text", "position": 36}, {"bbox_text": [[580.0, 906.0, 837.0, 920.0]], "bbox_layout": [570.03125, 896.4453125, 852.015625, 930.1171875], "text": ["Fait \u00e0 Alger, le 28 octobre 1965."], "label": "Text", "position": 37}, {"bbox_text": [[696.0, 934.0, 914.0, 948.0]], "bbox_layout": [689.1640625, 925.15625, 928.0234375, 958.828125], "text": ["P. le ministre du commerce,"], "label": "Text", "position": 38}, {"bbox_text": [[723.0, 963.0, 890.0, 977.0], [720.0, 985.0, 894.0, 998.0]], "bbox_layout": [706.953125, 953.8671875, 899.453125, 1006.6796875], "text": ["Le secr\u00e9taire g\u00e9n\u00e9ral,", "Mohamed LEMKAMI."], "label": "Text", "position": 39}, {"bbox_text": [[563.0, 1041.0, 1053.0, 1055.0], [595.0, 1060.0, 678.0, 1071.0]], "bbox_layout": [557.6328125, 1031.11328125, 1066.0234375, 1081.19140625], "text": ["Arr\u00eat\u00e9 du 28 octobre 1965 relatif aux conditions d'importation", "de textiles."], "label": "Text", "position": 40}, {"bbox_text": [[577.0, 1117.0, 781.0, 1130.0]], "bbox_layout": [567.875, 1106.30859375, 792.71875, 1139.98046875], "text": ["Le ministre du commerce,"], "label": "Text", "position": 41}, {"bbox_text": [[580.0, 1144.0, 1054.0, 1158.0], [564.0, 1160.0, 767.0, 1176.0]], "bbox_layout": [557.09375, 1132.96875, 1067.640625, 1185.78125], "text": ["Vu l'ordonnance n\u00ba 65-182 du 10 juillet 1965 portant consti-", "tution du Gouvernement ;"], "label": "Text", "position": 42}, {"bbox_text": [[580.0, 1188.0, 1054.0, 1204.0], [564.0, 1206.0, 815.0, 1220.0]], "bbox_layout": [555.4765625, 1180.13671875, 1066.0234375, 1230.21484375], "text": ["Vu le d\u00e9cret n\u00ba 64-233 du 10 ao\u00fbt 1964 fixant les statuts", "des groupements professionnels ;"], "label": "Text", "position": 43}, {"bbox_text": [[580.0, 1234.0, 1053.0, 1248.0], [563.0, 1251.0, 822.0, 1265.0]], "bbox_layout": [556.015625, 1224.5703125, 1067.640625, 1276.015625], "text": ["Vu le d\u00e9cret n\u00ba 64-342 du 2 d\u00e9cembre 1964 relatif aux attri-", "butions du ministre du commerce,"], "label": "Text", "position": 44}, {"bbox_text": [[580.0, 1278.0, 1053.0, 1293.0], [563.0, 1296.0, 1054.0, 1310.0], [565.0, 1313.0, 642.0, 1327.0]], "bbox_layout": [556.015625, 1269.6875, 1069.796875, 1337.5390625], "text": ["Vu l'arr\u00eat\u00e9 du 26 d\u00e9cembre 1964 portant cr\u00e9ation du grou-", "pement professionnel d'importation de textiles industriels", "(GADIT),"], "label": "Text", "position": 45}, {"bbox_text": [[654.0, 1342.0, 719.0, 1355.0]], "bbox_layout": [623.9375, 1329.84375, 736.65625, 1363.515625], "text": ["Arr\u00eate :"], "label": "SectionHeader", "position": 46}, {"bbox_text": [[668.0, 1371.0, 1052.0, 1384.0], [578.0, 1373.0, 667.0, 1383.0], [569.0, 1388.0, 1053.0, 1398.0]], "bbox_layout": [557.09375, 1357.87109375, 1070.875, 1410.0], "text": ["- A compter de la date de publication du pr\u00e9-", "Article 1er.", "ent arr\u00eat\u00e9, toutes les importations de textiles r\u00e9sultant des"], "label": "Text", "position": 47}]}, {"index": 7, "page": [{"bbox_text": [[31.0, 22.0, 528.0, 36.0], [31.0, 42.0, 526.0, 57.0], [30.0, 63.0, 191.0, 77.0]], "bbox_layout": [20.45068359375, 12.81494140625, 541.08056640625, 88.01513671875], "text": ["positions tarifaires douani\u00e8res : 51-04 A sont soumises au", "visa du groupement professionhel d'importation des textiles", "industriels (GADIT)."], "label": "Text", "position": 0}, {"bbox_text": [[48.0, 91.0, 526.0, 105.0], [30.0, 112.0, 525.0, 125.0], [30.0, 133.0, 225.0, 147.0]], "bbox_layout": [20.8377685546875, 81.6015625, 538.5, 157.1435546875], "text": ["Art. 2. - Les importations des t\u00e8xtiles vis\u00e9es \u00e0 l'article 1\u00bar", "supportent le chargement pr\u00e9vu \u00e0 l'arti\u00e9le 11 de l'arr\u00eat\u00e9 sus-", "vis\u00e9 du 26 d\u00e9cembre 1964."], "label": "Text", "position": 1}, {"bbox_text": [[47.0, 161.0, 525.0, 174.0], [32.0, 181.0, 518.0, 195.0], [30.0, 201.0, 523.0, 217.0]], "bbox_layout": [20.708740234375, 149.619140625, 536.693603515625, 227.3828125], "text": ["Art. 3. - Le directeur du commerce ext\u00e9fieur est charg\u00e9", "de l'ex\u00e9cution du pr\u00e9sent arr\u00eat\u00e9 qui sera publi\u00e9 au Journal", "officiel de la R\u00e9publique algerienne d\u00e9mocratique et populaire"], "label": "Text", "position": 2}, {"bbox_text": [[45.0, 232.0, 284.0, 244.0]], "bbox_layout": [42.19195556640625, 220.5419921875, 296.184814453125, 256.6064453125], "text": ["Fait \u00e0 Alger, le 28 octobre 1965."], "label": "Text", "position": 3}, {"bbox_text": [[165.0, 260.0, 386.0, 274.0]], "bbox_layout": [148.962890625, 249.08203125, 399.66552734375, 284.8046875], "text": ["P. le ministre du commerce,"], "label": "Text", "position": 4}, {"bbox_text": [[190.0, 288.0, 360.0, 303.0], [187.0, 309.0, 362.0, 324.0]], "bbox_layout": [173.3492431640625, 276.42578125, 377.98876953125, 331.2890625], "text": ["Le secretaire g\u00e9neral,", "Mohamed LEMKAMI."], "label": "Text", "position": 5}, {"bbox_text": [[644.0, 22.0, 951.0, 39.0], [713.0, 46.0, 883.0, 64.0]], "bbox_layout": [635.1416015625, 12.515869140625, 963.77734375, 77.889404296875], "text": ["MINISTERE DE LA JEUNESSE", "ET DES SPORTS"], "label": "SectionHeader", "position": 6}, {"bbox_text": [[549.0, 89.0, 1042.0, 104.0], [577.0, 109.0, 619.0, 120.0]], "bbox_layout": [533.9833984375, 79.3798828125, 1052.548828125, 133.388671875], "text": ["Arr\u00eat\u00e9 du 28 septembre 1965 portant cr\u00e9ation de foyers d'ac-", "cueil."], "label": "Text", "position": 7}, {"bbox_text": [[562.0, 143.0, 900.0, 159.0]], "bbox_layout": [555.66015625, 133.7255859375, 912.166015625, 169.27734375], "text": ["L'e ministre de la jeunesse et des sports,"], "label": "Text", "position": 8}, {"bbox_text": [[561.0, 164.0, 1044.0, 179.0], [548.0, 183.0, 663.0, 197.0]], "bbox_layout": [541.208984375, 155.6005859375, 1057.7099609375, 208.4130859375], "text": ["Sur proposition du directeur de la jeunesse et de l'\u00e9duca-", "tion populaire,"], "label": "Text", "position": 9}, {"bbox_text": [[562.0, 200.0, 1042.0, 218.0], [548.0, 217.0, 1043.0, 236.0], [546.0, 236.0, 772.0, 249.0]], "bbox_layout": [535.015625, 193.02734375, 1056.677734375, 263.61328125], "text": ["Vu le d\u00e9cret n\u00ba 65-215 du 19 aout 1965 r\u00e9latif aux centres", "sp\u00e9cialis\u00e9s et foyers d'accueil charg\u00e9s de la sauvegarde de", "l'enfance et de l'adolescence,"], "label": "Text", "position": 10}, {"bbox_text": [[639.0, 255.0, 702.0, 269.0]], "bbox_layout": [611.400390625, 249.5947265625, 707.78515625, 284.2919921875], "text": ["Arr\u00eate :"], "label": "Text", "position": 11}, {"bbox_text": [[679.0, 276.0, 1042.0, 292.0], [562.0, 277.0, 677.0, 288.0], [548.0, 291.0, 1043.0, 309.0], [547.0, 311.0, 624.0, 324.0]], "bbox_layout": [538.1123046875, 266.3427734375, 1054.61328125, 335.2197265625], "text": ["Pour assurer la sauvegarde et la protection", "Article 1er. -", "de l'enfatice et de l'adblescence, sont cr\u00e9\u00e9s les foyers d'accueil", "ci-apr\u00e8s :"], "label": "Text", "position": 12}, {"bbox_text": [[946.0, 360.0, 1034.0, 375.0], [36.0, 361.0, 170.0, 376.0], [237.0, 361.0, 401.0, 375.0], [524.0, 361.0, 617.0, 375.0], [719.0, 361.0, 924.0, 375.0], [140.0, 385.0, 147.0, 392.0], [714.0, 422.0, 852.0, 437.0], [72.0, 423.0, 134.0, 438.0], [207.0, 423.0, 255.0, 438.0], [461.0, 423.0, 508.0, 437.0], [714.0, 441.0, 760.0, 455.0], [984.0, 441.0, 1001.0, 453.0], [983.0, 455.0, 1002.0, 469.0], [460.0, 457.0, 527.0, 471.0], [713.0, 457.0, 779.0, 471.0], [209.0, 458.0, 255.0, 471.0], [48.0, 473.0, 155.0, 487.0], [208.0, 473.0, 325.0, 487.0], [460.0, 473.0, 577.0, 487.0], [712.0, 473.0, 827.0, 487.0], [983.0, 473.0, 1002.0, 486.0], [70.0, 490.0, 134.0, 505.0], [460.0, 490.0, 551.0, 506.0], [976.0, 490.0, 1002.0, 505.0], [207.0, 491.0, 300.0, 505.0], [713.0, 491.0, 802.0, 505.0], [714.0, 506.0, 844.0, 520.0], [207.0, 507.0, 261.0, 520.0], [460.0, 507.0, 515.0, 520.0], [975.0, 507.0, 1002.0, 521.0], [55.0, 522.0, 148.0, 537.0], [711.0, 522.0, 934.0, 537.0], [207.0, 523.0, 258.0, 537.0], [460.0, 525.0, 510.0, 537.0], [982.0, 525.0, 1003.0, 537.0], [207.0, 540.0, 289.0, 553.0], [460.0, 540.0, 550.0, 554.0], [712.0, 540.0, 787.0, 553.0], [975.0, 540.0, 1002.0, 554.0], [75.0, 555.0, 131.0, 570.0], [206.0, 556.0, 255.0, 570.0], [460.0, 557.0, 508.0, 570.0], [713.0, 557.0, 760.0, 570.0], [975.0, 557.0, 1002.0, 570.0], [206.0, 572.0, 283.0, 585.0], [460.0, 572.0, 536.0, 586.0], [713.0, 572.0, 790.0, 586.0], [975.0, 574.0, 1002.0, 588.0], [59.0, 588.0, 145.0, 603.0], [207.0, 590.0, 278.0, 603.0], [460.0, 590.0, 532.0, 604.0], [714.0, 590.0, 880.0, 604.0], [982.0, 590.0, 1002.0, 604.0], [206.0, 605.0, 294.0, 618.0], [460.0, 606.0, 525.0, 619.0], [713.0, 606.0, 786.0, 619.0], [983.0, 607.0, 1002.0, 621.0], [206.0, 623.0, 294.0, 635.0], [460.0, 623.0, 546.0, 637.0], [713.0, 623.0, 798.0, 637.0], [983.0, 623.0, 1002.0, 637.0], [206.0, 638.0, 280.0, 651.0], [713.0, 639.0, 784.0, 653.0], [982.0, 639.0, 1002.0, 653.0], [460.0, 640.0, 531.0, 654.0], [38.0, 652.0, 163.0, 670.0], [206.0, 655.0, 308.0, 669.0], [459.0, 655.0, 585.0, 669.0], [713.0, 655.0, 838.0, 669.0], [983.0, 656.0, 1002.0, 669.0], [207.0, 669.0, 266.0, 686.0], [39.0, 670.0, 164.0, 686.0], [711.0, 672.0, 770.0, 686.0], [460.0, 673.0, 518.0, 687.0], [977.0, 673.0, 1002.0, 687.0], [70.0, 688.0, 133.0, 702.0], [206.0, 688.0, 262.0, 701.0], [711.0, 688.0, 768.0, 702.0], [459.0, 689.0, 515.0, 702.0], [975.0, 689.0, 1002.0, 702.0], [206.0, 704.0, 251.0, 717.0], [712.0, 705.0, 754.0, 719.0], [982.0, 705.0, 1002.0, 719.0], [460.0, 707.0, 503.0, 719.0], [206.0, 721.0, 265.0, 735.0], [460.0, 722.0, 529.0, 735.0], [711.0, 722.0, 781.0, 735.0], [982.0, 722.0, 1002.0, 736.0], [206.0, 737.0, 265.0, 751.0], [460.0, 739.0, 516.0, 752.0], [711.0, 739.0, 768.0, 752.0], [983.0, 739.0, 1002.0, 752.0], [64.0, 751.0, 144.0, 767.0], [206.0, 753.0, 272.0, 767.0], [460.0, 754.0, 530.0, 767.0], [711.0, 754.0, 892.0, 768.0], [975.0, 754.0, 1002.0, 768.0], [206.0, 769.0, 272.0, 783.0], [459.0, 772.0, 524.0, 785.0], [712.0, 772.0, 776.0, 786.0], [981.0, 772.0, 1001.0, 786.0], [73.0, 784.0, 127.0, 800.0], [206.0, 786.0, 249.0, 800.0], [460.0, 787.0, 502.0, 801.0], [712.0, 787.0, 814.0, 801.0], [975.0, 787.0, 1001.0, 802.0], [206.0, 803.0, 286.0, 817.0], [460.0, 805.0, 539.0, 817.0], [713.0, 805.0, 791.0, 819.0], [982.0, 805.0, 1001.0, 819.0], [206.0, 820.0, 269.0, 833.0], [460.0, 820.0, 509.0, 834.0], [711.0, 820.0, 762.0, 835.0], [982.0, 822.0, 1002.0, 836.0], [65.0, 836.0, 136.0, 850.0], [206.0, 837.0, 291.0, 850.0], [460.0, 837.0, 542.0, 851.0], [710.0, 837.0, 796.0, 851.0], [982.0, 838.0, 1001.0, 851.0], [73.0, 852.0, 127.0, 866.0], [207.0, 852.0, 277.0, 867.0], [712.0, 853.0, 782.0, 869.0], [460.0, 854.0, 529.0, 868.0], [982.0, 856.0, 1002.0, 869.0], [44.0, 887.0, 81.0, 900.0], [136.0, 887.0, 380.0, 901.0], [82.0, 889.0, 102.0, 899.0], [382.0, 889.0, 410.0, 901.0], [409.0, 889.0, 524.0, 901.0], [562.0, 889.0, 1042.0, 903.0], [27.0, 901.0, 525.0, 919.0], [546.0, 904.0, 1042.0, 920.0], [28.0, 920.0, 525.0, 936.0], [546.0, 921.0, 653.0, 934.0], [27.0, 934.0, 523.0, 952.0], [562.0, 939.0, 1042.0, 957.0], [27.0, 954.0, 381.0, 967.0], [546.0, 957.0, 588.0, 972.0], [592.0, 959.0, 669.0, 971.0], [675.0, 959.0, 928.0, 973.0], [928.0, 960.0, 1040.0, 973.0], [545.0, 972.0, 690.0, 991.0], [41.0, 982.0, 325.0, 996.0], [636.0, 992.0, 701.0, 1005.0]], "bbox_layout": [16.837890625, 333.6767578125, 1052.548828125, 1015.56640625], "text": ["CAPACITE", "DEPARTEMENT", "ARRONDISSEMENT", "COMMUNE", "LIEU D'IMPLANTATION", "", "Villa Mahieddine,", "ALGER", "Alger,", "Alger.", "Alger,", "90", " 80", "Ch\u00e9raga", "Ch\u00e9raga,", "Alger;", "TIZI OUZOU", "Bordj Menaiel,", "Bordj M\u00e9naiel,", "Bordj M\u00e9naiel,", "50", "MEDEA", "Bou Sa\u00e2da,", "100", "Bou Sa\u00e2da,", "Bou Saada,", "Cit\u00e9 Belombarge,", "Djelfa,", "Djelfa,", "100", "EL ASNAM", "Sidi Akacha, ex-Montenotte", "T\u00e9n\u00e8s,", "T\u00e9n\u00e8s,", "80", "El Asna.n,", "Bou Kadir,", "Malakoff,", "100", "SAIDA", "Saida,", "Saida;", "Saida,", "100", "M\u00e9ch\u00e9ria,", "M\u00e9cheria,", "M\u00e9ch\u00e9ria,", "100", "TLEMCEN", "Tlemcen,", "Tlemcen,", "Monast\u00e8re St Benoit,", "00", "Ghazaouet,", "Djebala,", "Souahlia,", "80", "Ghazaouet,", "Ghazaouet,", "Ghazaouet,", "80", "Maghnia.", "Maghnia,", "80", "Maghnia,", "MOSTAGANEM", "Mostaganem,", "Hassi Mam\u00e8che,", "Hassi Mam\u00e8che,", "80", "Skikda,", "CONSTANTINE", "Skikda,", "Skikda,", "110", "BATNA", "Biskra,", "Biskra,", "Biskra,", "100", "Arris,", "Arris,", "go", "Arris,", "Barika,", "N'Gaous,", "N'Gaous,", "95", "Barika,", "Barika,", "Barika,", "60", "ANNABA", "Guelma,", "Belkheir,", "Belkheir, ex-Millesimo,", "100", "T\u00e9bessa,", "T\u00e9bessa,", "T\u00e9bessa,", "80", "SETIF", "S\u00e9tif,", "Setif,", "Cit\u00e9 Bel Air,", "120", "El Eulma,", "El Eulma,", "El Eulma,", "50", "Bejaia, .", "Tichy,", "Tichy,", "80", "SAOURA", "Timimoun;", "Timimoun,", "Timim-un;", "85", "OASIS", "El Oued,", "El Oued.", "El Oued,", "80", "Art.", "Le directeur de la jeunesse", "2.", "et ", "de l'\u00e9ducation", "Vu le d\u00e9eret n\u00ba 64-161 du 8 juin 1964 prorogeant jusqu'\u00e0", "populaire et le directeur de l'administration generale sont", "nouvel ordre les dispositions du decret n\u00ba 63-193 du 30 mai", "charg\u00e9s, chacun en ce qui le concerne, de l'ex\u00e9cution du", "1963 susvis\u00e9 :", "pr\u00e9sent arr\u00eat\u00e9 qui sera publi\u00e9 au Journal officiel de la R\u00e9pu-", "Vu le d\u00e9cret n\u00ba 65-38 du 10 f\u00e9vrier 1965 portant cr\u00e9ation", "blique alg\u00e9rienne d\u00e9mocratique et populaire.", "d\u2019un", "certificat", "d'aptitude professionnelle de ", "moniteurs de", "maisons d'enfants,", "Fait \u00e0 Alger, le 28 septembre 1965.", "Arr\u00eate :"], "label": "Table", "position": 13}, {"bbox_text": [[162.0, 1009.0, 384.0, 1024.0]], "bbox_layout": [156.8336181640625, 1002.40234375, 392.9560546875, 1037.44140625], "text": ["Abdelkrini BENMAHMOUD."], "label": "Text", "position": 14}, {"bbox_text": [[27.0, 1068.0, 522.0, 1083.0], [57.0, 1085.0, 522.0, 1099.0], [56.0, 1102.0, 331.0, 1116.0]], "bbox_layout": [16.579833984375, 1055.72265625, 534.629150390625, 1126.30859375], "text": ["Arr\u00eat\u00e9 du 25 octobre 1965 organisant un stage de formation", "de moniteurs de maisons d'enfants \u00e0 l'\u00e9cole nationale de", "formation d'\u00e9ducateurs sp\u00e9cialis\u00e9s."], "label": "Text", "position": 15}, {"bbox_text": [[40.0, 1152.0, 366.0, 1168.0]], "bbox_layout": [34.5147705078125, 1142.5390625, 376.95654296875, 1177.578125], "text": ["Le ministre de la jeunesse et des sports,"], "label": "Text", "position": 16}, {"bbox_text": [[40.0, 1186.0, 522.0, 1204.0], [24.0, 1205.0, 192.0, 1220.0]], "bbox_layout": [14.7734375, 1178.76953125, 533.85498046875, 1228.84765625], "text": ["Bur proposition du directeur g\u00e9n\u00e9ral de la jeunesse et de", "l'\u00e9ducation populaire,"], "label": "Text", "position": 17}, {"bbox_text": [[41.0, 1238.0, 521.0, 1252.0], [25.0, 1255.0, 522.0, 1270.0], [23.0, 1272.0, 134.0, 1285.0]], "bbox_layout": [14.1282958984375, 1228.671875, 532.306640625, 1296.5234375], "text": ["Vit le d\u00e9cret n\u00ba 03-193 du 30 mai 1963 fixant les modalit\u00e9s", "de recrutement de certains agents du minist\u00e8re de la jeunesse", "et des sports :"], "label": "Text", "position": 18}, {"bbox_text": [[41.0, 1305.0, 523.0, 1321.0], [24.0, 1324.0, 505.0, 1339.0]], "bbox_layout": [13.22509765625, 1297.03125, 530.75830078125, 1348.4765625], "text": ["Vu le d\u00e9cret n\u00ba 63-227 du 3 juillet 1963 portant cr\u00e9ation", "de l'\u00e9cole nationale de formation d'\u00e9ducateurs sp\u00e9cialis\u00e9s ;"], "label": "Text", "position": 19}, {"bbox_text": [[562.0, 939.0, 1042.0, 957.0], [546.0, 957.0, 588.0, 972.0], [592.0, 959.0, 669.0, 971.0], [675.0, 959.0, 928.0, 973.0], [928.0, 960.0, 1040.0, 973.0], [545.0, 972.0, 690.0, 991.0]], "bbox_layout": [536.0478515625, 935.41015625, 1055.6455078125, 1003.26171875], "text": ["Vu le d\u00e9cret n\u00ba 65-38 du 10 f\u00e9vrier 1965 portant cr\u00e9ation", "d\u2019un", "certificat", "d'aptitude professionnelle de ", "moniteurs de", "maisons d'enfants,"], "label": "Text", "position": 21}, {"bbox_text": [[561.0, 1007.0, 1041.0, 1024.0], [545.0, 1024.0, 1043.0, 1038.0], [545.0, 1040.0, 1041.0, 1057.0], [545.0, 1058.0, 657.0, 1071.0]], "bbox_layout": [535.015625, 997.6171875, 1056.677734375, 1081.875], "text": ["Article 1\u00bar. - Un stage de formation de moniteurs de mai-", "sons d'enfants se d\u00e9roulera \u00e0 l'\u00e9cole nationale de formation", "d'\u00e9ducateurs sp\u00e9cialis\u00e9s d'Ain Benian (Alger) du 4 janvier", "au 7 mai 1966."], "label": "Text", "position": 23}, {"bbox_text": [[560.0, 1078.0, 1042.0, 1096.0], [545.0, 1097.0, 1041.0, 1111.0], [545.0, 1114.0, 674.0, 1127.0]], "bbox_layout": [536.56396484375, 1069.39453125, 1055.12939453125, 1137.24609375], "text": ["Art. 2. - Sont admis \u00e0 ce stage, apr\u00e8s avoir subi le concours", "d'entr\u00e9e \u00e0 l'\u00e9cole, les candidats remplissant l'une des condi-", "tions suivantes :"], "label": "Text", "position": 24}, {"bbox_text": [[560.0, 1136.0, 1042.0, 1150.0]], "bbox_layout": [552.04736328125, 1125.44921875, 1053.06494140625, 1161.85546875], "text": ["- \u00eatre titulaire du certificat d'\u00e9tudes primaires \u00e9l\u00e9mentaires,"], "label": "Text", "position": 25}, {"bbox_text": [[579.0, 1157.0, 1042.0, 1172.0], [583.0, 1174.0, 1042.0, 1190.0], [582.0, 1192.0, 659.0, 1206.0]], "bbox_layout": [552.5634765625, 1145.95703125, 1055.6455078125, 1217.91015625], "text": ["poss\u00e9der un certificat de scolarit\u00e9 de la classe de 4\u00e8me", "incluse des lyc\u00e9es et coll\u00e8ges d'enseignement g\u00e9n\u00e9ral et", "technique."], "label": "ListItem", "position": 26}, {"bbox_text": [[559.0, 1211.0, 1040.0, 1228.0], [545.0, 1229.0, 1042.0, 1243.0], [543.0, 1245.0, 1040.0, 1259.0], [545.0, 1262.0, 1040.0, 1276.0], [544.0, 1279.0, 839.0, 1293.0]], "bbox_layout": [533.46728515625, 1201.328125, 1056.16162109375, 1301.9921875], "text": ["Art. 3. - Le directeur de la jeunesse et de l'\u00e9ducation", "populaire et le directeur de l'administration g\u00e9n\u00e9rale sont", "charges, chacun en ce qui ie concerne, de l'ex\u00e9cution du pr\u00e9-", "sent arr\u00eat\u00e9 qui sera publi\u00e9 au Journal officiel de la R\u00e9publique", "alg\u00e9rienne d\u00e9mocratique et populaire."], "label": "Text", "position": 27}, {"bbox_text": [[358.0, 1380.0, 680.0, 1395.0]], "bbox_layout": [356.4404296875, 1367.44140625, 705.720703125, 1405.21484375], "text": ["IMPRIMERIE OFFICI\u00c9LLE 7 et 9. cur Trollier . AL"], "label": "PageFooter", "position": 30}]}]